Workbook

Sheet CAPEX CJI3
A1: WBS Element | B1: Document Date | C1: Object | D1: Cost Element | E1: Purchasing Document | F1: Value in Obj. Crcy | G1: Value TranCurr | H1: CO area currency | I1: Transaction Currency | J1: Name | K1: Ref. Fiscal Year | L1: From Period | M1: Cost element descr. | N1: Posting Date
A2: N7941/2507 | B2: 45929 | C2: N7941/2507 | D2: 6190000001 | E2: 4791010474 | F2: 1145 | G2: 1145 | H2: EUR | I2: EUR | J2: SAP BELGIUM NV/Redesign Profitability Model-_30632 | K2: 2025 | L2: 9 | M2: Purch Investment IT | N2: 45929
A3: N7941/2507 | B3: 45950 | C3: N7941/2507 | D3: 6190000001 | E3: 4791010474 | F3: 2290 | G3: 2290 | H3: EUR | I3: EUR | J3: SAP BELGIUM NV/Redesign Profitability Model-_30632 | K3: 2025 | L3: 10 | M3: Purch Investment IT | N3: 45950
A4: N7941/2507 | B4: 45961 | C4: N7941/2507 | D4: 6190000001 | F4: 10950 | G4: 10950 | H4: EUR | I4: EUR | J4: Reclass internal hours from OPEX to Capex | K4: 2025 | L4: 10 | M4: Purch Investment IT | N4: 45961
A5: N7941/2507 | B5: 45991 | C5: N7941/2507 | D5: 6190000001 | F5: 1400 | G5: 1400 | H5: EUR | I5: EUR | J5: Reclass internal hours from OPEX to Capex | K5: 2025 | L5: 11 | M5: Purch Investment IT | N5: 45991
A6: N7941/2507 | B6: 45995 | C6: N7941/2507 | D6: 6190000001 | E6: 4791010474 | F6: 2290 | G6: 2290 | H6: EUR | I6: EUR | J6: SAP BELGIUM NV/Redesign Profitability Model-_30632 | K6: 2025 | L6: 12 | M6: Purch Investment IT | N6: 45995
A7: N7941/2507 | B7: 46005 | C7: N7941/2507 | D7: 6190000001 | E7: 4791010474 | F7: 2290 | G7: 2290 | H7: EUR | I7: EUR | J7: SAP BELGIUM NV/Redesign Profitability Model-_30632 | K7: 2025 | L7: 12 | M7: Purch Investment IT | N7: 46005
A8: N7941/2507 | B8: 46022 | C8: N7941/2507 | D8: 6190000001 | F8: 800 | G8: 800 | H8: EUR | I8: EUR | J8: Reclass internal hours from OPEX to Capex | K8: 2025 | L8: 12 | M8: Purch Investment IT | N8: 46022
A9: N7941/2507 | B9: 46053 | C9: N7941/2507 | D9: 6190000001 | F9: 3300 | G9: 3300 | H9: EUR | I9: EUR | J9: Reclass internal hours from OPEX to Capex | K9: 2026 | L9: 1 | M9: Purch Investment IT | N9: 46053
A10: N7941/2507 | B10: 46081 | C10: N7941/2507 | D10: 6190000001 | F10: 3100 | G10: 3100 | H10: EUR | I10: EUR | J10: Reclass internal hours from OPEX to Capex | K10: 2026 | L10: 2 | M10: Purch Investment IT | N10: 46081
A11: N7941/2507 | B11: 46112 | C11: N7941/2507 | D11: 6190000001 | F11: 1100 | G11: 1100 | H11: EUR | I11: EUR | J11: Reclass internal hours from OPEX to Capex | K11: 2026 | L11: 3 | M11: Purch Investment IT | N11: 46112
A12: N7941/2507 | B12: 46142 | C12: N7941/2507 | D12: 6190000001 | F12: 9400 | G12: 9400 | H12: EUR | I12: EUR | J12: Reclass internal hours from OPEX to Capex | K12: 2026 | L12: 4 | M12: Purch Investment IT | N12: 46142
A13: N7941/2507 | B13: 46173 | C13: N7941/2507 | D13: 6190000001 | F13: 3400 | G13: 3400 | H13: EUR | I13: EUR | J13: Reclass internal hours from OPEX to Capex | K13: 2026 | L13: 5 | M13: Purch Investment IT | N13: 46173
A14: N7941/2507 | B14: 46203 | C14: N7941/2507 | D14: 6190000001 | F14: 6175.28 | G14: 6175.28 | H14: EUR | I14: EUR | J14: Reclass internal hours from OPEX to Capex | K14: 2026 | L14: 6 | M14: Purch Investment IT | N14: 46203
A15: N7941/2507 | B15: 46219 | C15: N7941/2507 | D15: 6190000001 | E15: 4791010474 | F15: 2290 | G15: 2290 | H15: EUR | I15: EUR | J15: SAP BELGIUM N/Redesign Profitability Model-_306324 | K15: 2026 | L15: 7 | M15: Purch Investment IT | N15: 46219
A16: N7941/2507 | B16: 46234 | C16: N7941/2507 | D16: 6190000001 | F16: 3774.72 | G16: 3774.72 | H16: EUR | I16: EUR | J16: Reclass internal hours from OPEX to Capex | K16: 2026 | L16: 7 | M16: Purch Investment IT | N16: 46234
A17: N7941/2507 | B17: 46265 | C17: N7941/2507 | D17: 6190000001 | F17: 14668 | G17: 14668 | H17: EUR | I17: EUR | J17: Reclass internal hours from OPEX to Capex | K17: 2026 | L17: 8 | M17: Purch Investment IT | N17: 46265
A18: N7941/2507 | F18: 68373 | G18: 68373 | I18: EUR
A19: O6300/2603 | B19: 46239 | C19: O6300/2603 | D19: 6190000001 | E19: 4631069083 | F19: 571.85 | G19: 571.85 | H19: EUR | I19: EUR | J19: COMPUTACENTER NV/FortiGate switch controller | K19: 2026 | L19: 8 | M19: Purch Investment IT | N19: 46258
A20: O6300/2603 | F20: 571.85 | G20: 571.85 | I20: EUR
A21: O7941/2513 | B21: 45961 | C21: O7941/2513 | D21: 6190000001 | F21: 3800 | G21: 3800 | H21: EUR | I21: EUR | J21: Reclass internal hours from OPEX to Capex | K21: 2025 | L21: 10 | M21: Purch Investment IT | N21: 45961
A22: O7941/2513 | B22: 45991 | C22: O7941/2513 | D22: 6190000001 | F22: 1500 | G22: 1500 | H22: EUR | I22: EUR | J22: Reclass internal hours from OPEX to Capex | K22: 2025 | L22: 11 | M22: Purch Investment IT | N22: 45991
A23: O7941/2513 | B23: 45993 | C23: O7941/2513 | D23: 6190000001 | E23: 4791010526 | F23: 60000 | G23: 60000 | H23: EUR | I23: EUR | J23: PLANISWARE BELGIUM SRL/2025-Symphony implementatio | K23: 2025 | L23: 12 | M23: Purch Investment IT | N23: 45993
A24: O7941/2513 | B24: 45993 | C24: O7941/2513 | D24: 6190000001 | E24: 4791010526 | F24: 15000 | G24: 15000 | H24: EUR | I24: EUR | J24: PLANISWARE BELGIUM SRL/2025-licences | K24: 2025 | L24: 12 | M24: Purch Investment IT | N24: 45993
A25: O7941/2513 | B25: 46006 | C25: O7941/2513 | D25: 6190000001 | E25: 4791010526 | F25: 40000 | G25: 40000 | H25: EUR | I25: EUR | J25: PLANISWARE BELGIUM SRL/2025-Symphony implementatio | K25: 2025 | L25: 12 | M25: Purch Investment IT | N25: 46006
A26: O7941/2513 | B26: 46006 | C26: O7941/2513 | D26: 6190000001 | E26: 4791010606 | F26: 11760 | G26: 11760 | H26: EUR | I26: EUR | J26: TEAM4P/2025 implementation of Planisware softw | K26: 2025 | L26: 12 | M26: Purch Investment IT | N26: 46006
A27: O7941/2513 | B27: 46006 | C27: O7941/2513 | D27: 6190000001 | E27: 4791010526 | F27: 1687.8 | G27: 1687.8 | H27: EUR | I27: EUR | J27: PLANISWARE BELGIUM SRL/2025-essential travel | K27: 2025 | L27: 12 | M27: Purch Investment IT | N27: 46006
A28: O7941/2513 | B28: 46022 | C28: O7941/2513 | D28: 7405000000 | F28: 17548 | G28: 17548 | H28: EUR | I28: EUR | J28: 7941 - Engineering - Symphony Project | K28: 2025 | L28: 12 | M28: IC-Technical assistance & man fees | N28: 46022
A29: O7941/2513 | B29: 46022 | C29: O7941/2513 | D29: 6190000001 | F29: 12700 | G29: 12700 | H29: EUR | I29: EUR | J29: Reclass internal hours from OPEX to Capex | K29: 2025 | L29: 12 | M29: Purch Investment IT | N29: 46022
A30: O7941/2513 | B30: 46022 | C30: O7941/2513 | D30: 6405000000 | F30: 17548 | G30: 17548 | H30: EUR | I30: EUR | J30: 7941 - Engineering - Symphony Project | K30: 2025 | L30: 12 | M30: IC Oth oper chgs Tech assist & man fees | N30: 46022
A31: O7941/2513 | B31: 46053 | C31: O7941/2513 | D31: 7405000000 | F31: 26475 | G31: 26475 | H31: EUR | I31: EUR | J31: 7941 - Engineering - Symphony Project | K31: 2026 | L31: 1 | M31: IC-Technical assistance & man fees | N31: 46053
A32: O7941/2513 | B32: 46053 | C32: O7941/2513 | D32: 7405000000 | F32: 2675 | G32: 2675 | H32: EUR | I32: EUR | J32: 7941 - Engineering - Symphony Project | K32: 2026 | L32: 1 | M32: IC-Technical assistance & man fees | N32: 46053
A33: O7941/2513 | B33: 46053 | C33: O7941/2513 | D33: 6190000001 | F33: 1800 | G33: 1800 | H33: EUR | I33: EUR | J33: Reclass internal hours from OPEX to Capex | K33: 2026 | L33: 1 | M33: Purch Investment IT | N33: 46053
A34: O7941/2513 | B34: 46053 | C34: O7941/2513 | D34: 6190000001 | F34: 2675 | G34: 2675 | H34: EUR | I34: EUR | J34: Reclass | K34: 2026 | L34: 1 | M34: Purch Investment IT | N34: 46053
A35: O7941/2513 | B35: 46063 | C35: O7941/2513 | D35: 6190000001 | E35: 4791010606 | F35: 3570 | G35: 3570 | H35: EUR | I35: EUR | J35: TEAM4P/2026 implementation of Planisware softw | K35: 2026 | L35: 2 | M35: Purch Investment IT | N35: 46063
A36: O7941/2513 | B36: 46066 | C36: O7941/2513 | D36: 7405000000 | F36: 7543.5 | G36: 7543.5 | H36: EUR | I36: EUR | J36: 7941 - Engineering - Symphony Project | K36: 2026 | L36: 2 | M36: IC-Technical assistance & man fees | N36: 46066
A37: O7941/2513 | B37: 46081 | C37: O7941/2513 | D37: 6190000001 | F37: 5085 | G37: 5085 | H37: EUR | I37: EUR | J37: Reclass internal hours from OPEX to Capex | K37: 2026 | L37: 2 | M37: Purch Investment IT | N37: 46081
A38: O7941/2513 | B38: 46083 | C38: O7941/2513 | D38: 6190000001 | E38: 4791010606 | F38: 5600 | G38: 5600 | H38: EUR | I38: EUR | J38: TEAM4P/2026 implementation of Planisware softw | K38: 2026 | L38: 3 | M38: Purch Investment IT | N38: 46083
A39: O7941/2513 | B39: 46081 | C39: O7941/2513 | D39: 6190000001 | F39: 7543.5 | G39: 7543.5 | H39: EUR | I39: EUR | J39: Reclass | K39: 2026 | L39: 2 | M39: Purch Investment IT | N39: 46081
A40: O7941/2513 | B40: 46092 | C40: O7941/2513 | D40: 6190000001 | E40: 4791010688 | F40: 15000 | G40: 15000 | H40: EUR | I40: EUR | J40: PLANISWARE BELGIUM SRL/2026-symphony licences | K40: 2026 | L40: 3 | M40: Purch Investment IT | N40: 46092
A41: O7941/2513 | B41: 46092 | C41: O7941/2513 | D41: 6190000001 | E41: 4791010688 | F41: 40000 | G41: 40000 | H41: EUR | I41: EUR | J41: PLANISWARE BELGIUM SRL/2026-symphony implementatio | K41: 2026 | L41: 3 | M41: Purch Investment IT | N41: 46092
A42: O7941/2513 | B42: 46092 | C42: O7941/2513 | D42: 6190000001 | E42: 4791010688 | F42: 382.98 | G42: 382.98 | H42: EUR | I42: EUR | J42: PLANISWARE BELGIUM SRL/2026-essential travel | K42: 2026 | L42: 3 | M42: Purch Investment IT | N42: 46092
A43: O7941/2513 | B43: 46082 | C43: O7941/2513 | D43: 7405000000 | F43: 17708.5 | G43: 17708.5 | H43: EUR | I43: EUR | J43: 7941 - Engineering - Symphony Project | K43: 2026 | L43: 3 | M43: IC-Technical assistance & man fees | N43: 46082
A44: O7941/2513 | B44: 46097 | C44: O7941/2513 | D44: 6190000001 | E44: 4791010688 | F44: 40000 | G44: 40000 | H44: EUR | I44: EUR | J44: PLANISWARE BELGIUM SRL/2026-symphony implementatio | K44: 2026 | L44: 3 | M44: Purch Investment IT | N44: 46097
A45: O7941/2513 | B45: 46097 | C45: O7941/2513 | D45: 6190000001 | E45: 4791010688 | F45: 343.2 | G45: 343.2 | H45: EUR | I45: EUR | J45: PLANISWARE BELGIUM SRL/2026-essential travel | K45: 2026 | L45: 3 | M45: Purch Investment IT | N45: 46097
A46: O7941/2513 | B46: 46112 | C46: O7941/2513 | D46: 6190000001 | F46: 10105 | G46: 10105 | H46: EUR | I46: EUR | J46: Reclass internal hours from OPEX to Capex | K46: 2026 | L46: 3 | M46: Purch Investment IT | N46: 46112
A47: O7941/2513 | B47: 46114 | C47: O7941/2513 | D47: 6190000001 | E47: 4791010606 | F47: 6090 | G47: 6090 | H47: EUR | I47: EUR | J47: TEAM4P/2026 implementation of Planisware softw | K47: 2026 | L47: 4 | M47: Purch Investment IT | N47: 46114
A48: O7941/2513 | B48: 46112 | C48: O7941/2513 | D48: 6190000001 | F48: 343.2 | G48: 343.2 | H48: EUR | I48: EUR | J48: WBS Correction | K48: 2026 | L48: 3 | M48: Purch Investment IT | N48: 46112
A49: O7941/2513 | B49: 46112 | C49: O7941/2513 | D49: 6190000001 | F49: 382.98 | G49: 382.98 | H49: EUR | I49: EUR | J49: WBS Correction | K49: 2026 | L49: 3 | M49: Purch Investment IT | N49: 46112
A50: O7941/2513 | B50: 46112 | C50: O7941/2513 | D50: 6190000001 | F50: 5600 | G50: 5600 | H50: EUR | I50: EUR | J50: WBS Correction | K50: 2026 | L50: 3 | M50: Purch Investment IT | N50: 46112
A51: O7941/2513 | B51: 46112 | C51: O7941/2513 | D51: 6190000001 | F51: 10105 | G51: 10105 | H51: EUR | I51: EUR | J51: WBS Correction | K51: 2026 | L51: 3 | M51: Purch Investment IT | N51: 46112
A52: O7941/2513 | B52: 46112 | C52: O7941/2513 | D52: 6190000001 | F52: 15000 | G52: 15000 | H52: EUR | I52: EUR | J52: WBS Correction | K52: 2026 | L52: 3 | M52: Purch Investment IT | N52: 46112
A53: O7941/2513 | B53: 46112 | C53: O7941/2513 | D53: 6190000001 | F53: 40000 | G53: 40000 | H53: EUR | I53: EUR | J53: WBS Correction | K53: 2026 | L53: 3 | M53: Purch Investment IT | N53: 46112
A54: O7941/2513 | B54: 46112 | C54: O7941/2513 | D54: 6190000001 | F54: 40000 | G54: 40000 | H54: EUR | I54: EUR | J54: WBS Correction | K54: 2026 | L54: 3 | M54: Purch Investment IT | N54: 46112
A55: O7941/2513 | B55: 46112 | C55: O7941/2513 | D55: 7405000000 | F55: 343.2 | G55: 343.2 | H55: EUR | I55: EUR | J55: WBS Correction | K55: 2026 | L55: 3 | M55: IC-Technical assistance & man fees | N55: 46112
A56: O7941/2513 | B56: 46112 | C56: O7941/2513 | D56: 7405000000 | F56: 382.98 | G56: 382.98 | H56: EUR | I56: EUR | J56: WBS Correction | K56: 2026 | L56: 3 | M56: IC-Technical assistance & man fees | N56: 46112
A57: O7941/2513 | B57: 46112 | C57: O7941/2513 | D57: 7405000000 | F57: 5600 | G57: 5600 | H57: EUR | I57: EUR | J57: WBS Correction | K57: 2026 | L57: 3 | M57: IC-Technical assistance & man fees | N57: 46112
A58: O7941/2513 | B58: 46112 | C58: O7941/2513 | D58: 7405000000 | F58: 10105 | G58: 10105 | H58: EUR | I58: EUR | J58: WBS Correction | K58: 2026 | L58: 3 | M58: IC-Technical assistance & man fees | N58: 46112
A59: O7941/2513 | B59: 46112 | C59: O7941/2513 | D59: 7405000000 | F59: 15000 | G59: 15000 | H59: EUR | I59: EUR | J59: WBS Correction | K59: 2026 | L59: 3 | M59: IC-Technical assistance & man fees | N59: 46112
... A77: O7941/2513 | B77: 46142 | C77: O7941/2513 | D77: 7405000000 | F77: 17922.5 | G77: 17922.5 | H77: EUR | I77: EUR | J77: 7941 - Engineering - Symphony Project | K77: 2026 | L77: 4 | M77: IC-Technical assistance & man fees | N77: 46142
A78: O7941/2513 | B78: 46132 | C78: O7941/2513 | D78: 6190000001 | E78: 4791010688 | F78: 20000 | G78: 20000 | H78: EUR | I78: EUR | J78: PLANISWARE BELGIUM SRL/2026-symphony implementatio | K78: 2026 | L78: 4 | M78: Purch Investment IT | N78: 46132
A79: O7941/2513 | B79: 46132 | C79: O7941/2513 | D79: 6190000001 | E79: 4791010688 | F79: 648.48 | G79: 648.48 | H79: EUR | I79: EUR | J79: PLANISWARE BELGIUM SRL/2026-essential travel | K79: 2026 | L79: 4 | M79: Purch Investment IT | N79: 46132
A80: O7941/2513 | B80: 46142 | C80: O7941/2513 | D80: 6190000001 | F80: 17922.5 | G80: 17922.5 | H80: EUR | I80: EUR | J80: Reclass: WBS Correction | K80: 2026 | L80: 4 | M80: Purch Investment IT | N80: 46142
A81: O7941/2513 | B81: 46142 | C81: O7941/2513 | D81: 6190000001 | F81: 4700 | G81: 4700 | H81: EUR | I81: EUR | J81: Reclass internal hours from OPEX to Capex | K81: 2026 | L81: 4 | M81: Purch Investment IT | N81: 46142
A82: O7941/2513 | B82: 46146 | C82: O7941/2513 | D82: 6190000001 | E82: 4791010606 | F82: 2800 | G82: 2800 | H82: EUR | I82: EUR | J82: TEAM4P/2026 implementation of Planisware softw | K82: 2026 | L82: 5 | M82: Purch Investment IT | N82: 46146
A83: O7941/2513 | B83: 46150 | C83: O7941/2513 | D83: 6190000001 | E83: 4791010688 | F83: 413.49 | G83: 413.49 | H83: EUR | I83: EUR | J83: PLANISWARE BELGIUM SRL/2026-essential travel | K83: 2026 | L83: 5 | M83: Purch Investment IT | N83: 46150
A84: O7941/2513 | B84: 46153 | C84: O7941/2513 | D84: 6190000001 | E84: 4791010791 | F84: 20000 | G84: 20000 | H84: EUR | I84: EUR | J84: PLANISWARE BELGIUM SR/2026-Additional Scope releas | K84: 2026 | L84: 5 | M84: Purch Investment IT | N84: 46153
A85: O7941/2513 | B85: 46173 | C85: O7941/2513 | D85: 7405000000 | F85: 8667 | G85: 8667 | H85: EUR | I85: EUR | J85: 7941 - Engineering - Symphony Project | K85: 2026 | L85: 5 | M85: IC-Technical assistance & man fees | N85: 46173
A86: O7941/2513 | B86: 46173 | C86: O7941/2513 | D86: 6190000001 | F86: 9000 | G86: 9000 | H86: EUR | I86: EUR | J86: Reclass internal hours from OPEX to Capex | K86: 2026 | L86: 5 | M86: Purch Investment IT | N86: 46173
A87: O7941/2513 | B87: 46174 | C87: O7941/2513 | D87: 6190000001 | E87: 4791010606 | F87: 2520 | G87: 2520 | H87: EUR | I87: EUR | J87: TEAM4P/2026 implementation of Planisware softw | K87: 2026 | L87: 6 | M87: Purch Investment IT | N87: 46174
A88: O7941/2513 | B88: 46173 | C88: O7941/2513 | D88: 6190000001 | F88: 8667 | G88: 8667 | H88: EUR | I88: EUR | J88: Reclass: WBS Correction | K88: 2026 | L88: 5 | M88: Purch Investment IT | N88: 46173
A89: O7941/2513 | B89: 46203 | C89: O7941/2513 | D89: 7405000000 | F89: 9737 | G89: 9737 | H89: EUR | I89: EUR | J89: 7941 - Engineering - Symphony Project | K89: 2026 | L89: 6 | M89: IC-Technical assistance & man fees | N89: 46203
A90: O7941/2513 | B90: 46198 | C90: O7941/2513 | D90: 6190000001 | E90: 4791010791 | F90: 23062.5 | G90: 23062.5 | H90: EUR | I90: EUR | J90: PLANISWARE BELGIUM SR/2026-Additional Scope releas | K90: 2026 | L90: 6 | M90: Purch Investment IT | N90: 46198
A91: O7941/2513 | B91: 46203 | C91: O7941/2513 | D91: 6190000001 | F91: 18000 | G91: 18000 | H91: EUR | I91: EUR | J91: Reclass internal hours from OPEX to Capex | K91: 2026 | L91: 6 | M91: Purch Investment IT | N91: 46203
A92: O7941/2513 | B92: 46205 | C92: O7941/2513 | D92: 6190000001 | E92: 4791010606 | F92: 5059.4 | G92: 5059.4 | H92: EUR | I92: EUR | J92: TEAM4P/2026 implementation of Planisware softw | K92: 2026 | L92: 7 | M92: Purch Investment IT | N92: 46205
A93: O7941/2513 | B93: 46203 | C93: O7941/2513 | D93: 6190000001 | F93: 9737 | G93: 9737 | H93: EUR | I93: EUR | J93: Reclass: WBS Correction | K93: 2026 | L93: 6 | M93: Purch Investment IT | N93: 46203
A94: O7941/2513 | B94: 46234 | C94: O7941/2513 | D94: 7405000000 | F94: 12840 | G94: 12840 | H94: EUR | I94: EUR | J94: Symphony Project - Etex Engineering Fees | K94: 2026 | L94: 7 | M94: IC-Technical assistance & man fees | N94: 46234
A95: O7941/2513 | B95: 46238 | C95: O7941/2513 | D95: 6190000001 | E95: 4791010606 | F95: 560 | G95: 560 | H95: EUR | I95: EUR | J95: TEAM4P/2026 implementation of Planisware softw | K95: 2026 | L95: 8 | M95: Purch Investment IT | N95: 46238
A96: O7941/2513 | B96: 46234 | C96: O7941/2513 | D96: 6190000001 | F96: 12840 | G96: 12840 | H96: EUR | I96: EUR | J96: Reclass: WBS Correction | K96: 2026 | L96: 7 | M96: Purch Investment IT | N96: 46234
A97: O7941/2513 | B97: 46265 | C97: O7941/2513 | D97: 7405000000 | F97: 16906 | G97: 16906 | H97: EUR | I97: EUR | J97: 7941 - Symphony Project - Etex Engineering Fees | K97: 2026 | L97: 8 | M97: IC-Technical assistance & man fees | N97: 46265
A98: O7941/2513 | B98: 46265 | C98: O7941/2513 | D98: 6190000001 | F98: 16906 | G98: 16906 | H98: EUR | I98: EUR | J98: Reclass: WBS Correction | K98: 2026 | L98: 8 | M98: Purch Investment IT | N98: 46265
A99: O7941/2513 | B99: 46269 | C99: O7941/2513 | D99: 6190000001 | E99: 4791010606 | F99: 2030 | G99: 2030 | H99: EUR | I99: EUR | J99: TEAM4P/2026 implementation of Planisware softw | K99: 2026 | L99: 9 | M99: Purch Investment IT | N99: 46269
A100: O7941/2513 | F100: 1078512.6 | G100: 1078512.6 | I100: EUR
A101: O7941/2517 | B101: 45962 | C101: O7941/2517 | D101: 6113000040 | F101: 27762 | G101: 27762 | H101: EUR | I101: EUR | J101: Tagetik Subscription | K101: 2025 | L101: 11 | M101: Maintenance contracts Equipments | N101: 45962
A102: O7941/2517 | B102: 45986 | C102: O7941/2517 | D102: 6113000040 | F102: 61250 | G102: 61250 | H102: EUR | I102: EUR | J102: Tagetik Subscription | K102: 2025 | L102: 11 | M102: Maintenance contracts Equipments | N102: 45986
A103: O7941/2517 | B103: 45991 | C103: O7941/2517 | D103: 6190000001 | F103: 2100 | G103: 2100 | H103: EUR | I103: EUR | J103: Reclass internal hours from OPEX to Capex | K103: 2025 | L103: 11 | M103: Purch Investment IT | N103: 45991
A104: O7941/2517 | B104: 46006 | C104: O7941/2517 | D104: 6190000001 | E104: 4791010583 | F104: 32137.88 | G104: 32137.88 | H104: EUR | I104: EUR | J104: ERNST & YOUNG CONSULTI/Tacos - CCH Tagetik impleme | K104: 2025 | L104: 12 | M104: Purch Investment IT | N104: 46006
A105: O7941/2517 | B105: 46013 | C105: O7941/2517 | D105: 6190000001 | E105: 4791010583 | F105: 21000 | G105: 21000 | H105: EUR | I105: EUR | J105: ERNST & YOUNG CONSULTI/Tacos - CCH Tagetik impleme | K105: 2025 | L105: 12 | M105: Purch Investment IT | N105: 46013
A106: O7941/2517 | B106: 46022 | C106: O7941/2517 | D106: 6190000001 | F106: 800 | G106: 800 | H106: EUR | I106: EUR | J106: Reclass internal hours from OPEX to Capex | K106: 2025 | L106: 12 | M106: Purch Investment IT | N106: 46022
A107: O7941/2517 | B107: 46015 | C107: O7941/2517 | D107: 6190000001 | E107: 4791010583 | F107: 17444.7 | G107: 17444.7 | H107: EUR | I107: EUR | J107: ERNST & YOUNG CONSULTI/Tacos - CCH Tagetik impleme | K107: 2025 | L107: 12 | M107: Purch Investment IT | N107: 46015
A108: O7941/2517 | B108: 46015 | C108: O7941/2517 | D108: 6190000001 | E108: 4791010583 | F108: 29417.42 | G108: 29417.42 | H108: EUR | I108: EUR | J108: ERNST & YOUNG CONSULTI/Tacos - CCH Tagetik impleme | K108: 2025 | L108: 12 | M108: Purch Investment IT | N108: 46015
A109: O7941/2517 | B109: 46021 | C109: O7941/2517 | D109: 6190000001 | E109: 4791010583 | F109: 21088 | G109: 21088 | H109: EUR | I109: EUR | J109: ERNST & YOUNG CONSULTI/Tacos - CCH Tagetik impleme | K109: 2025 | L109: 12 | M109: Purch Investment IT | N109: 46021
A110: O7941/2517 | B110: 46112 | C110: O7941/2517 | D110: 6190000001 | F110: 13100 | G110: 13100 | H110: EUR | I110: EUR | J110: Reclass internal hours from OPEX to Capex | K110: 2026 | L110: 3 | M110: Purch Investment IT | N110: 46112
A111: O7941/2517 | B111: 46121 | C111: O7941/2517 | D111: 6190000001 | E111: 4791010583 | F111: 28044.84 | G111: 28044.84 | H111: EUR | I111: EUR | J111: ERNST & YOUNG CONSUL/2026 Tacos - CCH Tagetik impl | K111: 2026 | L111: 4 | M111: Purch Investment IT | N111: 46121
A112: O7941/2517 | B112: 46122 | C112: O7941/2517 | D112: 6190000001 | F112: 10416.67 | G112: 10416.67 | H112: EUR | I112: EUR | J112: 703 finance 04.2026 | K112: 2026 | L112: 4 | M112: Purch Investment IT | N112: 46122
A113: O7941/2517 | B113: 46134 | C113: O7941/2517 | D113: 6190000001 | E113: 4791010583 | F113: 38719.41 | G113: 38719.41 | H113: EUR | I113: EUR | J113: ERNST & YOUNG CONSUL/2026 Tacos - CCH Tagetik impl | K113: 2026 | L113: 4 | M113: Purch Investment IT | N113: 46134
A114: O7941/2517 | B114: 46122 | C114: O7941/2517 | D114: 6190000001 | F114: 20833.34 | G114: 20833.34 | H114: EUR | I114: EUR | J114: 703 finance 01-02.2026 | K114: 2026 | L114: 4 | M114: Purch Investment IT | N114: 46122
A115: O7941/2517 | B115: 46092 | C115: O7941/2517 | D115: 6190000001 | F115: 10416.67 | G115: 10416.67 | H115: EUR | I115: EUR | J115: 703 finance 03.2026 | K115: 2026 | L115: 4 | M115: Purch Investment IT | N115: 46122
A116: O7941/2517 | B116: 46142 | C116: O7941/2517 | D116: 6190000001 | F116: 3600 | G116: 3600 | H116: EUR | I116: EUR | J116: Reclass internal hours from OPEX to Capex | K116: 2026 | L116: 4 | M116: Purch Investment IT | N116: 46142
A117: O7941/2517 | B117: 46152 | C117: O7941/2517 | D117: 6190000001 | F117: 10416.67 | G117: 10416.67 | H117: EUR | I117: EUR | J117: 703 finance 05.2026 | K117: 2026 | L117: 5 | M117: Purch Investment IT | N117: 46152
...

Sheet OPEX CJI3
A1: WBS Element | B1: Document Date | C1: Object | D1: Cost Element | E1: Purchasing Document | F1: Value in Obj. Crcy | G1: Value TranCurr | H1: CO area currency | I1: Transaction Currency | J1: Name | K1: Ref. Fiscal Year | L1: From Period | M1: Cost element descr. | N1: Posting Date
A2: C7941/1896/1 | B2: 45447 | C2: C7941/1896/1 | D2: 7405000000 | F2: 30000 | G2: 30000 | H2: EUR | I2: EUR | L2: 5 | M2: IC-Technical assistance & man fees | N2: 45443
A3: C7941/1896/1 | B3: 45432 | C3: C7941/1896/1 | D3: 7405000000 | F3: -30000 | G3: -30000 | H3: EUR | I3: EUR | K3: 2024 | L3: 5 | M3: IC-Technical assistance & man fees | N3: 45432
A4: Period 5 | F4: 0 | G4: 0 | I4: EUR
A5: C7941/1896/1 | B5: 45475 | C5: C7941/1896/1 | D5: 7405000000 | F5: 30000 | G5: 30000 | H5: EUR | I5: EUR | L5: 6 | M5: IC-Technical assistance & man fees | N5: 45473
A6: C7941/1896/1 | B6: 45462 | C6: C7941/1896/1 | D6: 7405000000 | F6: -8000 | G6: -8000 | H6: EUR | I6: EUR | K6: 2024 | L6: 6 | M6: IC-Technical assistance & man fees | N6: 45462
A7: C7941/1896/1 | B7: 45462 | C7: C7941/1896/1 | D7: 7405000000 | F7: -22000 | G7: -22000 | H7: EUR | I7: EUR | K7: 2024 | L7: 6 | M7: IC-Technical assistance & man fees | N7: 45462
A8: Period 6 | F8: 0 | G8: 0 | I8: EUR
A9: C7941/1896/1 | B9: 45264 | C9: C7941/1896/1 | D9: 7405000000 | F9: 17000 | G9: 17000 | H9: EUR | I9: EUR | L9: 11 | M9: IC-Technical assistance & man fees | N9: 45260
A10: C7941/1896/1 | B10: 45247 | C10: C7941/1896/1 | D10: 7405000000 | F10: -17000 | G10: -17000 | H10: EUR | I10: EUR | K10: 2023 | L10: 11 | M10: IC-Technical assistance & man fees | N10: 45247
A11: Period 11 | F11: 0 | G11: 0 | I11: EUR
A12: C7941/1896/1 | B12: 44930 | C12: C7941/1896/1 | D12: 7405000000 | F12: 68000 | G12: 68000 | H12: EUR | I12: EUR | L12: 12 | M12: IC-Technical assistance & man fees | N12: 44926
A13: C7941/1896/1 | B13: 45295 | C13: C7941/1896/1 | D13: 7405000000 | F13: 34000 | G13: 34000 | H13: EUR | I13: EUR | L13: 12 | M13: IC-Technical assistance & man fees | N13: 45291
A14: C7941/1896/1 | B14: 44914 | C14: C7941/1896/1 | D14: 7405000000 | F14: -17000 | G14: -17000 | H14: EUR | I14: EUR | K14: 2022 | L14: 12 | M14: IC-Technical assistance & man fees | N14: 44914
A15: C7941/1896/1 | B15: 44914 | C15: C7941/1896/1 | D15: 7405000000 | F15: -17000 | G15: -17000 | H15: EUR | I15: EUR | K15: 2022 | L15: 12 | M15: IC-Technical assistance & man fees | N15: 44914
A16: C7941/1896/1 | B16: 44915 | C16: C7941/1896/1 | D16: 7405000000 | F16: -17000 | G16: -17000 | H16: EUR | I16: EUR | K16: 2022 | L16: 12 | M16: IC-Technical assistance & man fees | N16: 44915
A17: C7941/1896/1 | B17: 44915 | C17: C7941/1896/1 | D17: 7405000000 | F17: -17000 | G17: -17000 | H17: EUR | I17: EUR | K17: 2022 | L17: 12 | M17: IC-Technical assistance & man fees | N17: 44915
A18: C7941/1896/1 | B18: 45271 | C18: C7941/1896/1 | D18: 7405000000 | F18: -17000 | G18: -17000 | H18: EUR | I18: EUR | K18: 2023 | L18: 12 | M18: IC-Technical assistance & man fees | N18: 45271
A19: C7941/1896/1 | B19: 45271 | C19: C7941/1896/1 | D19: 7405000000 | F19: -17000 | G19: -17000 | H19: EUR | I19: EUR | K19: 2023 | L19: 12 | M19: IC-Technical assistance & man fees | N19: 45271
A20: Period 12 | F20: 0 | G20: 0 | I20: EUR
A21: C7941/1896/1 | F21: 0 | G21: 0 | I21: EUR
A22: C7941/1896/2/1 | B22: 44596 | C22: C7941/1896/2/1 | D22: 6133000035 | F22: -1500 | G22: -1500 | H22: EUR | I22: EUR | L22: 1 | M22: Service IT | N22: 44592
A23: C7941/1896/2/1 | B23: 44960 | C23: C7941/1896/2/1 | D23: 6133000035 | F23: -2900 | G23: -2900 | H23: EUR | I23: EUR | L23: 1 | M23: Service IT | N23: 44957
A24: C7941/1896/2/1 | B24: 45324 | C24: C7941/1896/2/1 | D24: 6133000035 | F24: -200 | G24: -200 | H24: EUR | I24: EUR | L24: 1 | M24: Service IT | N24: 45322
A25: C7941/1896/2/1 | B25: 44561 | C25: C7941/1896/2/1 | D25: 6133000035 | F25: -400 | G25: -400 | H25: EUR | I25: EUR | J25: App Mandays Dec 2021 | K25: 2022 | L25: 1 | M25: Service IT | N25: 44562
A26: C7941/1896/2/1 | B26: 44592 | C26: C7941/1896/2/1 | D26: 6133000035 | F26: 1900 | G26: 1900 | H26: EUR | I26: EUR | J26: App Mandays Jan 2022 | K26: 2022 | L26: 1 | M26: Service IT | N26: 44592
A27: C7941/1896/2/1 | B27: 44957 | C27: C7941/1896/2/1 | D27: 6133000035 | F27: 2900 | G27: 2900 | H27: EUR | I27: EUR | J27: App Mandays Jan 2023 | K27: 2023 | L27: 1 | M27: Service IT | N27: 44957
A28: C7941/1896/2/1 | B28: 45322 | C28: C7941/1896/2/1 | D28: 6133000035 | F28: 200 | G28: 200 | H28: EUR | I28: EUR | J28: IT Business Solutions Mandays Jan 2024 | K28: 2024 | L28: 1 | M28: Service IT | N28: 45322
A29: Period 1 | F29: 0 | G29: 0 | I29: EUR
A30: C7941/1896/2/1 | B30: 44623 | C30: C7941/1896/2/1 | D30: 6133000035 | F30: -3800 | G30: -3800 | H30: EUR | I30: EUR | L30: 2 | M30: Service IT | N30: 44620
A31: C7941/1896/2/1 | B31: 44988 | C31: C7941/1896/2/1 | D31: 6133000035 | F31: -1600 | G31: -1600 | H31: EUR | I31: EUR | L31: 2 | M31: Service IT | N31: 44985
A32: C7941/1896/2/1 | B32: 45356 | C32: C7941/1896/2/1 | D32: 6133000035 | F32: -9500 | G32: -9500 | H32: EUR | I32: EUR | L32: 2 | M32: Service IT | N32: 45351
A33: C7941/1896/2/1 | B33: 44592 | C33: C7941/1896/2/1 | D33: 6133000035 | F33: -1900 | G33: -1900 | H33: EUR | I33: EUR | J33: App Mandays Jan 2022 | K33: 2022 | L33: 2 | M33: Service IT | N33: 44593
A34: C7941/1896/2/1 | B34: 44620 | C34: C7941/1896/2/1 | D34: 6133000035 | F34: 5100 | G34: 5100 | H34: EUR | I34: EUR | J34: App Mandays Feb 2022 | K34: 2022 | L34: 2 | M34: Service IT | N34: 44620
A35: C7941/1896/2/1 | B35: 44620 | C35: C7941/1896/2/1 | D35: 6133000035 | F35: 600 | G35: 600 | H35: EUR | I35: EUR | J35: Techn Mandays Feb 2022 | K35: 2022 | L35: 2 | M35: Service IT | N35: 44620
A36: C7941/1896/2/1 | B36: 44957 | C36: C7941/1896/2/1 | D36: 6133000035 | F36: -2900 | G36: -2900 | H36: EUR | I36: EUR | J36: App Mandays Jan 2023 | K36: 2023 | L36: 2 | M36: Service IT | N36: 44958
A37: C7941/1896/2/1 | B37: 44985 | C37: C7941/1896/2/1 | D37: 6133000035 | F37: 4500 | G37: 4500 | H37: EUR | I37: EUR | J37: App Mandays Feb 2023 | K37: 2023 | L37: 2 | M37: Service IT | N37: 44985
A38: C7941/1896/2/1 | B38: 45322 | C38: C7941/1896/2/1 | D38: 6133000035 | F38: -200 | G38: -200 | H38: EUR | I38: EUR | J38: IT Business Solutions Mandays Jan 2024 | K38: 2024 | L38: 2 | M38: Service IT | N38: 45323
A39: C7941/1896/2/1 | B39: 45351 | C39: C7941/1896/2/1 | D39: 6133000035 | F39: 9700 | G39: 9700 | H39: EUR | I39: EUR | J39: IT Business Solutions Mandays Feb 2024 | K39: 2024 | L39: 2 | M39: Service IT | N39: 45351
A40: Period 2 | F40: 0 | G40: 0 | I40: EUR
A41: C7941/1896/2/1 | B41: 44656 | C41: C7941/1896/2/1 | D41: 6133000035 | F41: -6300 | G41: -6300 | H41: EUR | I41: EUR | L41: 3 | M41: Service IT | N41: 44651
A42: C7941/1896/2/1 | B42: 45020 | C42: C7941/1896/2/1 | D42: 6133000035 | F42: -1300 | G42: -1300 | H42: EUR | I42: EUR | L42: 3 | M42: Service IT | N42: 45016
A43: C7941/1896/2/1 | B43: 45379 | C43: C7941/1896/2/1 | D43: 6133000035 | F43: 9700 | G43: 9700 | H43: EUR | I43: EUR | L43: 3 | M43: Service IT | N43: 45382
A44: C7941/1896/2/1 | B44: 45386 | C44: C7941/1896/2/1 | D44: 6133000035 | F44: -26100 | G44: -26100 | H44: EUR | I44: EUR | L44: 3 | M44: Service IT | N44: 45382
A45: C7941/1896/2/1 | B45: 44620 | C45: C7941/1896/2/1 | D45: 6133000035 | F45: -5100 | G45: -5100 | H45: EUR | I45: EUR | J45: App Mandays Feb 2022 | K45: 2022 | L45: 3 | M45: Service IT | N45: 44621
A46: C7941/1896/2/1 | B46: 44620 | C46: C7941/1896/2/1 | D46: 6133000035 | F46: -600 | G46: -600 | H46: EUR | I46: EUR | J46: Techn Mandays Feb 2022 | K46: 2022 | L46: 3 | M46: Service IT | N46: 44621
A47: C7941/1896/2/1 | B47: 44651 | C47: C7941/1896/2/1 | D47: 6133000035 | F47: 11100 | G47: 11100 | H47: EUR | I47: EUR | J47: App Mandays Mar 2022 | K47: 2022 | L47: 3 | M47: Service IT | N47: 44651
A48: C7941/1896/2/1 | B48: 44651 | C48: C7941/1896/2/1 | D48: 6133000035 | F48: 900 | G48: 900 | H48: EUR | I48: EUR | J48: Techn Mandays Mar 2022 | K48: 2022 | L48: 3 | M48: Service IT | N48: 44651
A49: C7941/1896/2/1 | B49: 44985 | C49: C7941/1896/2/1 | D49: 6133000035 | F49: -4500 | G49: -4500 | H49: EUR | I49: EUR | J49: App Mandays Feb 2023 | K49: 2023 | L49: 3 | M49: Service IT | N49: 44986
A50: C7941/1896/2/1 | B50: 45016 | C50: C7941/1896/2/1 | D50: 6133000035 | F50: 5800 | G50: 5800 | H50: EUR | I50: EUR | J50: App Mandays Mar 2023 | K50: 2023 | L50: 3 | M50: Service IT | N50: 45016
A51: C7941/1896/2/1 | B51: 45351 | C51: C7941/1896/2/1 | D51: 6133000035 | F51: -9700 | G51: -9700 | H51: EUR | I51: EUR | J51: IT Business Solutions Mandays Feb 2024 | K51: 2024 | L51: 3 | M51: Service IT | N51: 45352
A52: C7941/1896/2/1 | B52: 45382 | C52: C7941/1896/2/1 | D52: 6133000035 | F52: 26100 | G52: 26100 | H52: EUR | I52: EUR | J52: IT Business Solutions Mandays Mar 2024 | K52: 2024 | L52: 3 | M52: Service IT | N52: 45382
A53: Period 3 | F53: 0 | G53: 0 | I53: EUR
A54: C7941/1896/2/1 | B54: 44685 | C54: C7941/1896/2/1 | D54: 6133000035 | F54: -4000 | G54: -4000 | H54: EUR | I54: EUR | L54: 4 | M54: Service IT | N54: 44681
A55: C7941/1896/2/1 | B55: 45415 | C55: C7941/1896/2/1 | D55: 6133000035 | F55: -10400 | G55: -10400 | H55: EUR | I55: EUR | L55: 4 | M55: Service IT | N55: 45412
A56: C7941/1896/2/1 | B56: 44651 | C56: C7941/1896/2/1 | D56: 6133000035 | F56: -11100 | G56: -11100 | H56: EUR | I56: EUR | J56: App Mandays Mar 2022 | K56: 2022 | L56: 4 | M56: Service IT | N56: 44652
A57: C7941/1896/2/1 | B57: 44651 | C57: C7941/1896/2/1 | D57: 6133000035 | F57: -900 | G57: -900 | H57: EUR | I57: EUR | J57: Techn Mandays Mar 2022 | K57: 2022 | L57: 4 | M57: Service IT | N57: 44652
A58: C7941/1896/2/1 | B58: 44681 | C58: C7941/1896/2/1 | D58: 6133000035 | F58: 14600 | G58: 14600 | H58: EUR | I58: EUR | J58: App Mandays Apr 2022 | K58: 2022 | L58: 4 | M58: Service IT | N58: 44681
A59: C7941/1896/2/1 | B59: 44681 | C59: C7941/1896/2/1 | D59: 6133000035 | F59: 1400 | G59: 1400 | H59: EUR | I59: EUR | J59: Techn Mandays Apr 2022 | K59: 2022 | L59: 4 | M59: Service IT | N59: 44681
A60: C7941/1896/2/1 | B60: 45016 | C60: C7941/1896/2/1 | D60: 6133000035 | F60: -5800 | G60: -5800 | H60: EUR | I60: EUR | J60: App Mandays Mar 2023 | K60: 2023 | L60: 4 | M60: Service IT | N60: 45017
A61: C7941/1896/2/1 | B61: 45046 | C61: C7941/1896/2/1 | D61: 6133000035 | F61: 5800 | G61: 5800 | H61: EUR | I61: EUR | J61: App Mandays Apr 2023 | K61: 2023 | L61: 4 | M61: Service IT | N61: 45046
A62: C7941/1896/2/1 | B62: 45382 | C62: C7941/1896/2/1 | D62: 6133000035 | F62: -26100 | G62: -26100 | H62: EUR | I62: EUR | J62: IT Business Solutions Mandays Mar 2024 | K62: 2024 | L62: 4 | M62: Service IT | N62: 45383
A63: C7941/1896/2/1 | B63: 45412 | C63: C7941/1896/2/1 | D63: 6133000035 | F63: 36500 | G63: 36500 | H63: EUR | I63: EUR | J63: IT Business Solutions Mandays Apr 2024 | K63: 2024 | L63: 4 | M63: Service IT | N63: 45412
A64: Period 4 | F64: 0 | G64: 0 | I64: EUR
A65: C7941/1896/2/1 | B65: 44715 | C65: C7941/1896/2/1 | D65: 6133000035 | F65: -1800 | G65: -1800 | H65: EUR | I65: EUR | L65: 5 | M65: Service IT | N65: 44712
A66: C7941/1896/2/1 | B66: 45082 | C66: C7941/1896/2/1 | D66: 6133000035 | F66: -4200 | G66: -4200 | H66: EUR | I66: EUR | L66: 5 | M66: Service IT | N66: 45077
A67: C7941/1896/2/1 | B67: 45447 | C67: C7941/1896/2/1 | D67: 6133000035 | F67: -3400 | G67: -3400 | H67: EUR | I67: EUR | L67: 5 | M67: Service IT | N67: 45443
A68: C7941/1896/2/1 | B68: 44681 | C68: C7941/1896/2/1 | D68: 6133000035 | F68: -14600 | G68: -14600 | H68: EUR | I68: EUR | J68: App Mandays Apr 2022 | K68: 2022 | L68: 5 | M68: Service IT | N68: 44682
A69: C7941/1896/2/1 | B69: 44681 | C69: C7941/1896/2/1 | D69: 6133000035 | F69: -1400 | G69: -1400 | H69: EUR | I69: EUR | J69: Techn Mandays Apr 2022 | K69: 2022 | L69: 5 | M69: Service IT | N69: 44682
A70: C7941/1896/2/1 | B70: 44712 | C70: C7941/1896/2/1 | D70: 6133000035 | F70: 16400 | G70: 16400 | H70: EUR | I70: EUR | J70: App Mandays May 2022 | K70: 2022 | L70: 5 | M70: Service IT | N70: 44712
A71: C7941/1896/2/1 | B71: 44712 | C71: C7941/1896/2/1 | D71: 6133000035 | F71: 1400 | G71: 1400 | H71: EUR | I71: EUR | J71: Techn Mandays May 2022 | K71: 2022 | L71: 5 | M71: Service IT | N71: 44712
A72: C7941/1896/2/1 | B72: 45046 | C72: C7941/1896/2/1 | D72: 6133000035 | F72: -5800 | G72: -5800 | H72: EUR | I72: EUR | J72: App Mandays Apr 2023 | K72: 2023 | L72: 5 | M72: Service IT | N72: 45047
A73: C7941/1896/2/1 | B73: 45077 | C73: C7941/1896/2/1 | D73: 6133000035 | F73: 10000 | G73: 10000 | H73: EUR | I73: EUR | J73: App Mandays May 2023 | K73: 2023 | L73: 5 | M73: Service IT | N73: 45077
A74: C7941/1896/2/1 | B74: 45412 | C74: C7941/1896/2/1 | D74: 6133000035 | F74: -36500 | G74: -36500 | H74: EUR | I74: EUR | J74: IT Business Solutions Mandays Apr 2024 | K74: 2024 | L74: 5 | M74: Service IT | N74: 45413
A75: C7941/1896/2/1 | B75: 45443 | C75: C7941/1896/2/1 | D75: 6133000035 | F75: 39900 | G75: 39900 | H75: EUR | I75: EUR | J75: IT Business Solutions Mandays May 2024 | K75: 2024 | L75: 5 | M75: Service IT | N75: 45443
A76: Period 5 | F76: 0 | G76: 0 | I76: EUR
A77: C7941/1896/2/1 | B77: 44747 | C77: C7941/1896/2/1 | D77: 6133000035 | F77: -2600 | G77: -2600 | H77: EUR | I77: EUR | L77: 6 | M77: Service IT | N77: 44742
A78: C7941/1896/2/1 | B78: 45111 | C78: C7941/1896/2/1 | D78: 6133000035 | F78: -600 | G78: -600 | H78: EUR | I78: EUR | L78: 6 | M78: Service IT | N78: 45107
A79: C7941/1896/2/1 | B79: 44712 | C79: C7941/1896/2/1 | D79: 6133000035 | F79: -16400 | G79: -16400 | H79: EUR | I79: EUR | J79: App Mandays May 2022 | K79: 2022 | L79: 6 | M79: Service IT | N79: 44713
A80: C7941/1896/2/1 | B80: 44712 | C80: C7941/1896/2/1 | D80: 6133000035 | F80: -1400 | G80: -1400 | H80: EUR | I80: EUR | J80: Techn Mandays May 2022 | K80: 2022 | L80: 6 | M80: Service IT | N80: 44713
A81: C7941/1896/2/1 | B81: 44742 | C81: C7941/1896/2/1 | D81: 6133000035 | F81: 18700 | G81: 18700 | H81: EUR | I81: EUR | J81: App Mandays Jun 2022 | K81: 2022 | L81: 6 | M81: Service IT | N81: 44742
A82: C7941/1896/2/1 | B82: 44742 | C82: C7941/1896/2/1 | D82: 6133000035 | F82: 1700 | G82: 1700 | H82: EUR | I82: EUR | J82: Techn Mandays Jun 2022 | K82: 2022 | L82: 6 | M82: Service IT | N82: 44742
A83: C7941/1896/2/1 | B83: 45077 | C83: C7941/1896/2/1 | D83: 6133000035 | F83: -10000 | G83: -10000 | H83: EUR | I83: EUR | J83: App Mandays May 2023 | K83: 2023 | L83: 6 | M83: Service IT | N83: 45078
A84: C7941/1896/2/1 | B84: 45107 | C84: C7941/1896/2/1 | D84: 6133000035 | F84: 10600 | G84: 10600 | H84: EUR | I84: EUR | J84: App Mandays June 2023 | K84: 2023 | L84: 6 | M84: Service IT | N84: 45107
A85: C7941/1896/2/1 | B85: 45443 | C85: C7941/1896/2/1 | D85: 6133000035 | F85: -39900 | G85: -39900 | H85: EUR | I85: EUR | J85: IT Business Solutions Mandays May 2024 | K85: 2024 | L85: 6 | M85: Service IT | N85: 45444
A86: C7941/1896/2/1 | B86: 45473 | C86: C7941/1896/2/1 | D86: 6133000035 | F86: 39900 | G86: 39900 | H86: EUR | I86: EUR | J86: IT Business Solutions Mandays June 2024 | K86: 2024 | L86: 6 | M86: Service IT | N86: 45473
A87: Period 6 | F87: 0 | G87: 0 | I87: EUR
A88: C7941/1896/2/1 | B88: 44775 | C88: C7941/1896/2/1 | D88: 6133000035 | F88: -15900 | G88: -15900 | H88: EUR | I88: EUR | L88: 7 | M88: Service IT | N88: 44773
A89: C7941/1896/2/1 | B89: 45140 | C89: C7941/1896/2/1 | D89: 6133000035 | F89: -1600 | G89: -1600 | H89: EUR | I89: EUR | L89: 7 | M89: Service IT | N89: 45138
A90: C7941/1896/2/1 | B90: 45509 | C90: C7941/1896/2/1 | D90: 6133000035 | F90: -4800 | G90: -4800 | H90: EUR | I90: EUR | L90: 7 | M90: Service IT | N90: 45504
A91: C7941/1896/2/1 | B91: 44742 | C91: C7941/1896/2/1 | D91: 6133000035 | F91: -18700 | G91: -18700 | H91: EUR | I91: EUR | J91: App Mandays Jun 2022 | K91: 2022 | L91: 7 | M91: Service IT | N91: 44743
A92: C7941/1896/2/1 | B92: 44742 | C92: C7941/1896/2/1 | D92: 6133000035 | F92: -1700 | G92: -1700 | H92: EUR | I92: EUR | J92: Techn Mandays Jun 2022 | K92: 2022 | L92: 7 | M92: Service IT | N92: 44743
A93: C7941/1896/2/1 | B93: 44773 | C93: C7941/1896/2/1 | D93: 6133000035 | F93: 34600 | G93: 34600 | H93: EUR | I93: EUR | J93: App Mandays Jul 2022 | K93: 2022 | L93: 7 | M93: Service IT | N93: 44773
A94: C7941/1896/2/1 | B94: 44773 | C94: C7941/1896/2/1 | D94: 6133000035 | F94: 1700 | G94: 1700 | H94: EUR | I94: EUR | J94: Techn Mandays Jul 2022 | K94: 2022 | L94: 7 | M94: Service IT | N94: 44773
A95: C7941/1896/2/1 | B95: 45107 | C95: C7941/1896/2/1 | D95: 6133000035 | F95: -10600 | G95: -10600 | H95: EUR | I95: EUR | J95: App Mandays June 2023 | K95: 2023 | L95: 7 | M95: Service IT | N95: 45108
A96: C7941/1896/2/1 | B96: 45138 | C96: C7941/1896/2/1 | D96: 6133000035 | F96: 12200 | G96: 12200 | H96: EUR | I96: EUR | J96: App Mandays July 2023 | K96: 2023 | L96: 7 | M96: Service IT | N96: 45138
A97: C7941/1896/2/1 | B97: 45473 | C97: C7941/1896/2/1 | D97: 6133000035 | F97: -39900 | G97: -39900 | H97: EUR | I97: EUR | J97: IT Business Solutions Mandays June 2024 | K97: 2024 | L97: 7 | M97: Service IT | N97: 45474
A98: C7941/1896/2/1 | B98: 45504 | C98: C7941/1896/2/1 | D98: 6133000035 | F98: 44700 | G98: 44700 | H98: EUR | I98: EUR | J98: IT Business Solutions Mandays July 2024 | K98: 2024 | L98: 7 | M98: Service IT | N98: 45504
A99: Period 7 | F99: 0 | G99: 0 | I99: EUR
A100: C7941/1896/2/1 | B100: 44806 | C100: C7941/1896/2/1 | D100: 6133000035 | F100: -3500 | G100: -3500 | H100: EUR | I100: EUR | L100: 8 | M100: Service IT | N100: 44804
...

Sheet CAPEX Tables
A1: CAPEX Spend Overview
A2: Project and vendor spend from Capex CJI3 | Fiscal years 2025–2026
A3: Classification: Internal Reclass includes descriptions containing ‘Reclass internal hours’; External includes transactions with a Purchasing Document; Other includes remaining non-PO CAPEX postings after excluding WBS-correction transfer rows and duplicate 6405 intercompany entries. For O7941/2513, 7405 charges before the March 2026 correction period are also excluded. Subtotal rows are excluded.
A5: Total Spend | B5: =SUM(CapexProjectSpend[Grand Total]) -> 7830293.7 | D5: Internal Reclass | E5: =SUM(CapexProjectSpend[2025 Internal Reclass])+SUM(CapexProjectSpend[2026 Internal Reclass]) -> 2396751.7 | G5: External | H5: =SUM(CapexProjectSpend[2025 External])+SUM(CapexProjectSpend[2026 External]) -> 2492605.5 | J5: Other | K5: =SUM(CapexProjectSpend[2025 Other])+SUM(CapexProjectSpend[2026 Other]) -> 2312831.2
A6: PROJECT SPEND BY YEAR AND CLASSIFICATION
A7: CAPEX WBS | B7: 2025 Internal Reclass | C7: 2025 External | D7: 2025 Other | E7: 2025 Total | F7: 2026 Internal Reclass | G7: 2026 External | H7: 2026 Other | I7: 2026 Total | J7: Grand Total | K7: Latest Posting | L7: Transactions | M7: PO Lines | N7: Currency | O7: Project Budget
A8: N7941/2507 | B8: =SUMIFS('[1]Capex CJI3'!$F$2:$F$433,'[1]Capex CJI3'!$A$2:$A$433,$A8,'[1]Capex CJI3'!$K$2:$K$433,2025,'[1]Capex CJI3'!$J$2:$J$433,"*Reclass internal hours*") -> 13150 | C8: {=SUMPRODUCT(('[1]Capex CJI3'!$A$2:$A$433=$A8)*(IFERROR(VALUE('[1]Capex CJI3'!$K$2:$K$433),0)=2025)*(LEN('[1]Capex CJI3'!$E$2:$E$433)>0)*ISERROR(SEARCH("Reclass internal hours",'[1]Capex CJI3'!$J$2:$J$433))*IFERROR(VALUE('[1]Capex CJI3'!$F$2:$F$433),0))} -> 8015 | D8: {=SUMPRODUCT(('[1]Capex CJI3'!$A$2:$A$433=$A8)*(IFERROR(VALUE('[1]Capex CJI3'!$K$2:$K$433),0)=2025)*(LEN('[1]Capex CJI3'!$E$2:$E$433)=0)*ISERROR(SEARCH("Reclass internal hours",'[1]Capex CJI3'!$J$2:$J$433))*ISERROR(SEARCH("WBS Correction",'[1]Capex CJI3'!$J$2:$J$433))*('[1]Capex CJI3'!$D$2:$D$433<>"6405000000")*IFERROR(VALUE('[1]Capex CJI3'!$F$2:$F$433),0))} -> 0 | E8: =SUM(B8:D8) -> 21165 | F8: =SUMIFS('[1]Capex CJI3'!$F$2:$F$433,'[1]Capex CJI3'!$A$2:$A$433,$A8,'[1]Capex CJI3'!$K$2:$K$433,2026,'[1]Capex CJI3'!$J$2:$J$433,"*Reclass internal hours*") -> 44918 | G8: {=SUMPRODUCT(('[1]Capex CJI3'!$A$2:$A$433=$A8)*(IFERROR(VALUE('[1]Capex CJI3'!$K$2:$K$433),0)=2026)*(LEN('[1]Capex CJI3'!$E$2:$E$433)>0)*ISERROR(SEARCH("Reclass internal hours",'[1]Capex CJI3'!$J$2:$J$433))*IFERROR(VALUE('[1]Capex CJI3'!$F$2:$F$433),0))-IF($A8="O7941/2517",'[1]Capex CJI3'!$F$124,0)-IF($A8="O7941/2613",'[1]Capex CJI3'!$F$313,0)} -> 2290 | H8: {=SUMPRODUCT(('[1]Capex CJI3'!$A$2:$A$433=$A8)*(IFERROR(VALUE('[1]Capex CJI3'!$K$2:$K$433),0)=2026)*(LEN('[1]Capex CJI3'!$E$2:$E$433)=0)*ISERROR(SEARCH("Reclass internal hours",'[1]Capex CJI3'!$J$2:$J$433))*ISERROR(SEARCH("WBS Correction",'[1]Capex CJI3'!$J$2:$J$433))*('[1]Capex CJI3'!$D$2:$D$433<>"6405000000")*((($A8<>"O7941/2513")+('[1]Capex CJI3'!$D$2:$D$433<>"7405000000")+(IFERROR(VALUE('[1]Capex CJI3'!$L$2:$L$433),0)>=3))>0)*IFERROR(VALUE('[1]Capex CJI3'!$F$2:$F$433),0))-IF($A8="O7941/2517",'[1]Capex CJI3'!$F$132,0)-IF($A8="O9100/2601",'[1]Capex CJI3'!$F$429,0)} -> 0 | I8: =SUM(F8:H8) -> 47208 | J8: =E8+I8 -> 68373 | K8: 46265 | L8: {=SUMPRODUCT(('[1]Capex CJI3'!$A$2:$A$433=$A8)*(IFERROR(VALUE('[1]Capex CJI3'!$K$2:$K$433),0)>0)*((ISNUMBER(SEARCH("Reclass internal hours",'[1]Capex CJI3'!$J$2:$J$433)))+((LEN('[1]Capex CJI3'!$E$2:$E$433)>0)*ISERROR(SEARCH("Reclass internal hours",'[1]Capex CJI3'!$J$2:$J$433)))+((LEN('[1]Capex CJI3'!$E$2:$E$433)=0)*ISERROR(SEARCH("Reclass internal hours",'[1]Capex CJI3'!$J$2:$J$433))*ISERROR(SEARCH("WBS Correction",'[1]Capex CJI3'!$J$2:$J$433))*('[1]Capex CJI3'!$D$2:$D$433<>"6405000000"))>0))-IF($A8="O7941/2517",2,0)-IF($A8="O7941/2613",1,0)-IF($A8="O9100/2601",1,0)-IF($A8="O7941/2513",4,0)} -> 16 | M8: {=SUMPRODUCT(('[1]Capex CJI3'!$A$2:$A$433=$A8)*(IFERROR(VALUE('[1]Capex CJI3'!$K$2:$K$433),0)>0)*(LEN('[1]Capex CJI3'!$E$2:$E$433)>0)*ISERROR(SEARCH("Reclass internal hours",'[1]Capex CJI3'!$J$2:$J$433)))-IF($A8="O7941/2517",1,0)-IF($A8="O7941/2613",1,0)} -> 5 | N8: EUR | O8: 140000
A9: O6300/2603 | B9: =SUMIFS('[1]Capex CJI3'!$F$2:$F$433,'[1]Capex CJI3'!$A$2:$A$433,$A9,'[1]Capex CJI3'!$K$2:$K$433,2025,'[1]Capex CJI3'!$J$2:$J$433,"*Reclass internal hours*") -> 0 | C9: {=SUMPRODUCT(('[1]Capex CJI3'!$A$2:$A$433=$A9)*(IFERROR(VALUE('[1]Capex CJI3'!$K$2:$K$433),0)=2025)*(LEN('[1]Capex CJI3'!$E$2:$E$433)>0)*ISERROR(SEARCH("Reclass internal hours",'[1]Capex CJI3'!$J$2:$J$433))*IFERROR(VALUE('[1]Capex CJI3'!$F$2:$F$433),0))} -> 0 | D9: {=SUMPRODUCT(('[1]Capex CJI3'!$A$2:$A$433=$A9)*(IFERROR(VALUE('[1]Capex CJI3'!$K$2:$K$433),0)=2025)*(LEN('[1]Capex CJI3'!$E$2:$E$433)=0)*ISERROR(SEARCH("Reclass internal hours",'[1]Capex CJI3'!$J$2:$J$433))*ISERROR(SEARCH("WBS Correction",'[1]Capex CJI3'!$J$2:$J$433))*('[1]Capex CJI3'!$D$2:$D$433<>"6405000000")*IFERROR(VALUE('[1]Capex CJI3'!$F$2:$F$433),0))} -> 0 | E9: =SUM(B9:D9) -> 0 | F9: =SUMIFS('[1]Capex CJI3'!$F$2:$F$433,'[1]Capex CJI3'!$A$2:$A$433,$A9,'[1]Capex CJI3'!$K$2:$K$433,2026,'[1]Capex CJI3'!$J$2:$J$433,"*Reclass internal hours*") -> 0 | G9: {=SUMPRODUCT(('[1]Capex CJI3'!$A$2:$A$433=$A9)*(IFERROR(VALUE('[1]Capex CJI3'!$K$2:$K$433),0)=2026)*(LEN('[1]Capex CJI3'!$E$2:$E$433)>0)*ISERROR(SEARCH("Reclass internal hours",'[1]Capex CJI3'!$J$2:$J$433))*IFERROR(VALUE('[1]Capex CJI3'!$F$2:$F$433),0))-IF($A9="O7941/2517",'[1]Capex CJI3'!$F$124,0)-IF($A9="O7941/2613",'[1]Capex CJI3'!$F$313,0)} -> 571.85 | H9: {=SUMPRODUCT(('[1]Capex CJI3'!$A$2:$A$433=$A9)*(IFERROR(VALUE('[1]Capex CJI3'!$K$2:$K$433),0)=2026)*(LEN('[1]Capex CJI3'!$E$2:$E$433)=0)*ISERROR(SEARCH("Reclass internal hours",'[1]Capex CJI3'!$J$2:$J$433))*ISERROR(SEARCH("WBS Correction",'[1]Capex CJI3'!$J$2:$J$433))*('[1]Capex CJI3'!$D$2:$D$433<>"6405000000")*((($A9<>"O7941/2513")+('[1]Capex CJI3'!$D$2:$D$433<>"7405000000")+(IFERROR(VALUE('[1]Capex CJI3'!$L$2:$L$433),0)>=3))>0)*IFERROR(VALUE('[1]Capex CJI3'!$F$2:$F$433),0))-IF($A9="O7941/2517",'[1]Capex CJI3'!$F$132,0)-IF($A9="O9100/2601",'[1]Capex CJI3'!$F$429,0)} -> 0 | I9: =SUM(F9:H9) -> 571.85 | J9: =E9+I9 -> 571.85 | K9: 46258 | L9: {=SUMPRODUCT(('[1]Capex CJI3'!$A$2:$A$433=$A9)*(IFERROR(VALUE('[1]Capex CJI3'!$K$2:$K$433),0)>0)*((ISNUMBER(SEARCH("Reclass internal hours",'[1]Capex CJI3'!$J$2:$J$433)))+((LEN('[1]Capex CJI3'!$E$2:$E$433)>0)*ISERROR(SEARCH("Reclass internal hours",'[1]Capex CJI3'!$J$2:$J$433)))+((LEN('[1]Capex CJI3'!$E$2:$E$433)=0)*ISERROR(SEARCH("Reclass internal hours",'[1]Capex CJI3'!$J$2:$J$433))*ISERROR(SEARCH("WBS Correction",'[1]Capex CJI3'!$J$2:$J$433))*('[1]Capex CJI3'!$D$2:$D$433<>"6405000000"))>0))-IF($A9="O7941/2517",2,0)-IF($A9="O7941/2613",1,0)-IF($A9="O9100/2601",1,0)-IF($A9="O7941/2513",4,0)} -> 1 | M9: {=SUMPRODUCT(('[1]Capex CJI3'!$A$2:$A$433=$A9)*(IFERROR(VALUE('[1]Capex CJI3'!$K$2:$K$433),0)>0)*(LEN('[1]Capex CJI3'!$E$2:$E$433)>0)*ISERROR(SEARCH("Reclass internal hours",'[1]Capex CJI3'!$J$2:$J$433)))-IF($A9="O7941/2517",1,0)-IF($A9="O7941/2613",1,0)} -> 1 | N9: EUR | O9: 54700
A10: O7941/2513 | B10: =SUMIFS('[1]Capex CJI3'!$F$2:$F$433,'[1]Capex CJI3'!$A$2:$A$433,$A10,'[1]Capex CJI3'!$K$2:$K$433,2025,'[1]Capex CJI3'!$J$2:$J$433,"*Reclass internal hours*") -> 18000 | C10: {=SUMPRODUCT(('[1]Capex CJI3'!$A$2:$A$433=$A10)*(IFERROR(VALUE('[1]Capex CJI3'!$K$2:$K$433),0)=2025)*(LEN('[1]Capex CJI3'!$E$2:$E$433)>0)*ISERROR(SEARCH("Reclass internal hours",'[1]Capex CJI3'!$J$2:$J$433))*IFERROR(VALUE('[1]Capex CJI3'!$F$2:$F$433),0))} -> 128447.8 | D10: {=SUMPRODUCT(('[1]Capex CJI3'!$A$2:$A$433=$A10)*(IFERROR(VALUE('[1]Capex CJI3'!$K$2:$K$433),0)=2025)*(LEN('[1]Capex CJI3'!$E$2:$E$433)=0)*ISERROR(SEARCH("Reclass internal hours",'[1]Capex CJI3'!$J$2:$J$433))*ISERROR(SEARCH("WBS Correction",'[1]Capex CJI3'!$J$2:$J$433))*('[1]Capex CJI3'!$D$2:$D$433<>"6405000000")*IFERROR(VALUE('[1]Capex CJI3'!$F$2:$F$433),0))} -> 17548 | E10: =SUM(B10:D10) -> 163995.8 | F10: =SUMIFS('[1]Capex CJI3'!$F$2:$F$433,'[1]Capex CJI3'!$A$2:$A$433,$A10,'[1]Capex CJI3'!$K$2:$K$433,2026,'[1]Capex CJI3'!$J$2:$J$433,"*Reclass internal hours*") -> 48690 | G10: {=SUMPRODUCT(('[1]Capex CJI3'!$A$2:$A$433=$A10)*(IFERROR(VALUE('[1]Capex CJI3'!$K$2:$K$433),0)=2026)*(LEN('[1]Capex CJI3'!$E$2:$E$433)>0)*ISERROR(SEARCH("Reclass internal hours",'[1]Capex CJI3'!$J$2:$J$433))*IFERROR(VALUE('[1]Capex CJI3'!$F$2:$F$433),0))-IF($A10="O7941/2517",'[1]Capex CJI3'!$F$124,0)-IF($A10="O7941/2613",'[1]Capex CJI3'!$F$313,0)} -> 188080.05 | H10: {=SUMPRODUCT(('[1]Capex CJI3'!$A$2:$A$433=$A10)*(IFERROR(VALUE('[1]Capex CJI3'!$K$2:$K$433),0)=2026)*(LEN('[1]Capex CJI3'!$E$2:$E$433)=0)*ISERROR(SEARCH("Reclass internal hours",'[1]Capex CJI3'!$J$2:$J$433))*ISERROR(SEARCH("WBS Correction",'[1]Capex CJI3'!$J$2:$J$433))*('[1]Capex CJI3'!$D$2:$D$433<>"6405000000")*((($A10<>"O7941/2513")+('[1]Capex CJI3'!$D$2:$D$433<>"7405000000")+(IFERROR(VALUE('[1]Capex CJI3'!$L$2:$L$433),0)>=3))>0)*IFERROR(VALUE('[1]Capex CJI3'!$F$2:$F$433),0))-IF($A10="O7941/2517",'[1]Capex CJI3'!$F$132,0)-IF($A10="O9100/2601",'[1]Capex CJI3'!$F$429,0)} -> 93999.5 | I10: =SUM(F10:H10) -> 330769.55 | J10: =E10+I10 -> 494765.35 | K10: 46269 | L10: {=SUMPRODUCT(('[1]Capex CJI3'!$A$2:$A$433=$A10)*(IFERROR(VALUE('[1]Capex CJI3'!$K$2:$K$433),0)>0)*((ISNUMBER(SEARCH("Reclass internal hours",'[1]Capex CJI3'!$J$2:$J$433)))+((LEN('[1]Capex CJI3'!$E$2:$E$433)>0)*ISERROR(SEARCH("Reclass internal hours",'[1]Capex CJI3'!$J$2:$J$433)))+((LEN('[1]Capex CJI3'!$E$2:$E$433)=0)*ISERROR(SEARCH("Reclass internal hours",'[1]Capex CJI3'!$J$2:$J$433))*ISERROR(SEARCH("WBS Correction",'[1]Capex CJI3'!$J$2:$J$433))*('[1]Capex CJI3'!$D$2:$D$433<>"6405000000"))>0))-IF($A10="O7941/2517",2,0)-IF($A10="O7941/2613",1,0)-IF($A10="O9100/2601",1,0)-IF($A10="O7941/2513",4,0)} -> 40 | M10: {=SUMPRODUCT(('[1]Capex CJI3'!$A$2:$A$433=$A10)*(IFERROR(VALUE('[1]Capex CJI3'!$K$2:$K$433),0)>0)*(LEN('[1]Capex CJI3'!$E$2:$E$433)>0)*ISERROR(SEARCH("Reclass internal hours",'[1]Capex CJI3'!$J$2:$J$433)))-IF($A10="O7941/2517",1,0)-IF($A10="O7941/2613",1,0)} -> 23 | N10: EUR | O10: 585000
A11: O7941/2517 | B11: =SUMIFS('[1]Capex CJI3'!$F$2:$F$433,'[1]Capex CJI3'!$A$2:$A$433,$A11,'[1]Capex CJI3'!$K$2:$K$433,2025,'[1]Capex CJI3'!$J$2:$J$433,"*Reclass internal hours*") -> 2900 | C11: {=SUMPRODUCT(('[1]Capex CJI3'!$A$2:$A$433=$A11)*(IFERROR(VALUE('[1]Capex CJI3'!$K$2:$K$433),0)=2025)*(LEN('[1]Capex CJI3'!$E$2:$E$433)>0)*ISERROR(SEARCH("Reclass internal hours",'[1]Capex CJI3'!$J$2:$J$433))*IFERROR(VALUE('[1]Capex CJI3'!$F$2:$F$433),0))} -> 121088 | D11: {=SUMPRODUCT(('[1]Capex CJI3'!$A$2:$A$433=$A11)*(IFERROR(VALUE('[1]Capex CJI3'!$K$2:$K$433),0)=2025)*(LEN('[1]Capex CJI3'!$E$2:$E$433)=0)*ISERROR(SEARCH("Reclass internal hours",'[1]Capex CJI3'!$J$2:$J$433))*ISERROR(SEARCH("WBS Correction",'[1]Capex CJI3'!$J$2:$J$433))*('[1]Capex CJI3'!$D$2:$D$433<>"6405000000")*IFERROR(VALUE('[1]Capex CJI3'!$F$2:$F$433),0))} -> 89012 | E11: =SUM(B11:D11) -> 213000 | F11: =SUMIFS('[1]Capex CJI3'!$F$2:$F$433,'[1]Capex CJI3'!$A$2:$A$433,$A11,'[1]Capex CJI3'!$K$2:$K$433,2026,'[1]Capex CJI3'!$J$2:$J$433,"*Reclass internal hours*") -> 79238 | G11: {=SUMPRODUCT(('[1]Capex CJI3'!$A$2:$A$433=$A11)*(IFERROR(VALUE('[1]Capex CJI3'!$K$2:$K$433),0)=2026)*(LEN('[1]Capex CJI3'!$E$2:$E$433)>0)*ISERROR(SEARCH("Reclass internal hours",'[1]Capex CJI3'!$J$2:$J$433))*IFERROR(VALUE('[1]Capex CJI3'!$F$2:$F$433),0))-IF($A11="O7941/2517",'[1]Capex CJI3'!$F$124,0)-IF($A11="O7941/2613",'[1]Capex CJI3'!$F$313,0)} -> 164692.23 | H11: 148581.52 | I11: =SUM(F11:H11) -> 392511.75 | J11: =E11+I11 -> 605511.75 | K11: 46265 | L11: {=SUMPRODUCT(('[1]Capex CJI3'!$A$2:$A$433=$A11)*(IFERROR(VALUE('[1]Capex CJI3'!$K$2:$K$433),0)>0)*((ISNUMBER(SEARCH("Reclass internal hours",'[1]Capex CJI3'!$J$2:$J$433)))+((LEN('[1]Capex CJI3'!$E$2:$E$433)>0)*ISERROR(SEARCH("Reclass internal hours",'[1]Capex CJI3'!$J$2:$J$433)))+((LEN('[1]Capex CJI3'!$E$2:$E$433)=0)*ISERROR(SEARCH("Reclass internal hours",'[1]Capex CJI3'!$J$2:$J$433))*ISERROR(SEARCH("WBS Correction",'[1]Capex CJI3'!$J$2:$J$433))*('[1]Capex CJI3'!$D$2:$D$433<>"6405000000"))>0))-IF($A11="O7941/2517",2,0)-IF($A11="O7941/2613",1,0)-IF($A11="O9100/2601",1,0)-IF($A11="O7941/2513",4,0)} -> 30 | M11: {=SUMPRODUCT(('[1]Capex CJI3'!$A$2:$A$433=$A11)*(IFERROR(VALUE('[1]Capex CJI3'!$K$2:$K$433),0)>0)*(LEN('[1]Capex CJI3'!$E$2:$E$433)>0)*ISERROR(SEARCH("Reclass internal hours",'[1]Capex CJI3'!$J$2:$J$433)))-IF($A11="O7941/2517",1,0)-IF($A11="O7941/2613",1,0)} -> 11 | N11: EUR | O11: 928000
A12: O7941/2519 | B12: =SUMIFS('[1]Capex CJI3'!$F$2:$F$433,'[1]Capex CJI3'!$A$2:$A$433,$A12,'[1]Capex CJI3'!$K$2:$K$433,2025,'[1]Capex CJI3'!$J$2:$J$433,"*Reclass internal hours*") -> 38000 | C12: {=SUMPRODUCT(('[1]Capex CJI3'!$A$2:$A$433=$A12)*(IFERROR(VALUE('[1]Capex CJI3'!$K$2:$K$433),0)=2025)*(LEN('[1]Capex CJI3'!$E$2:$E$433)>0)*ISERROR(SEARCH("Reclass internal hours",'[1]Capex CJI3'!$J$2:$J$433))*IFERROR(VALUE('[1]Capex CJI3'!$F$2:$F$433),0))} -> 100000 | D12: {=SUMPRODUCT(('[1]Capex CJI3'!$A$2:$A$433=$A12)*(IFERROR(VALUE('[1]Capex CJI3'!$K$2:$K$433),0)=2025)*(LEN('[1]Capex CJI3'!$E$2:$E$433)=0)*ISERROR(SEARCH("Reclass internal hours",'[1]Capex CJI3'!$J$2:$J$433))*ISERROR(SEARCH("WBS Correction",'[1]Capex CJI3'!$J$2:$J$433))*('[1]Capex CJI3'!$D$2:$D$433<>"6405000000")*IFERROR(VALUE('[1]Capex CJI3'!$F$2:$F$433),0))} -> 0 | E12: =SUM(B12:D12) -> 138000 | F12: =SUMIFS('[1]Capex CJI3'!$F$2:$F$433,'[1]Capex CJI3'!$A$2:$A$433,$A12,'[1]Capex CJI3'!$K$2:$K$433,2026,'[1]Capex CJI3'!$J$2:$J$433,"*Reclass internal hours*") -> 227750.4 | G12: {=SUMPRODUCT(('[1]Capex CJI3'!$A$2:$A$433=$A12)*(IFERROR(VALUE('[1]Capex CJI3'!$K$2:$K$433),0)=2026)*(LEN('[1]Capex CJI3'!$E$2:$E$433)>0)*ISERROR(SEARCH("Reclass internal hours",'[1]Capex CJI3'!$J$2:$J$433))*IFERROR(VALUE('[1]Capex CJI3'!$F$2:$F$433),0))-IF($A12="O7941/2517",'[1]Capex CJI3'!$F$124,0)-IF($A12="O7941/2613",'[1]Capex CJI3'!$F$313,0)} -> 277505.1 | H12: 112698.44 | I12: =SUM(F12:H12) -> 617953.94 | J12: =E12+I12 -> 755953.94 | K12: 46269 | L12: {=SUMPRODUCT(('[1]Capex CJI3'!$A$2:$A$433=$A12)*(IFERROR(VALUE('[1]Capex CJI3'!$K$2:$K$433),0)>0)*((ISNUMBER(SEARCH("Reclass internal hours",'[1]Capex CJI3'!$J$2:$J$433)))+((LEN('[1]Capex CJI3'!$E$2:$E$433)>0)*ISERROR(SEARCH("Reclass internal hours",'[1]Capex CJI3'!$J$2:$J$433)))+((LEN('[1]Capex CJI3'!$E$2:$E$433)=0)*ISERROR(SEARCH("Reclass internal hours",'[1]Capex CJI3'!$J$2:$J$433))*ISERROR(SEARCH("WBS Correction",'[1]Capex CJI3'!$J$2:$J$433))*('[1]Capex CJI3'!$D$2:$D$433<>"6405000000"))>0))-IF($A12="O7941/2517",2,0)-IF($A12="O7941/2613",1,0)-IF($A12="O9100/2601",1,0)-IF($A12="O7941/2513",4,0)} -> 32 | M12: {=SUMPRODUCT(('[1]Capex CJI3'!$A$2:$A$433=$A12)*(IFERROR(VALUE('[1]Capex CJI3'!$K$2:$K$433),0)>0)*(LEN('[1]Capex CJI3'!$E$2:$E$433)>0)*ISERROR(SEARCH("Reclass internal hours",'[1]Capex CJI3'!$J$2:$J$433)))-IF($A12="O7941/2517",1,0)-IF($A12="O7941/2613",1,0)} -> 10 | N12: EUR | O12: 874000
A13: O7941/2523 | B13: =SUMIFS('[1]Capex CJI3'!$F$2:$F$433,'[1]Capex CJI3'!$A$2:$A$433,$A13,'[1]Capex CJI3'!$K$2:$K$433,2025,'[1]Capex CJI3'!$J$2:$J$433,"*Reclass internal hours*") -> 0 | C13: {=SUMPRODUCT(('[1]Capex CJI3'!$A$2:$A$433=$A13)*(IFERROR(VALUE('[1]Capex CJI3'!$K$2:$K$433),0)=2025)*(LEN('[1]Capex CJI3'!$E$2:$E$433)>0)*ISERROR(SEARCH("Reclass internal hours",'[1]Capex CJI3'!$J$2:$J$433))*IFERROR(VALUE('[1]Capex CJI3'!$F$2:$F$433),0))} -> 31990.6 | D13: {=SUMPRODUCT(('[1]Capex CJI3'!$A$2:$A$433=$A13)*(IFERROR(VALUE('[1]Capex CJI3'!$K$2:$K$433),0)=2025)*(LEN('[1]Capex CJI3'!$E$2:$E$433)=0)*ISERROR(SEARCH("Reclass internal hours",'[1]Capex CJI3'!$J$2:$J$433))*ISERROR(SEARCH("WBS Correction",'[1]Capex CJI3'!$J$2:$J$433))*('[1]Capex CJI3'!$D$2:$D$433<>"6405000000")*IFERROR(VALUE('[1]Capex CJI3'!$F$2:$F$433),0))} -> 0 | E13: =SUM(B13:D13) -> 31990.6 | F13: =SUMIFS('[1]Capex CJI3'!$F$2:$F$433,'[1]Capex CJI3'!$A$2:$A$433,$A13,'[1]Capex CJI3'!$K$2:$K$433,2026,'[1]Capex CJI3'!$J$2:$J$433,"*Reclass internal hours*") -> 26009 | G13: {=SUMPRODUCT(('[1]Capex CJI3'!$A$2:$A$433=$A13)*(IFERROR(VALUE('[1]Capex CJI3'!$K$2:$K$433),0)=2026)*(LEN('[1]Capex CJI3'!$E$2:$E$433)>0)*ISERROR(SEARCH("Reclass internal hours",'[1]Capex CJI3'!$J$2:$J$433))*IFERROR(VALUE('[1]Capex CJI3'!$F$2:$F$433),0))-IF($A13="O7941/2517",'[1]Capex CJI3'!$F$124,0)-IF($A13="O7941/2613",'[1]Capex CJI3'!$F$313,0)} -> 39646 | H13: {=SUMPRODUCT(('[1]Capex CJI3'!$A$2:$A$433=$A13)*(IFERROR(VALUE('[1]Capex CJI3'!$K$2:$K$433),0)=2026)*(LEN('[1]Capex CJI3'!$E$2:$E$433)=0)*ISERROR(SEARCH("Reclass internal hours",'[1]Capex CJI3'!$J$2:$J$433))*ISERROR(SEARCH("WBS Correction",'[1]Capex CJI3'!$J$2:$J$433))*('[1]Capex CJI3'!$D$2:$D$433<>"6405000000")*((($A13<>"O7941/2513")+('[1]Capex CJI3'!$D$2:$D$433<>"7405000000")+(IFERROR(VALUE('[1]Capex CJI3'!$L$2:$L$433),0)>=3))>0)*IFERROR(VALUE('[1]Capex CJI3'!$F$2:$F$433),0))-IF($A13="O7941/2517",'[1]Capex CJI3'!$F$132,0)-IF($A13="O9100/2601",'[1]Capex CJI3'!$F$429,0)} -> 0 | I13: =SUM(F13:H13) -> 65655 | J13: =E13+I13 -> 97645.6 | K13: 46255 | L13: {=SUMPRODUCT(('[1]Capex CJI3'!$A$2:$A$433=$A13)*(IFERROR(VALUE('[1]Capex CJI3'!$K$2:$K$433),0)>0)*((ISNUMBER(SEARCH("Reclass internal hours",'[1]Capex CJI3'!$J$2:$J$433)))+((LEN('[1]Capex CJI3'!$E$2:$E$433)>0)*ISERROR(SEARCH("Reclass internal hours",'[1]Capex CJI3'!$J$2:$J$433)))+((LEN('[1]Capex CJI3'!$E$2:$E$433)=0)*ISERROR(SEARCH("Reclass internal hours",'[1]Capex CJI3'!$J$2:$J$433))*ISERROR(SEARCH("WBS Correction",'[1]Capex CJI3'!$J$2:$J$433))*('[1]Capex CJI3'!$D$2:$D$433<>"6405000000"))>0))-IF($A13="O7941/2517",2,0)-IF($A13="O7941/2613",1,0)-IF($A13="O9100/2601",1,0)-IF($A13="O7941/2513",4,0)} -> 7 | M13: {=SUMPRODUCT(('[1]Capex CJI3'!$A$2:$A$433=$A13)*(IFERROR(VALUE('[1]Capex CJI3'!$K$2:$K$433),0)>0)*(LEN('[1]Capex CJI3'!$E$2:$E$433)>0)*ISERROR(SEARCH("Reclass internal hours",'[1]Capex CJI3'!$J$2:$J$433)))-IF($A13="O7941/2517",1,0)-IF($A13="O7941/2613",1,0)} -> 3 | N13: EUR | O13: 119580
A14: O7941/2524 | B14: =SUMIFS('[1]Capex CJI3'!$F$2:$F$433,'[1]Capex CJI3'!$A$2:$A$433,$A14,'[1]Capex CJI3'!$K$2:$K$433,2025,'[1]Capex CJI3'!$J$2:$J$433,"*Reclass internal hours*") -> 0 | C14: {=SUMPRODUCT(('[1]Capex CJI3'!$A$2:$A$433=$A14)*(IFERROR(VALUE('[1]Capex CJI3'!$K$2:$K$433),0)=2025)*(LEN('[1]Capex CJI3'!$E$2:$E$433)>0)*ISERROR(SEARCH("Reclass internal hours",'[1]Capex CJI3'!$J$2:$J$433))*IFERROR(VALUE('[1]Capex CJI3'!$F$2:$F$433),0))} -> 0 | D14: {=SUMPRODUCT(('[1]Capex CJI3'!$A$2:$A$433=$A14)*(IFERROR(VALUE('[1]Capex CJI3'!$K$2:$K$433),0)=2025)*(LEN('[1]Capex CJI3'!$E$2:$E$433)=0)*ISERROR(SEARCH("Reclass internal hours",'[1]Capex CJI3'!$J$2:$J$433))*ISERROR(SEARCH("WBS Correction",'[1]Capex CJI3'!$J$2:$J$433))*('[1]Capex CJI3'!$D$2:$D$433<>"6405000000")*IFERROR(VALUE('[1]Capex CJI3'!$F$2:$F$433),0))} -> 0 | E14: =SUM(B14:D14) -> 0 | F14: =SUMIFS('[1]Capex CJI3'!$F$2:$F$433,'[1]Capex CJI3'!$A$2:$A$433,$A14,'[1]Capex CJI3'!$K$2:$K$433,2026,'[1]Capex CJI3'!$J$2:$J$433,"*Reclass internal hours*") -> 0 | G14: {=SUMPRODUCT(('[1]Capex CJI3'!$A$2:$A$433=$A14)*(IFERROR(VALUE('[1]Capex CJI3'!$K$2:$K$433),0)=2026)*(LEN('[1]Capex CJI3'!$E$2:$E$433)>0)*ISERROR(SEARCH("Reclass internal hours",'[1]Capex CJI3'!$J$2:$J$433))*IFERROR(VALUE('[1]Capex CJI3'!$F$2:$F$433),0))-IF($A14="O7941/2517",'[1]Capex CJI3'!$F$124,0)-IF($A14="O7941/2613",'[1]Capex CJI3'!$F$313,0)} -> 169189 | H14: {=SUMPRODUCT(('[1]Capex CJI3'!$A$2:$A$433=$A14)*(IFERROR(VALUE('[1]Capex CJI3'!$K$2:$K$433),0)=2026)*(LEN('[1]Capex CJI3'!$E$2:$E$433)=0)*ISERROR(SEARCH("Reclass internal hours",'[1]Capex CJI3'!$J$2:$J$433))*ISERROR(SEARCH("WBS Correction",'[1]Capex CJI3'!$J$2:$J$433))*('[1]Capex CJI3'!$D$2:$D$433<>"6405000000")*((($A14<>"O7941/2513")+('[1]Capex CJI3'!$D$2:$D$433<>"7405000000")+(IFERROR(VALUE('[1]Capex CJI3'!$L$2:$L$433),0)>=3))>0)*IFERROR(VALUE('[1]Capex CJI3'!$F$2:$F$433),0))-IF($A14="O7941/2517",'[1]Capex CJI3'!$F$132,0)-IF($A14="O9100/2601",'[1]Capex CJI3'!$F$429,0)} -> 164155 | I14: =SUM(I15:I21) -> 961449.31 | J14: =E14+I14 -> 961449.31 | K14: 46274 | L14: {=SUMPRODUCT(('[1]Capex CJI3'!$A$2:$A$433=$A14)*(IFERROR(VALUE('[1]Capex CJI3'!$K$2:$K$433),0)>0)*((ISNUMBER(SEARCH("Reclass internal hours",'[1]Capex CJI3'!$J$2:$J$433)))+((LEN('[1]Capex CJI3'!$E$2:$E$433)>0)*ISERROR(SEARCH("Reclass internal hours",'[1]Capex CJI3'!$J$2:$J$433)))+((LEN('[1]Capex CJI3'!$E$2:$E$433)=0)*ISERROR(SEARCH("Reclass internal hours",'[1]Capex CJI3'!$J$2:$J$433))*ISERROR(SEARCH("WBS Correction",'[1]Capex CJI3'!$J$2:$J$433))*('[1]Capex CJI3'!$D$2:$D$433<>"6405000000"))>0))-IF($A14="O7941/2517",2,0)-IF($A14="O7941/2613",1,0)-IF($A14="O9100/2601",1,0)-IF($A14="O7941/2513",4,0)} -> 6 | M14: {=SUMPRODUCT(('[1]Capex CJI3'!$A$2:$A$433=$A14)*(IFERROR(VALUE('[1]Capex CJI3'!$K$2:$K$433),0)>0)*(LEN('[1]Capex CJI3'!$E$2:$E$433)>0)*ISERROR(SEARCH("Reclass internal hours",'[1]Capex CJI3'!$J$2:$J$433)))-IF($A14="O7941/2517",1,0)-IF($A14="O7941/2613",1,0)} -> 5 | N14: EUR | O14: 1937717
A15: O7941/2524/1 | B15: =SUMIFS('[1]Capex CJI3'!$F$2:$F$433,'[1]Capex CJI3'!$A$2:$A$433,$A15,'[1]Capex CJI3'!$K$2:$K$433,2025,'[1]Capex CJI3'!$J$2:$J$433,"*Reclass internal hours*") -> 0 | C15: {=SUMPRODUCT(('[1]Capex CJI3'!$A$2:$A$433=$A15)*(IFERROR(VALUE('[1]Capex CJI3'!$K$2:$K$433),0)=2025)*(LEN('[1]Capex CJI3'!$E$2:$E$433)>0)*ISERROR(SEARCH("Reclass internal hours",'[1]Capex CJI3'!$J$2:$J$433))*IFERROR(VALUE('[1]Capex CJI3'!$F$2:$F$433),0))} -> 0 | D15: {=SUMPRODUCT(('[1]Capex CJI3'!$A$2:$A$433=$A15)*(IFERROR(VALUE('[1]Capex CJI3'!$K$2:$K$433),0)=2025)*(LEN('[1]Capex CJI3'!$E$2:$E$433)=0)*ISERROR(SEARCH("Reclass internal hours",'[1]Capex CJI3'!$J$2:$J$433))*ISERROR(SEARCH("WBS Correction",'[1]Capex CJI3'!$J$2:$J$433))*('[1]Capex CJI3'!$D$2:$D$433<>"6405000000")*IFERROR(VALUE('[1]Capex CJI3'!$F$2:$F$433),0))} -> 0 | E15: =SUM(B15:D15) -> 0 | F15: =SUMIFS('[1]Capex CJI3'!$F$2:$F$433,'[1]Capex CJI3'!$A$2:$A$433,$A15,'[1]Capex CJI3'!$K$2:$K$433,2026,'[1]Capex CJI3'!$J$2:$J$433,"*Reclass internal hours*") -> 0 | G15: {=SUMPRODUCT(('[1]Capex CJI3'!$A$2:$A$433=$A15)*(IFERROR(VALUE('[1]Capex CJI3'!$K$2:$K$433),0)=2026)*(LEN('[1]Capex CJI3'!$E$2:$E$433)>0)*ISERROR(SEARCH("Reclass internal hours",'[1]Capex CJI3'!$J$2:$J$433))*IFERROR(VALUE('[1]Capex CJI3'!$F$2:$F$433),0))-IF($A15="O7941/2517",'[1]Capex CJI3'!$F$124,0)-IF($A15="O7941/2613",'[1]Capex CJI3'!$F$313,0)} -> 632000 | H15: {=SUMPRODUCT(('[1]Capex CJI3'!$A$2:$A$433=$A15)*(IFERROR(VALUE('[1]Capex CJI3'!$K$2:$K$433),0)=2026)*(LEN('[1]Capex CJI3'!$E$2:$E$433)=0)*ISERROR(SEARCH("Reclass internal hours",'[1]Capex CJI3'!$J$2:$J$433))*ISERROR(SEARCH("WBS Correction",'[1]Capex CJI3'!$J$2:$J$433))*('[1]Capex CJI3'!$D$2:$D$433<>"6405000000")*((($A15<>"O7941/2513")+('[1]Capex CJI3'!$D$2:$D$433<>"7405000000")+(IFERROR(VALUE('[1]Capex CJI3'!$L$2:$L$433),0)>=3))>0)*IFERROR(VALUE('[1]Capex CJI3'!$F$2:$F$433),0))-IF($A15="O7941/2517",'[1]Capex CJI3'!$F$132,0)-IF($A15="O9100/2601",'[1]Capex CJI3'!$F$429,0)} -> 161000 | I15: =SUM(F15:H15) -> 793000 | J15: =E15+I15 -> 793000 | K15: 46274 | L15: {=SUMPRODUCT(('[1]Capex CJI3'!$A$2:$A$433=$A15)*(IFERROR(VALUE('[1]Capex CJI3'!$K$2:$K$433),0)>0)*((ISNUMBER(SEARCH("Reclass internal hours",'[1]Capex CJI3'!$J$2:$J$433)))+((LEN('[1]Capex CJI3'!$E$2:$E$433)>0)*ISERROR(SEARCH("Reclass internal hours",'[1]Capex CJI3'!$J$2:$J$433)))+((LEN('[1]Capex CJI3'!$E$2:$E$433)=0)*ISERROR(SEARCH("Reclass internal hours",'[1]Capex CJI3'!$J$2:$J$433))*ISERROR(SEARCH("WBS Correction",'[1]Capex CJI3'!$J$2:$J$433))*('[1]Capex CJI3'!$D$2:$D$433<>"6405000000"))>0))-IF($A15="O7941/2517",2,0)-IF($A15="O7941/2613",1,0)-IF($A15="O9100/2601",1,0)-IF($A15="O7941/2513",4,0)} -> 8 | M15: {=SUMPRODUCT(('[1]Capex CJI3'!$A$2:$A$433=$A15)*(IFERROR(VALUE('[1]Capex CJI3'!$K$2:$K$433),0)>0)*(LEN('[1]Capex CJI3'!$E$2:$E$433)>0)*ISERROR(SEARCH("Reclass internal hours",'[1]Capex CJI3'!$J$2:$J$433)))-IF($A15="O7941/2517",1,0)-IF($A15="O7941/2613",1,0)} -> 6 | N15: EUR
A16: O7941/2524/2 | B16: =SUMIFS('[1]Capex CJI3'!$F$2:$F$433,'[1]Capex CJI3'!$A$2:$A$433,$A16,'[1]Capex CJI3'!$K$2:$K$433,2025,'[1]Capex CJI3'!$J$2:$J$433,"*Reclass internal hours*") -> 0 | C16: {=SUMPRODUCT(('[1]Capex CJI3'!$A$2:$A$433=$A16)*(IFERROR(VALUE('[1]Capex CJI3'!$K$2:$K$433),0)=2025)*(LEN('[1]Capex CJI3'!$E$2:$E$433)>0)*ISERROR(SEARCH("Reclass internal hours",'[1]Capex CJI3'!$J$2:$J$433))*IFERROR(VALUE('[1]Capex CJI3'!$F$2:$F$433),0))} -> 0 | D16: {=SUMPRODUCT(('[1]Capex CJI3'!$A$2:$A$433=$A16)*(IFERROR(VALUE('[1]Capex CJI3'!$K$2:$K$433),0)=2025)*(LEN('[1]Capex CJI3'!$E$2:$E$433)=0)*ISERROR(SEARCH("Reclass internal hours",'[1]Capex CJI3'!$J$2:$J$433))*ISERROR(SEARCH("WBS Correction",'[1]Capex CJI3'!$J$2:$J$433))*('[1]Capex CJI3'!$D$2:$D$433<>"6405000000")*IFERROR(VALUE('[1]Capex CJI3'!$F$2:$F$433),0))} -> 0 | E16: =SUM(B16:D16) -> 0 | F16: =SUMIFS('[1]Capex CJI3'!$F$2:$F$433,'[1]Capex CJI3'!$A$2:$A$433,$A16,'[1]Capex CJI3'!$K$2:$K$433,2026,'[1]Capex CJI3'!$J$2:$J$433,"*Reclass internal hours*") -> 0 | G16: {=SUMPRODUCT(('[1]Capex CJI3'!$A$2:$A$433=$A16)*(IFERROR(VALUE('[1]Capex CJI3'!$K$2:$K$433),0)=2026)*(LEN('[1]Capex CJI3'!$E$2:$E$433)>0)*ISERROR(SEARCH("Reclass internal hours",'[1]Capex CJI3'!$J$2:$J$433))*IFERROR(VALUE('[1]Capex CJI3'!$F$2:$F$433),0))-IF($A16="O7941/2517",'[1]Capex CJI3'!$F$124,0)-IF($A16="O7941/2613",'[1]Capex CJI3'!$F$313,0)} -> 74760 | H16: {=SUMPRODUCT(('[1]Capex CJI3'!$A$2:$A$433=$A16)*(IFERROR(VALUE('[1]Capex CJI3'!$K$2:$K$433),0)=2026)*(LEN('[1]Capex CJI3'!$E$2:$E$433)=0)*ISERROR(SEARCH("Reclass internal hours",'[1]Capex CJI3'!$J$2:$J$433))*ISERROR(SEARCH("WBS Correction",'[1]Capex CJI3'!$J$2:$J$433))*('[1]Capex CJI3'!$D$2:$D$433<>"6405000000")*((($A16<>"O7941/2513")+('[1]Capex CJI3'!$D$2:$D$433<>"7405000000")+(IFERROR(VALUE('[1]Capex CJI3'!$L$2:$L$433),0)>=3))>0)*IFERROR(VALUE('[1]Capex CJI3'!$F$2:$F$433),0))-IF($A16="O7941/2517",'[1]Capex CJI3'!$F$132,0)-IF($A16="O9100/2601",'[1]Capex CJI3'!$F$429,0)} -> 14199.99 | I16: =SUM(F16:H16) -> 88959.99 | J16: =E16+I16 -> 88959.99 | K16: 46251 | L16: {=SUMPRODUCT(('[1]Capex CJI3'!$A$2:$A$433=$A16)*(IFERROR(VALUE('[1]Capex CJI3'!$K$2:$K$433),0)>0)*((ISNUMBER(SEARCH("Reclass internal hours",'[1]Capex CJI3'!$J$2:$J$433)))+((LEN('[1]Capex CJI3'!$E$2:$E$433)>0)*ISERROR(SEARCH("Reclass internal hours",'[1]Capex CJI3'!$J$2:$J$433)))+((LEN('[1]Capex CJI3'!$E$2:$E$433)=0)*ISERROR(SEARCH("Reclass internal hours",'[1]Capex CJI3'!$J$2:$J$433))*ISERROR(SEARCH("WBS Correction",'[1]Capex CJI3'!$J$2:$J$433))*('[1]Capex CJI3'!$D$2:$D$433<>"6405000000"))>0))-IF($A16="O7941/2517",2,0)-IF($A16="O7941/2613",1,0)-IF($A16="O9100/2601",1,0)-IF($A16="O7941/2513",4,0)} -> 7 | M16: {=SUMPRODUCT(('[1]Capex CJI3'!$A$2:$A$433=$A16)*(IFERROR(VALUE('[1]Capex CJI3'!$K$2:$K$433),0)>0)*(LEN('[1]Capex CJI3'!$E$2:$E$433)>0)*ISERROR(SEARCH("Reclass internal hours",'[1]Capex CJI3'!$J$2:$J$433)))-IF($A16="O7941/2517",1,0)-IF($A16="O7941/2613",1,0)} -> 6 | N16: EUR
A17: O7941/2524/3 | B17: =SUMIFS('[1]Capex CJI3'!$F$2:$F$433,'[1]Capex CJI3'!$A$2:$A$433,$A17,'[1]Capex CJI3'!$K$2:$K$433,2025,'[1]Capex CJI3'!$J$2:$J$433,"*Reclass internal hours*") -> 0 | C17: {=SUMPRODUCT(('[1]Capex CJI3'!$A$2:$A$433=$A17)*(IFERROR(VALUE('[1]Capex CJI3'!$K$2:$K$433),0)=2025)*(LEN('[1]Capex CJI3'!$E$2:$E$433)>0)*ISERROR(SEARCH("Reclass internal hours",'[1]Capex CJI3'!$J$2:$J$433))*IFERROR(VALUE('[1]Capex CJI3'!$F$2:$F$433),0))} -> 0 | D17: {=SUMPRODUCT(('[1]Capex CJI3'!$A$2:$A$433=$A17)*(IFERROR(VALUE('[1]Capex CJI3'!$K$2:$K$433),0)=2025)*(LEN('[1]Capex CJI3'!$E$2:$E$433)=0)*ISERROR(SEARCH("Reclass internal hours",'[1]Capex CJI3'!$J$2:$J$433))*ISERROR(SEARCH("WBS Correction",'[1]Capex CJI3'!$J$2:$J$433))*('[1]Capex CJI3'!$D$2:$D$433<>"6405000000")*IFERROR(VALUE('[1]Capex CJI3'!$F$2:$F$433),0))} -> 0 | E17: =SUM(B17:D17) -> 0 | F17: =SUMIFS('[1]Capex CJI3'!$F$2:$F$433,'[1]Capex CJI3'!$A$2:$A$433,$A17,'[1]Capex CJI3'!$K$2:$K$433,2026,'[1]Capex CJI3'!$J$2:$J$433,"*Reclass internal hours*") -> 0 | G17: {=SUMPRODUCT(('[1]Capex CJI3'!$A$2:$A$433=$A17)*(IFERROR(VALUE('[1]Capex CJI3'!$K$2:$K$433),0)=2026)*(LEN('[1]Capex CJI3'!$E$2:$E$433)>0)*ISERROR(SEARCH("Reclass internal hours",'[1]Capex CJI3'!$J$2:$J$433))*IFERROR(VALUE('[1]Capex CJI3'!$F$2:$F$433),0))-IF($A17="O7941/2517",'[1]Capex CJI3'!$F$124,0)-IF($A17="O7941/2613",'[1]Capex CJI3'!$F$313,0)} -> 0 | H17: {=SUMPRODUCT(('[1]Capex CJI3'!$A$2:$A$433=$A17)*(IFERROR(VALUE('[1]Capex CJI3'!$K$2:$K$433),0)=2026)*(LEN('[1]Capex CJI3'!$E$2:$E$433)=0)*ISERROR(SEARCH("Reclass internal hours",'[1]Capex CJI3'!$J$2:$J$433))*ISERROR(SEARCH("WBS Correction",'[1]Capex CJI3'!$J$2:$J$433))*('[1]Capex CJI3'!$D$2:$D$433<>"6405000000")*((($A17<>"O7941/2513")+('[1]Capex CJI3'!$D$2:$D$433<>"7405000000")+(IFERROR(VALUE('[1]Capex CJI3'!$L$2:$L$433),0)>=3))>0)*IFERROR(VALUE('[1]Capex CJI3'!$F$2:$F$433),0))-IF($A17="O7941/2517",'[1]Capex CJI3'!$F$132,0)-IF($A17="O9100/2601",'[1]Capex CJI3'!$F$429,0)} -> 11745 | I17: =SUM(F17:H17) -> 11745 | J17: =E17+I17 -> 11745 | K17: 46265 | L17: {=SUMPRODUCT(('[1]Capex CJI3'!$A$2:$A$433=$A17)*(IFERROR(VALUE('[1]Capex CJI3'!$K$2:$K$433),0)>0)*((ISNUMBER(SEARCH("Reclass internal hours",'[1]Capex CJI3'!$J$2:$J$433)))+((LEN('[1]Capex CJI3'!$E$2:$E$433)>0)*ISERROR(SEARCH("Reclass internal hours",'[1]Capex CJI3'!$J$2:$J$433)))+((LEN('[1]Capex CJI3'!$E$2:$E$433)=0)*ISERROR(SEARCH("Reclass internal hours",'[1]Capex CJI3'!$J$2:$J$433))*ISERROR(SEARCH("WBS Correction",'[1]Capex CJI3'!$J$2:$J$433))*('[1]Capex CJI3'!$D$2:$D$433<>"6405000000"))>0))-IF($A17="O7941/2517",2,0)-IF($A17="O7941/2613",1,0)-IF($A17="O9100/2601",1,0)-IF($A17="O7941/2513",4,0)} -> 5 | M17: {=SUMPRODUCT(('[1]Capex CJI3'!$A$2:$A$433=$A17)*(IFERROR(VALUE('[1]Capex CJI3'!$K$2:$K$433),0)>0)*(LEN('[1]Capex CJI3'!$E$2:$E$433)>0)*ISERROR(SEARCH("Reclass internal hours",'[1]Capex CJI3'!$J$2:$J$433)))-IF($A17="O7941/2517",1,0)-IF($A17="O7941/2613",1,0)} -> 0 | N17: EUR
A18: O7941/2524/4 | B18: =SUMIFS('[1]Capex CJI3'!$F$2:$F$433,'[1]Capex CJI3'!$A$2:$A$433,$A18,'[1]Capex CJI3'!$K$2:$K$433,2025,'[1]Capex CJI3'!$J$2:$J$433,"*Reclass internal hours*") -> 0 | C18: {=SUMPRODUCT(('[1]Capex CJI3'!$A$2:$A$433=$A18)*(IFERROR(VALUE('[1]Capex CJI3'!$K$2:$K$433),0)=2025)*(LEN('[1]Capex CJI3'!$E$2:$E$433)>0)*ISERROR(SEARCH("Reclass internal hours",'[1]Capex CJI3'!$J$2:$J$433))*IFERROR(VALUE('[1]Capex CJI3'!$F$2:$F$433),0))} -> 0 | D18: {=SUMPRODUCT(('[1]Capex CJI3'!$A$2:$A$433=$A18)*(IFERROR(VALUE('[1]Capex CJI3'!$K$2:$K$433),0)=2025)*(LEN('[1]Capex CJI3'!$E$2:$E$433)=0)*ISERROR(SEARCH("Reclass internal hours",'[1]Capex CJI3'!$J$2:$J$433))*ISERROR(SEARCH("WBS Correction",'[1]Capex CJI3'!$J$2:$J$433))*('[1]Capex CJI3'!$D$2:$D$433<>"6405000000")*IFERROR(VALUE('[1]Capex CJI3'!$F$2:$F$433),0))} -> 0 | E18: =SUM(B18:D18) -> 0 | F18: =SUMIFS('[1]Capex CJI3'!$F$2:$F$433,'[1]Capex CJI3'!$A$2:$A$433,$A18,'[1]Capex CJI3'!$K$2:$K$433,2026,'[1]Capex CJI3'!$J$2:$J$433,"*Reclass internal hours*") -> 43090 | G18: {=SUMPRODUCT(('[1]Capex CJI3'!$A$2:$A$433=$A18)*(IFERROR(VALUE('[1]Capex CJI3'!$K$2:$K$433),0)=2026)*(LEN('[1]Capex CJI3'!$E$2:$E$433)>0)*ISERROR(SEARCH("Reclass internal hours",'[1]Capex CJI3'!$J$2:$J$433))*IFERROR(VALUE('[1]Capex CJI3'!$F$2:$F$433),0))-IF($A18="O7941/2517",'[1]Capex CJI3'!$F$124,0)-IF($A18="O7941/2613",'[1]Capex CJI3'!$F$313,0)} -> 14062.5 | H18: -14062.5 | I18: =SUM(F18:H18) -> 43090 | J18: =E18+I18 -> 43090 | K18: 46265 | L18: {=SUMPRODUCT(('[1]Capex CJI3'!$A$2:$A$433=$A18)*(IFERROR(VALUE('[1]Capex CJI3'!$K$2:$K$433),0)>0)*((ISNUMBER(SEARCH("Reclass internal hours",'[1]Capex CJI3'!$J$2:$J$433)))+((LEN('[1]Capex CJI3'!$E$2:$E$433)>0)*ISERROR(SEARCH("Reclass internal hours",'[1]Capex CJI3'!$J$2:$J$433)))+((LEN('[1]Capex CJI3'!$E$2:$E$433)=0)*ISERROR(SEARCH("Reclass internal hours",'[1]Capex CJI3'!$J$2:$J$433))*ISERROR(SEARCH("WBS Correction",'[1]Capex CJI3'!$J$2:$J$433))*('[1]Capex CJI3'!$D$2:$D$433<>"6405000000"))>0))-IF($A18="O7941/2517",2,0)-IF($A18="O7941/2613",1,0)-IF($A18="O9100/2601",1,0)-IF($A18="O7941/2513",4,0)} -> 9 | M18: {=SUMPRODUCT(('[1]Capex CJI3'!$A$2:$A$433=$A18)*(IFERROR(VALUE('[1]Capex CJI3'!$K$2:$K$433),0)>0)*(LEN('[1]Capex CJI3'!$E$2:$E$433)>0)*ISERROR(SEARCH("Reclass internal hours",'[1]Capex CJI3'!$J$2:$J$433)))-IF($A18="O7941/2517",1,0)-IF($A18="O7941/2613",1,0)} -> 2 | N18: EUR
A19: O7941/2524/5 | B19: =SUMIFS('[1]Capex CJI3'!$F$2:$F$433,'[1]Capex CJI3'!$A$2:$A$433,$A19,'[1]Capex CJI3'!$K$2:$K$433,2025,'[1]Capex CJI3'!$J$2:$J$433,"*Reclass internal hours*") -> 0 | C19: {=SUMPRODUCT(('[1]Capex CJI3'!$A$2:$A$433=$A19)*(IFERROR(VALUE('[1]Capex CJI3'!$K$2:$K$433),0)=2025)*(LEN('[1]Capex CJI3'!$E$2:$E$433)>0)*ISERROR(SEARCH("Reclass internal hours",'[1]Capex CJI3'!$J$2:$J$433))*IFERROR(VALUE('[1]Capex CJI3'!$F$2:$F$433),0))} -> 0 | D19: {=SUMPRODUCT(('[1]Capex CJI3'!$A$2:$A$433=$A19)*(IFERROR(VALUE('[1]Capex CJI3'!$K$2:$K$433),0)=2025)*(LEN('[1]Capex CJI3'!$E$2:$E$433)=0)*ISERROR(SEARCH("Reclass internal hours",'[1]Capex CJI3'!$J$2:$J$433))*ISERROR(SEARCH("WBS Correction",'[1]Capex CJI3'!$J$2:$J$433))*('[1]Capex CJI3'!$D$2:$D$433<>"6405000000")*IFERROR(VALUE('[1]Capex CJI3'!$F$2:$F$433),0))} -> 0 | E19: =SUM(B19:D19) -> 0 | F19: =SUMIFS('[1]Capex CJI3'!$F$2:$F$433,'[1]Capex CJI3'!$A$2:$A$433,$A19,'[1]Capex CJI3'!$K$2:$K$433,2026,'[1]Capex CJI3'!$J$2:$J$433,"*Reclass internal hours*") -> 0 | G19: {=SUMPRODUCT(('[1]Capex CJI3'!$A$2:$A$433=$A19)*(IFERROR(VALUE('[1]Capex CJI3'!$K$2:$K$433),0)=2026)*(LEN('[1]Capex CJI3'!$E$2:$E$433)>0)*ISERROR(SEARCH("Reclass internal hours",'[1]Capex CJI3'!$J$2:$J$433))*IFERROR(VALUE('[1]Capex CJI3'!$F$2:$F$433),0))-IF($A19="O7941/2517",'[1]Capex CJI3'!$F$124,0)-IF($A19="O7941/2613",'[1]Capex CJI3'!$F$313,0)} -> 2058.59 | H19: {=SUMPRODUCT(('[1]Capex CJI3'!$A$2:$A$433=$A19)*(IFERROR(VALUE('[1]Capex CJI3'!$K$2:$K$433),0)=2026)*(LEN('[1]Capex CJI3'!$E$2:$E$433)=0)*ISERROR(SEARCH("Reclass internal hours",'[1]Capex CJI3'!$J$2:$J$433))*ISERROR(SEARCH("WBS Correction",'[1]Capex CJI3'!$J$2:$J$433))*('[1]Capex CJI3'!$D$2:$D$433<>"6405000000")*((($A19<>"O7941/2513")+('[1]Capex CJI3'!$D$2:$D$433<>"7405000000")+(IFERROR(VALUE('[1]Capex CJI3'!$L$2:$L$433),0)>=3))>0)*IFERROR(VALUE('[1]Capex CJI3'!$F$2:$F$433),0))-IF($A19="O7941/2517",'[1]Capex CJI3'!$F$132,0)-IF($A19="O9100/2601",'[1]Capex CJI3'!$F$429,0)} -> 3155 | I19: =SUM(F19:H19) -> 5213.59 | J19: =E19+I19 -> 5213.59 | K19: 46237 | L19: {=SUMPRODUCT(('[1]Capex CJI3'!$A$2:$A$433=$A19)*(IFERROR(VALUE('[1]Capex CJI3'!$K$2:$K$433),0)>0)*((ISNUMBER(SEARCH("Reclass internal hours",'[1]Capex CJI3'!$J$2:$J$433)))+((LEN('[1]Capex CJI3'!$E$2:$E$433)>0)*ISERROR(SEARCH("Reclass internal hours",'[1]Capex CJI3'!$J$2:$J$433)))+((LEN('[1]Capex CJI3'!$E$2:$E$433)=0)*ISERROR(SEARCH("Reclass internal hours",'[1]Capex CJI3'!$J$2:$J$433))*ISERROR(SEARCH("WBS Correction",'[1]Capex CJI3'!$J$2:$J$433))*('[1]Capex CJI3'!$D$2:$D$433<>"6405000000"))>0))-IF($A19="O7941/2517",2,0)-IF($A19="O7941/2613",1,0)-IF($A19="O9100/2601",1,0)-IF($A19="O7941/2513",4,0)} -> 3 | M19: {=SUMPRODUCT(('[1]Capex CJI3'!$A$2:$A$433=$A19)*(IFERROR(VALUE('[1]Capex CJI3'!$K$2:$K$433),0)>0)*(LEN('[1]Capex CJI3'!$E$2:$E$433)>0)*ISERROR(SEARCH("Reclass internal hours",'[1]Capex CJI3'!$J$2:$J$433)))-IF($A19="O7941/2517",1,0)-IF($A19="O7941/2613",1,0)} -> 2 | N19: EUR
A20: O7941/2524/6 | B20: =SUMIFS('[1]Capex CJI3'!$F$2:$F$433,'[1]Capex CJI3'!$A$2:$A$433,$A20,'[1]Capex CJI3'!$K$2:$K$433,2025,'[1]Capex CJI3'!$J$2:$J$433,"*Reclass internal hours*") -> 0 | C20: {=SUMPRODUCT(('[1]Capex CJI3'!$A$2:$A$433=$A20)*(IFERROR(VALUE('[1]Capex CJI3'!$K$2:$K$433),0)=2025)*(LEN('[1]Capex CJI3'!$E$2:$E$433)>0)*ISERROR(SEARCH("Reclass internal hours",'[1]Capex CJI3'!$J$2:$J$433))*IFERROR(VALUE('[1]Capex CJI3'!$F$2:$F$433),0))} -> 0 | D20: {=SUMPRODUCT(('[1]Capex CJI3'!$A$2:$A$433=$A20)*(IFERROR(VALUE('[1]Capex CJI3'!$K$2:$K$433),0)=2025)*(LEN('[1]Capex CJI3'!$E$2:$E$433)=0)*ISERROR(SEARCH("Reclass internal hours",'[1]Capex CJI3'!$J$2:$J$433))*ISERROR(SEARCH("WBS Correction",'[1]Capex CJI3'!$J$2:$J$433))*('[1]Capex CJI3'!$D$2:$D$433<>"6405000000")*IFERROR(VALUE('[1]Capex CJI3'!$F$2:$F$433),0))} -> 0 | E20: =SUM(B20:D20) -> 0 | F20: =SUMIFS('[1]Capex CJI3'!$F$2:$F$433,'[1]Capex CJI3'!$A$2:$A$433,$A20,'[1]Capex CJI3'!$K$2:$K$433,2026,'[1]Capex CJI3'!$J$2:$J$433,"*Reclass internal hours*") -> 0 | G20: {=SUMPRODUCT(('[1]Capex CJI3'!$A$2:$A$433=$A20)*(IFERROR(VALUE('[1]Capex CJI3'!$K$2:$K$433),0)=2026)*(LEN('[1]Capex CJI3'!$E$2:$E$433)>0)*ISERROR(SEARCH("Reclass internal hours",'[1]Capex CJI3'!$J$2:$J$433))*IFERROR(VALUE('[1]Capex CJI3'!$F$2:$F$433),0))-IF($A20="O7941/2517",'[1]Capex CJI3'!$F$124,0)-IF($A20="O7941/2613",'[1]Capex CJI3'!$F$313,0)} -> 5378.23 | H20: {=SUMPRODUCT(('[1]Capex CJI3'!$A$2:$A$433=$A20)*(IFERROR(VALUE('[1]Capex CJI3'!$K$2:$K$433),0)=2026)*(LEN('[1]Capex CJI3'!$E$2:$E$433)=0)*ISERROR(SEARCH("Reclass internal hours",'[1]Capex CJI3'!$J$2:$J$433))*ISERROR(SEARCH("WBS Correction",'[1]Capex CJI3'!$J$2:$J$433))*('[1]Capex CJI3'!$D$2:$D$433<>"6405000000")*((($A20<>"O7941/2513")+('[1]Capex CJI3'!$D$2:$D$433<>"7405000000")+(IFERROR(VALUE('[1]Capex CJI3'!$L$2:$L$433),0)>=3))>0)*IFERROR(VALUE('[1]Capex CJI3'!$F$2:$F$433),0))-IF($A20="O7941/2517",'[1]Capex CJI3'!$F$132,0)-IF($A20="O9100/2601",'[1]Capex CJI3'!$F$429,0)} -> 0 | I20: =SUM(F20:H20) -> 5378.23 | J20: =E20+I20 -> 5378.23 | K20: 46212 | L20: {=SUMPRODUCT(('[1]Capex CJI3'!$A$2:$A$433=$A20)*(IFERROR(VALUE('[1]Capex CJI3'!$K$2:$K$433),0)>0)*((ISNUMBER(SEARCH("Reclass internal hours",'[1]Capex CJI3'!$J$2:$J$433)))+((LEN('[1]Capex CJI3'!$E$2:$E$433)>0)*ISERROR(SEARCH("Reclass internal hours",'[1]Capex CJI3'!$J$2:$J$433)))+((LEN('[1]Capex CJI3'!$E$2:$E$433)=0)*ISERROR(SEARCH("Reclass internal hours",'[1]Capex CJI3'!$J$2:$J$433))*ISERROR(SEARCH("WBS Correction",'[1]Capex CJI3'!$J$2:$J$433))*('[1]Capex CJI3'!$D$2:$D$433<>"6405000000"))>0))-IF($A20="O7941/2517",2,0)-IF($A20="O7941/2613",1,0)-IF($A20="O9100/2601",1,0)-IF($A20="O7941/2513",4,0)} -> 1 | M20: {=SUMPRODUCT(('[1]Capex CJI3'!$A$2:$A$433=$A20)*(IFERROR(VALUE('[1]Capex CJI3'!$K$2:$K$433),0)>0)*(LEN('[1]Capex CJI3'!$E$2:$E$433)>0)*ISERROR(SEARCH("Reclass internal hours",'[1]Capex CJI3'!$J$2:$J$433)))-IF($A20="O7941/2517",1,0)-IF($A20="O7941/2613",1,0)} -> 1 | N20: EUR
A21: O7941/2524/7 | B21: =SUMIFS('[1]Capex CJI3'!$F$2:$F$433,'[1]Capex CJI3'!$A$2:$A$433,$A21,'[1]Capex CJI3'!$K$2:$K$433,2025,'[1]Capex CJI3'!$J$2:$J$433,"*Reclass internal hours*") -> 0 | C21: {=SUMPRODUCT(('[1]Capex CJI3'!$A$2:$A$433=$A21)*(IFERROR(VALUE('[1]Capex CJI3'!$K$2:$K$433),0)=2025)*(LEN('[1]Capex CJI3'!$E$2:$E$433)>0)*ISERROR(SEARCH("Reclass internal hours",'[1]Capex CJI3'!$J$2:$J$433))*IFERROR(VALUE('[1]Capex CJI3'!$F$2:$F$433),0))} -> 0 | D21: {=SUMPRODUCT(('[1]Capex CJI3'!$A$2:$A$433=$A21)*(IFERROR(VALUE('[1]Capex CJI3'!$K$2:$K$433),0)=2025)*(LEN('[1]Capex CJI3'!$E$2:$E$433)=0)*ISERROR(SEARCH("Reclass internal hours",'[1]Capex CJI3'!$J$2:$J$433))*ISERROR(SEARCH("WBS Correction",'[1]Capex CJI3'!$J$2:$J$433))*('[1]Capex CJI3'!$D$2:$D$433<>"6405000000")*IFERROR(VALUE('[1]Capex CJI3'!$F$2:$F$433),0))} -> 0 | E21: =SUM(B21:D21) -> 0 | F21: =SUMIFS('[1]Capex CJI3'!$F$2:$F$433,'[1]Capex CJI3'!$A$2:$A$433,$A21,'[1]Capex CJI3'!$K$2:$K$433,2026,'[1]Capex CJI3'!$J$2:$J$433,"*Reclass internal hours*") -> 0 | G21: {=SUMPRODUCT(('[1]Capex CJI3'!$A$2:$A$433=$A21)*(IFERROR(VALUE('[1]Capex CJI3'!$K$2:$K$433),0)=2026)*(LEN('[1]Capex CJI3'!$E$2:$E$433)>0)*ISERROR(SEARCH("Reclass internal hours",'[1]Capex CJI3'!$J$2:$J$433))*IFERROR(VALUE('[1]Capex CJI3'!$F$2:$F$433),0))-IF($A21="O7941/2517",'[1]Capex CJI3'!$F$124,0)-IF($A21="O7941/2613",'[1]Capex CJI3'!$F$313,0)} -> 0 | H21: {=SUMPRODUCT(('[1]Capex CJI3'!$A$2:$A$433=$A21)*(IFERROR(VALUE('[1]Capex CJI3'!$K$2:$K$433),0)=2026)*(LEN('[1]Capex CJI3'!$E$2:$E$433)=0)*ISERROR(SEARCH("Reclass internal hours",'[1]Capex CJI3'!$J$2:$J$433))*ISERROR(SEARCH("WBS Correction",'[1]Capex CJI3'!$J$2:$J$433))*('[1]Capex CJI3'!$D$2:$D$433<>"6405000000")*((($A21<>"O7941/2513")+('[1]Capex CJI3'!$D$2:$D$433<>"7405000000")+(IFERROR(VALUE('[1]Capex CJI3'!$L$2:$L$433),0)>=3))>0)*IFERROR(VALUE('[1]Capex CJI3'!$F$2:$F$433),0))-IF($A21="O7941/2517",'[1]Capex CJI3'!$F$132,0)-IF($A21="O9100/2601",'[1]Capex CJI3'!$F$429,0)} -> 14062.5 | I21: =SUM(F21:H21) -> 14062.5 | J21: =E21+I21 -> 14062.5 | K21: 46265 | L21: {=SUMPRODUCT(('[1]Capex CJI3'!$A$2:$A$433=$A21)*(IFERROR(VALUE('[1]Capex CJI3'!$K$2:$K$433),0)>0)*((ISNUMBER(SEARCH("Reclass internal hours",'[1]Capex CJI3'!$J$2:$J$433)))+((LEN('[1]Capex CJI3'!$E$2:$E$433)>0)*ISERROR(SEARCH("Reclass internal hours",'[1]Capex CJI3'!$J$2:$J$433)))+((LEN('[1]Capex CJI3'!$E$2:$E$433)=0)*ISERROR(SEARCH("Reclass internal hours",'[1]Capex CJI3'!$J$2:$J$433))*ISERROR(SEARCH("WBS Correction",'[1]Capex CJI3'!$J$2:$J$433))*('[1]Capex CJI3'!$D$2:$D$433<>"6405000000"))>0))-IF($A21="O7941/2517",2,0)-IF($A21="O7941/2613",1,0)-IF($A21="O9100/2601",1,0)-IF($A21="O7941/2513",4,0)} -> 1 | M21: {=SUMPRODUCT(('[1]Capex CJI3'!$A$2:$A$433=$A21)*(IFERROR(VALUE('[1]Capex CJI3'!$K$2:$K$433),0)>0)*(LEN('[1]Capex CJI3'!$E$2:$E$433)>0)*ISERROR(SEARCH("Reclass internal hours",'[1]Capex CJI3'!$J$2:$J$433)))-IF($A21="O7941/2517",1,0)-IF($A21="O7941/2613",1,0)} -> 0 | N21: EUR
A22: O7941/2603 | B22: =SUMIFS('[1]Capex CJI3'!$F$2:$F$433,'[1]Capex CJI3'!$A$2:$A$433,$A22,'[1]Capex CJI3'!$K$2:$K$433,2025,'[1]Capex CJI3'!$J$2:$J$433,"*Reclass internal hours*") -> 0 | C22: {=SUMPRODUCT(('[1]Capex CJI3'!$A$2:$A$433=$A22)*(IFERROR(VALUE('[1]Capex CJI3'!$K$2:$K$433),0)=2025)*(LEN('[1]Capex CJI3'!$E$2:$E$433)>0)*ISERROR(SEARCH("Reclass internal hours",'[1]Capex CJI3'!$J$2:$J$433))*IFERROR(VALUE('[1]Capex CJI3'!$F$2:$F$433),0))} -> 0 | D22: {=SUMPRODUCT(('[1]Capex CJI3'!$A$2:$A$433=$A22)*(IFERROR(VALUE('[1]Capex CJI3'!$K$2:$K$433),0)=2025)*(LEN('[1]Capex CJI3'!$E$2:$E$433)=0)*ISERROR(SEARCH("Reclass internal hours",'[1]Capex CJI3'!$J$2:$J$433))*ISERROR(SEARCH("WBS Correction",'[1]Capex CJI3'!$J$2:$J$433))*('[1]Capex CJI3'!$D$2:$D$433<>"6405000000")*IFERROR(VALUE('[1]Capex CJI3'!$F$2:$F$433),0))} -> 0 | E22: =SUM(B22:D22) -> 0 | F22: =SUMIFS('[1]Capex CJI3'!$F$2:$F$433,'[1]Capex CJI3'!$A$2:$A$433,$A22,'[1]Capex CJI3'!$K$2:$K$433,2026,'[1]Capex CJI3'!$J$2:$J$433,"*Reclass internal hours*") -> 15650 | G22: {=SUMPRODUCT(('[1]Capex CJI3'!$A$2:$A$433=$A22)*(IFERROR(VALUE('[1]Capex CJI3'!$K$2:$K$433),0)=2026)*(LEN('[1]Capex CJI3'!$E$2:$E$433)>0)*ISERROR(SEARCH("Reclass internal hours",'[1]Capex CJI3'!$J$2:$J$433))*IFERROR(VALUE('[1]Capex CJI3'!$F$2:$F$433),0))-IF($A22="O7941/2517",'[1]Capex CJI3'!$F$124,0)-IF($A22="O7941/2613",'[1]Capex CJI3'!$F$313,0)} -> 84480.53 | H22: -3073 | I22: =SUM(F22:H22) -> 97057.53 | J22: =E22+I22 -> 97057.53 | K22: 46274 | L22: {=SUMPRODUCT(('[1]Capex CJI3'!$A$2:$A$433=$A22)*(IFERROR(VALUE('[1]Capex CJI3'!$K$2:$K$433),0)>0)*((ISNUMBER(SEARCH("Reclass internal hours",'[1]Capex CJI3'!$J$2:$J$433)))+((LEN('[1]Capex CJI3'!$E$2:$E$433)>0)*ISERROR(SEARCH("Reclass internal hours",'[1]Capex CJI3'!$J$2:$J$433)))+((LEN('[1]Capex CJI3'!$E$2:$E$433)=0)*ISERROR(SEARCH("Reclass internal hours",'[1]Capex CJI3'!$J$2:$J$433))*ISERROR(SEARCH("WBS Correction",'[1]Capex CJI3'!$J$2:$J$433))*('[1]Capex CJI3'!$D$2:$D$433<>"6405000000"))>0))-IF($A22="O7941/2517",2,0)-IF($A22="O7941/2613",1,0)-IF($A22="O9100/2601",1,0)-IF($A22="O7941/2513",4,0)} -> 17 | M22: {=SUMPRODUCT(('[1]Capex CJI3'!$A$2:$A$433=$A22)*(IFERROR(VALUE('[1]Capex CJI3'!$K$2:$K$433),0)>0)*(LEN('[1]Capex CJI3'!$E$2:$E$433)>0)*ISERROR(SEARCH("Reclass internal hours",'[1]Capex CJI3'!$J$2:$J$433)))-IF($A22="O7941/2517",1,0)-IF($A22="O7941/2613",1,0)} -> 13 | N22: EUR | O22: =J22 -> 97057.53
A23: O7941/2604 | B23: =SUMIFS('[1]Capex CJI3'!$F$2:$F$433,'[1]Capex CJI3'!$A$2:$A$433,$A23,'[1]Capex CJI3'!$K$2:$K$433,2025,'[1]Capex CJI3'!$J$2:$J$433,"*Reclass internal hours*") -> 0 | C23: {=SUMPRODUCT(('[1]Capex CJI3'!$A$2:$A$433=$A23)*(IFERROR(VALUE('[1]Capex CJI3'!$K$2:$K$433),0)=2025)*(LEN('[1]Capex CJI3'!$E$2:$E$433)>0)*ISERROR(SEARCH("Reclass internal hours",'[1]Capex CJI3'!$J$2:$J$433))*IFERROR(VALUE('[1]Capex CJI3'!$F$2:$F$433),0))} -> 0 | D23: {=SUMPRODUCT(('[1]Capex CJI3'!$A$2:$A$433=$A23)*(IFERROR(VALUE('[1]Capex CJI3'!$K$2:$K$433),0)=2025)*(LEN('[1]Capex CJI3'!$E$2:$E$433)=0)*ISERROR(SEARCH("Reclass internal hours",'[1]Capex CJI3'!$J$2:$J$433))*ISERROR(SEARCH("WBS Correction",'[1]Capex CJI3'!$J$2:$J$433))*('[1]Capex CJI3'!$D$2:$D$433<>"6405000000")*IFERROR(VALUE('[1]Capex CJI3'!$F$2:$F$433),0))} -> 0 | E23: =SUM(B23:D23) -> 0 | F23: =SUMIFS('[1]Capex CJI3'!$F$2:$F$433,'[1]Capex CJI3'!$A$2:$A$433,$A23,'[1]Capex CJI3'!$K$2:$K$433,2026,'[1]Capex CJI3'!$J$2:$J$433,"*Reclass internal hours*") -> 38000 | G23: {=SUMPRODUCT(('[1]Capex CJI3'!$A$2:$A$433=$A23)*(IFERROR(VALUE('[1]Capex CJI3'!$K$2:$K$433),0)=2026)*(LEN('[1]Capex CJI3'!$E$2:$E$433)>0)*ISERROR(SEARCH("Reclass internal hours",'[1]Capex CJI3'!$J$2:$J$433))*IFERROR(VALUE('[1]Capex CJI3'!$F$2:$F$433),0))-IF($A23="O7941/2517",'[1]Capex CJI3'!$F$124,0)-IF($A23="O7941/2613",'[1]Capex CJI3'!$F$313,0)} -> 3583.96 | H23: {=SUMPRODUCT(('[1]Capex CJI3'!$A$2:$A$433=$A23)*(IFERROR(VALUE('[1]Capex CJI3'!$K$2:$K$433),0)=2026)*(LEN('[1]Capex CJI3'!$E$2:$E$433)=0)*ISERROR(SEARCH("Reclass internal hours",'[1]Capex CJI3'!$J$2:$J$433))*ISERROR(SEARCH("WBS Correction",'[1]Capex CJI3'!$J$2:$J$433))*('[1]Capex CJI3'!$D$2:$D$433<>"6405000000")*((($A23<>"O7941/2513")+('[1]Capex CJI3'!$D$2:$D$433<>"7405000000")+(IFERROR(VALUE('[1]Capex CJI3'!$L$2:$L$433),0)>=3))>0)*IFERROR(VALUE('[1]Capex CJI3'!$F$2:$F$433),0))-IF($A23="O7941/2517",'[1]Capex CJI3'!$F$132,0)-IF($A23="O9100/2601",'[1]Capex CJI3'!$F$429,0)} -> 0 | I23: =SUM(F23:H23) -> 41583.96 | J23: =E23+I23 -> 41583.96 | K23: 46265 | L23: {=SUMPRODUCT(('[1]Capex CJI3'!$A$2:$A$433=$A23)*(IFERROR(VALUE('[1]Capex CJI3'!$K$2:$K$433),0)>0)*((ISNUMBER(SEARCH("Reclass internal hours",'[1]Capex CJI3'!$J$2:$J$433)))+((LEN('[1]Capex CJI3'!$E$2:$E$433)>0)*ISERROR(SEARCH("Reclass internal hours",'[1]Capex CJI3'!$J$2:$J$433)))+((LEN('[1]Capex CJI3'!$E$2:$E$433)=0)*ISERROR(SEARCH("Reclass internal hours",'[1]Capex CJI3'!$J$2:$J$433))*ISERROR(SEARCH("WBS Correction",'[1]Capex CJI3'!$J$2:$J$433))*('[1]Capex CJI3'!$D$2:$D$433<>"6405000000"))>0))-IF($A23="O7941/2517",2,0)-IF($A23="O7941/2613",1,0)-IF($A23="O9100/2601",1,0)-IF($A23="O7941/2513",4,0)} -> 10 | M23: {=SUMPRODUCT(('[1]Capex CJI3'!$A$2:$A$433=$A23)*(IFERROR(VALUE('[1]Capex CJI3'!$K$2:$K$433),0)>0)*(LEN('[1]Capex CJI3'!$E$2:$E$433)>0)*ISERROR(SEARCH("Reclass internal hours",'[1]Capex CJI3'!$J$2:$J$433)))-IF($A23="O7941/2517",1,0)-IF($A23="O7941/2613",1,0)} -> 3 | N23: EUR | O23: 116424
A24: O7941/2605 | B24: =SUMIFS('[1]Capex CJI3'!$F$2:$F$433,'[1]Capex CJI3'!$A$2:$A$433,$A24,'[1]Capex CJI3'!$K$2:$K$433,2025,'[1]Capex CJI3'!$J$2:$J$433,"*Reclass internal hours*") -> 0 | C24: {=SUMPRODUCT(('[1]Capex CJI3'!$A$2:$A$433=$A24)*(IFERROR(VALUE('[1]Capex CJI3'!$K$2:$K$433),0)=2025)*(LEN('[1]Capex CJI3'!$E$2:$E$433)>0)*ISERROR(SEARCH("Reclass internal hours",'[1]Capex CJI3'!$J$2:$J$433))*IFERROR(VALUE('[1]Capex CJI3'!$F$2:$F$433),0))} -> 0 | D24: {=SUMPRODUCT(('[1]Capex CJI3'!$A$2:$A$433=$A24)*(IFERROR(VALUE('[1]Capex CJI3'!$K$2:$K$433),0)=2025)*(LEN('[1]Capex CJI3'!$E$2:$E$433)=0)*ISERROR(SEARCH("Reclass internal hours",'[1]Capex CJI3'!$J$2:$J$433))*ISERROR(SEARCH("WBS Correction",'[1]Capex CJI3'!$J$2:$J$433))*('[1]Capex CJI3'!$D$2:$D$433<>"6405000000")*IFERROR(VALUE('[1]Capex CJI3'!$F$2:$F$433),0))} -> 0 | E24: =SUM(B24:D24) -> 0 | F24: =SUMIFS('[1]Capex CJI3'!$F$2:$F$433,'[1]Capex CJI3'!$A$2:$A$433,$A24,'[1]Capex CJI3'!$K$2:$K$433,2026,'[1]Capex CJI3'!$J$2:$J$433,"*Reclass internal hours*") -> 0 | G24: {=SUMPRODUCT(('[1]Capex CJI3'!$A$2:$A$433=$A24)*(IFERROR(VALUE('[1]Capex CJI3'!$K$2:$K$433),0)=2026)*(LEN('[1]Capex CJI3'!$E$2:$E$433)>0)*ISERROR(SEARCH("Reclass internal hours",'[1]Capex CJI3'!$J$2:$J$433))*IFERROR(VALUE('[1]Capex CJI3'!$F$2:$F$433),0))-IF($A24="O7941/2517",'[1]Capex CJI3'!$F$124,0)-IF($A24="O7941/2613",'[1]Capex CJI3'!$F$313,0)} -> 50000 | H24: {=SUMPRODUCT(('[1]Capex CJI3'!$A$2:$A$433=$A24)*(IFERROR(VALUE('[1]Capex CJI3'!$K$2:$K$433),0)=2026)*(LEN('[1]Capex CJI3'!$E$2:$E$433)=0)*ISERROR(SEARCH("Reclass internal hours",'[1]Capex CJI3'!$J$2:$J$433))*ISERROR(SEARCH("WBS Correction",'[1]Capex CJI3'!$J$2:$J$433))*('[1]Capex CJI3'!$D$2:$D$433<>"6405000000")*((($A24<>"O7941/2513")+('[1]Capex CJI3'!$D$2:$D$433<>"7405000000")+(IFERROR(VALUE('[1]Capex CJI3'!$L$2:$L$433),0)>=3))>0)*IFERROR(VALUE('[1]Capex CJI3'!$F$2:$F$433),0))-IF($A24="O7941/2517",'[1]Capex CJI3'!$F$132,0)-IF($A24="O9100/2601",'[1]Capex CJI3'!$F$429,0)} -> 0 | I24: =SUM(F24:H24) -> 50000 | J24: =E24+I24 -> 50000 | K24: 46188 | L24: {=SUMPRODUCT(('[1]Capex CJI3'!$A$2:$A$433=$A24)*(IFERROR(VALUE('[1]Capex CJI3'!$K$2:$K$433),0)>0)*((ISNUMBER(SEARCH("Reclass internal hours",'[1]Capex CJI3'!$J$2:$J$433)))+((LEN('[1]Capex CJI3'!$E$2:$E$433)>0)*ISERROR(SEARCH("Reclass internal hours",'[1]Capex CJI3'!$J$2:$J$433)))+((LEN('[1]Capex CJI3'!$E$2:$E$433)=0)*ISERROR(SEARCH("Reclass internal hours",'[1]Capex CJI3'!$J$2:$J$433))*ISERROR(SEARCH("WBS Correction",'[1]Capex CJI3'!$J$2:$J$433))*('[1]Capex CJI3'!$D$2:$D$433<>"6405000000"))>0))-IF($A24="O7941/2517",2,0)-IF($A24="O7941/2613",1,0)-IF($A24="O9100/2601",1,0)-IF($A24="O7941/2513",4,0)} -> 5 | M24: {=SUMPRODUCT(('[1]Capex CJI3'!$A$2:$A$433=$A24)*(IFERROR(VALUE('[1]Capex CJI3'!$K$2:$K$433),0)>0)*(LEN('[1]Capex CJI3'!$E$2:$E$433)>0)*ISERROR(SEARCH("Reclass internal hours",'[1]Capex CJI3'!$J$2:$J$433)))-IF($A24="O7941/2517",1,0)-IF($A24="O7941/2613",1,0)} -> 5 | N24: EUR | O24: 50000
A25: O7941/2606 | B25: =SUMIFS('[1]Capex CJI3'!$F$2:$F$433,'[1]Capex CJI3'!$A$2:$A$433,$A25,'[1]Capex CJI3'!$K$2:$K$433,2025,'[1]Capex CJI3'!$J$2:$J$433,"*Reclass internal hours*") -> 0 | C25: {=SUMPRODUCT(('[1]Capex CJI3'!$A$2:$A$433=$A25)*(IFERROR(VALUE('[1]Capex CJI3'!$K$2:$K$433),0)=2025)*(LEN('[1]Capex CJI3'!$E$2:$E$433)>0)*ISERROR(SEARCH("Reclass internal hours",'[1]Capex CJI3'!$J$2:$J$433))*IFERROR(VALUE('[1]Capex CJI3'!$F$2:$F$433),0))} -> 0 | D25: {=SUMPRODUCT(('[1]Capex CJI3'!$A$2:$A$433=$A25)*(IFERROR(VALUE('[1]Capex CJI3'!$K$2:$K$433),0)=2025)*(LEN('[1]Capex CJI3'!$E$2:$E$433)=0)*ISERROR(SEARCH("Reclass internal hours",'[1]Capex CJI3'!$J$2:$J$433))*ISERROR(SEARCH("WBS Correction",'[1]Capex CJI3'!$J$2:$J$433))*('[1]Capex CJI3'!$D$2:$D$433<>"6405000000")*IFERROR(VALUE('[1]Capex CJI3'!$F$2:$F$433),0))} -> 0 | E25: =SUM(B25:D25) -> 0 | F25: =SUMIFS('[1]Capex CJI3'!$F$2:$F$433,'[1]Capex CJI3'!$A$2:$A$433,$A25,'[1]Capex CJI3'!$K$2:$K$433,2026,'[1]Capex CJI3'!$J$2:$J$433,"*Reclass internal hours*") -> 0 | G25: {=SUMPRODUCT(('[1]Capex CJI3'!$A$2:$A$433=$A25)*(IFERROR(VALUE('[1]Capex CJI3'!$K$2:$K$433),0)=2026)*(LEN('[1]Capex CJI3'!$E$2:$E$433)>0)*ISERROR(SEARCH("Reclass internal hours",'[1]Capex CJI3'!$J$2:$J$433))*IFERROR(VALUE('[1]Capex CJI3'!$F$2:$F$433),0))-IF($A25="O7941/2517",'[1]Capex CJI3'!$F$124,0)-IF($A25="O7941/2613",'[1]Capex CJI3'!$F$313,0)} -> 32500 | H25: {=SUMPRODUCT(('[1]Capex CJI3'!$A$2:$A$433=$A25)*(IFERROR(VALUE('[1]Capex CJI3'!$K$2:$K$433),0)=2026)*(LEN('[1]Capex CJI3'!$E$2:$E$433)=0)*ISERROR(SEARCH("Reclass internal hours",'[1]Capex CJI3'!$J$2:$J$433))*ISERROR(SEARCH("WBS Correction",'[1]Capex CJI3'!$J$2:$J$433))*('[1]Capex CJI3'!$D$2:$D$433<>"6405000000")*((($A25<>"O7941/2513")+('[1]Capex CJI3'!$D$2:$D$433<>"7405000000")+(IFERROR(VALUE('[1]Capex CJI3'!$L$2:$L$433),0)>=3))>0)*IFERROR(VALUE('[1]Capex CJI3'!$F$2:$F$433),0))-IF($A25="O7941/2517",'[1]Capex CJI3'!$F$132,0)-IF($A25="O9100/2601",'[1]Capex CJI3'!$F$429,0)} -> 0 | I25: =SUM(F25:H25) -> 32500 | J25: =E25+I25 -> 32500 | K25: 46085 | L25: {=SUMPRODUCT(('[1]Capex CJI3'!$A$2:$A$433=$A25)*(IFERROR(VALUE('[1]Capex CJI3'!$K$2:$K$433),0)>0)*((ISNUMBER(SEARCH("Reclass internal hours",'[1]Capex CJI3'!$J$2:$J$433)))+((LEN('[1]Capex CJI3'!$E$2:$E$433)>0)*ISERROR(SEARCH("Reclass internal hours",'[1]Capex CJI3'!$J$2:$J$433)))+((LEN('[1]Capex CJI3'!$E$2:$E$433)=0)*ISERROR(SEARCH("Reclass internal hours",'[1]Capex CJI3'!$J$2:$J$433))*ISERROR(SEARCH("WBS Correction",'[1]Capex CJI3'!$J$2:$J$433))*('[1]Capex CJI3'!$D$2:$D$433<>"6405000000"))>0))-IF($A25="O7941/2517",2,0)-IF($A25="O7941/2613",1,0)-IF($A25="O9100/2601",1,0)-IF($A25="O7941/2513",4,0)} -> 2 | M25: {=SUMPRODUCT(('[1]Capex CJI3'!$A$2:$A$433=$A25)*(IFERROR(VALUE('[1]Capex CJI3'!$K$2:$K$433),0)>0)*(LEN('[1]Capex CJI3'!$E$2:$E$433)>0)*ISERROR(SEARCH("Reclass internal hours",'[1]Capex CJI3'!$J$2:$J$433)))-IF($A25="O7941/2517",1,0)-IF($A25="O7941/2613",1,0)} -> 2 | N25: EUR | O25: 135470
A26: O7941/2607 | B26: =SUMIFS('[1]Capex CJI3'!$F$2:$F$433,'[1]Capex CJI3'!$A$2:$A$433,$A26,'[1]Capex CJI3'!$K$2:$K$433,2025,'[1]Capex CJI3'!$J$2:$J$433,"*Reclass internal hours*") -> 0 | C26: {=SUMPRODUCT(('[1]Capex CJI3'!$A$2:$A$433=$A26)*(IFERROR(VALUE('[1]Capex CJI3'!$K$2:$K$433),0)=2025)*(LEN('[1]Capex CJI3'!$E$2:$E$433)>0)*ISERROR(SEARCH("Reclass internal hours",'[1]Capex CJI3'!$J$2:$J$433))*IFERROR(VALUE('[1]Capex CJI3'!$F$2:$F$433),0))} -> 0 | D26: {=SUMPRODUCT(('[1]Capex CJI3'!$A$2:$A$433=$A26)*(IFERROR(VALUE('[1]Capex CJI3'!$K$2:$K$433),0)=2025)*(LEN('[1]Capex CJI3'!$E$2:$E$433)=0)*ISERROR(SEARCH("Reclass internal hours",'[1]Capex CJI3'!$J$2:$J$433))*ISERROR(SEARCH("WBS Correction",'[1]Capex CJI3'!$J$2:$J$433))*('[1]Capex CJI3'!$D$2:$D$433<>"6405000000")*IFERROR(VALUE('[1]Capex CJI3'!$F$2:$F$433),0))} -> 0 | E26: =SUM(B26:D26) -> 0 | F26: =SUMIFS('[1]Capex CJI3'!$F$2:$F$433,'[1]Capex CJI3'!$A$2:$A$433,$A26,'[1]Capex CJI3'!$K$2:$K$433,2026,'[1]Capex CJI3'!$J$2:$J$433,"*Reclass internal hours*") -> 191538 | G26: {=SUMPRODUCT(('[1]Capex CJI3'!$A$2:$A$433=$A26)*(IFERROR(VALUE('[1]Capex CJI3'!$K$2:$K$433),0)=2026)*(LEN('[1]Capex CJI3'!$E$2:$E$433)>0)*ISERROR(SEARCH("Reclass internal hours",'[1]Capex CJI3'!$J$2:$J$433))*IFERROR(VALUE('[1]Capex CJI3'!$F$2:$F$433),0))-IF($A26="O7941/2517",'[1]Capex CJI3'!$F$124,0)-IF($A26="O7941/2613",'[1]Capex CJI3'!$F$313,0)} -> 0 | H26: {=SUMPRODUCT(('[1]Capex CJI3'!$A$2:$A$433=$A26)*(IFERROR(VALUE('[1]Capex CJI3'!$K$2:$K$433),0)=2026)*(LEN('[1]Capex CJI3'!$E$2:$E$433)=0)*ISERROR(SEARCH("Reclass internal hours",'[1]Capex CJI3'!$J$2:$J$433))*ISERROR(SEARCH("WBS Correction",'[1]Capex CJI3'!$J$2:$J$433))*('[1]Capex CJI3'!$D$2:$D$433<>"6405000000")*((($A26<>"O7941/2513")+('[1]Capex CJI3'!$D$2:$D$433<>"7405000000")+(IFERROR(VALUE('[1]Capex CJI3'!$L$2:$L$433),0)>=3))>0)*IFERROR(VALUE('[1]Capex CJI3'!$F$2:$F$433),0))-IF($A26="O7941/2517",'[1]Capex CJI3'!$F$132,0)-IF($A26="O9100/2601",'[1]Capex CJI3'!$F$429,0)} -> 0 | I26: =SUM(F26:H26) -> 191538 | J26: =E26+I26 -> 191538 | K26: 46142 | L26: {=SUMPRODUCT(('[1]Capex CJI3'!$A$2:$A$433=$A26)*(IFERROR(VALUE('[1]Capex CJI3'!$K$2:$K$433),0)>0)*((ISNUMBER(SEARCH("Reclass internal hours",'[1]Capex CJI3'!$J$2:$J$433)))+((LEN('[1]Capex CJI3'!$E$2:$E$433)>0)*ISERROR(SEARCH("Reclass internal hours",'[1]Capex CJI3'!$J$2:$J$433)))+((LEN('[1]Capex CJI3'!$E$2:$E$433)=0)*ISERROR(SEARCH("Reclass internal hours",'[1]Capex CJI3'!$J$2:$J$433))*ISERROR(SEARCH("WBS Correction",'[1]Capex CJI3'!$J$2:$J$433))*('[1]Capex CJI3'!$D$2:$D$433<>"6405000000"))>0))-IF($A26="O7941/2517",2,0)-IF($A26="O7941/2613",1,0)-IF($A26="O9100/2601",1,0)-IF($A26="O7941/2513",4,0)} -> 3 | M26: {=SUMPRODUCT(('[1]Capex CJI3'!$A$2:$A$433=$A26)*(IFERROR(VALUE('[1]Capex CJI3'!$K$2:$K$433),0)>0)*(LEN('[1]Capex CJI3'!$E$2:$E$433)>0)*ISERROR(SEARCH("Reclass internal hours",'[1]Capex CJI3'!$J$2:$J$433)))-IF($A26="O7941/2517",1,0)-IF($A26="O7941/2613",1,0)} -> 0 | N26: EUR | O26: 191538
A27: O7941/2609/2 | B27: =SUMIFS('[1]Capex CJI3'!$F$2:$F$433,'[1]Capex CJI3'!$A$2:$A$433,$A27,'[1]Capex CJI3'!$K$2:$K$433,2025,'[1]Capex CJI3'!$J$2:$J$433,"*Reclass internal hours*") -> 0 | C27: {=SUMPRODUCT(('[1]Capex CJI3'!$A$2:$A$433=$A27)*(IFERROR(VALUE('[1]Capex CJI3'!$K$2:$K$433),0)=2025)*(LEN('[1]Capex CJI3'!$E$2:$E$433)>0)*ISERROR(SEARCH("Reclass internal hours",'[1]Capex CJI3'!$J$2:$J$433))*IFERROR(VALUE('[1]Capex CJI3'!$F$2:$F$433),0))} -> 0 | D27: {=SUMPRODUCT(('[1]Capex CJI3'!$A$2:$A$433=$A27)*(IFERROR(VALUE('[1]Capex CJI3'!$K$2:$K$433),0)=2025)*(LEN('[1]Capex CJI3'!$E$2:$E$433)=0)*ISERROR(SEARCH("Reclass internal hours",'[1]Capex CJI3'!$J$2:$J$433))*ISERROR(SEARCH("WBS Correction",'[1]Capex CJI3'!$J$2:$J$433))*('[1]Capex CJI3'!$D$2:$D$433<>"6405000000")*IFERROR(VALUE('[1]Capex CJI3'!$F$2:$F$433),0))} -> 0 | E27: =SUM(B27:D27) -> 0 | F27: =SUMIFS('[1]Capex CJI3'!$F$2:$F$433,'[1]Capex CJI3'!$A$2:$A$433,$A27,'[1]Capex CJI3'!$K$2:$K$433,2026,'[1]Capex CJI3'!$J$2:$J$433,"*Reclass internal hours*") -> 58560 | G27: {=SUMPRODUCT(('[1]Capex CJI3'!$A$2:$A$433=$A27)*(IFERROR(VALUE('[1]Capex CJI3'!$K$2:$K$433),0)=2026)*(LEN('[1]Capex CJI3'!$E$2:$E$433)>0)*ISERROR(SEARCH("Reclass internal hours",'[1]Capex CJI3'!$J$2:$J$433))*IFERROR(VALUE('[1]Capex CJI3'!$F$2:$F$433),0))-IF($A27="O7941/2517",'[1]Capex CJI3'!$F$124,0)-IF($A27="O7941/2613",'[1]Capex CJI3'!$F$313,0)} -> 8100 | H27: {=SUMPRODUCT(('[1]Capex CJI3'!$A$2:$A$433=$A27)*(IFERROR(VALUE('[1]Capex CJI3'!$K$2:$K$433),0)=2026)*(LEN('[1]Capex CJI3'!$E$2:$E$433)=0)*ISERROR(SEARCH("Reclass internal hours",'[1]Capex CJI3'!$J$2:$J$433))*ISERROR(SEARCH("WBS Correction",'[1]Capex CJI3'!$J$2:$J$433))*('[1]Capex CJI3'!$D$2:$D$433<>"6405000000")*((($A27<>"O7941/2513")+('[1]Capex CJI3'!$D$2:$D$433<>"7405000000")+(IFERROR(VALUE('[1]Capex CJI3'!$L$2:$L$433),0)>=3))>0)*IFERROR(VALUE('[1]Capex CJI3'!$F$2:$F$433),0))-IF($A27="O7941/2517",'[1]Capex CJI3'!$F$132,0)-IF($A27="O9100/2601",'[1]Capex CJI3'!$F$429,0)} -> 9225 | I27: =SUM(F27:H27) -> 75885 | J27: =E27+I27 -> 75885 | K27: 46265 | L27: {=SUMPRODUCT(('[1]Capex CJI3'!$A$2:$A$433=$A27)*(IFERROR(VALUE('[1]Capex CJI3'!$K$2:$K$433),0)>0)*((ISNUMBER(SEARCH("Reclass internal hours",'[1]Capex CJI3'!$J$2:$J$433)))+((LEN('[1]Capex CJI3'!$E$2:$E$433)>0)*ISERROR(SEARCH("Reclass internal hours",'[1]Capex CJI3'!$J$2:$J$433)))+((LEN('[1]Capex CJI3'!$E$2:$E$433)=0)*ISERROR(SEARCH("Reclass internal hours",'[1]Capex CJI3'!$J$2:$J$433))*ISERROR(SEARCH("WBS Correction",'[1]Capex CJI3'!$J$2:$J$433))*('[1]Capex CJI3'!$D$2:$D$433<>"6405000000"))>0))-IF($A27="O7941/2517",2,0)-IF($A27="O7941/2613",1,0)-IF($A27="O9100/2601",1,0)-IF($A27="O7941/2513",4,0)} -> 9 | M27: {=SUMPRODUCT(('[1]Capex CJI3'!$A$2:$A$433=$A27)*(IFERROR(VALUE('[1]Capex CJI3'!$K$2:$K$433),0)>0)*(LEN('[1]Capex CJI3'!$E$2:$E$433)>0)*ISERROR(SEARCH("Reclass internal hours",'[1]Capex CJI3'!$J$2:$J$433)))-IF($A27="O7941/2517",1,0)-IF($A27="O7941/2613",1,0)} -> 3 | N27: EUR
A28: O7941/2610 | B28: =SUMIFS('[1]Capex CJI3'!$F$2:$F$433,'[1]Capex CJI3'!$A$2:$A$433,$A28,'[1]Capex CJI3'!$K$2:$K$433,2025,'[1]Capex CJI3'!$J$2:$J$433,"*Reclass internal hours*") -> 0 | C28: {=SUMPRODUCT(('[1]Capex CJI3'!$A$2:$A$433=$A28)*(IFERROR(VALUE('[1]Capex CJI3'!$K$2:$K$433),0)=2025)*(LEN('[1]Capex CJI3'!$E$2:$E$433)>0)*ISERROR(SEARCH("Reclass internal hours",'[1]Capex CJI3'!$J$2:$J$433))*IFERROR(VALUE('[1]Capex CJI3'!$F$2:$F$433),0))} -> 0 | D28: {=SUMPRODUCT(('[1]Capex CJI3'!$A$2:$A$433=$A28)*(IFERROR(VALUE('[1]Capex CJI3'!$K$2:$K$433),0)=2025)*(LEN('[1]Capex CJI3'!$E$2:$E$433)=0)*ISERROR(SEARCH("Reclass internal hours",'[1]Capex CJI3'!$J$2:$J$433))*ISERROR(SEARCH("WBS Correction",'[1]Capex CJI3'!$J$2:$J$433))*('[1]Capex CJI3'!$D$2:$D$433<>"6405000000")*IFERROR(VALUE('[1]Capex CJI3'!$F$2:$F$433),0))} -> 0 | E28: =SUM(B28:D28) -> 0 | F28: =SUMIFS('[1]Capex CJI3'!$F$2:$F$433,'[1]Capex CJI3'!$A$2:$A$433,$A28,'[1]Capex CJI3'!$K$2:$K$433,2026,'[1]Capex CJI3'!$J$2:$J$433,"*Reclass internal hours*") -> 329156 | G28: {=SUMPRODUCT(('[1]Capex CJI3'!$A$2:$A$433=$A28)*(IFERROR(VALUE('[1]Capex CJI3'!$K$2:$K$433),0)=2026)*(LEN('[1]Capex CJI3'!$E$2:$E$433)>0)*ISERROR(SEARCH("Reclass internal hours",'[1]Capex CJI3'!$J$2:$J$433))*IFERROR(VALUE('[1]Capex CJI3'!$F$2:$F$433),0))-IF($A28="O7941/2517",'[1]Capex CJI3'!$F$124,0)-IF($A28="O7941/2613",'[1]Capex CJI3'!$F$313,0)} -> 0 | H28: {=SUMPRODUCT(('[1]Capex CJI3'!$A$2:$A$433=$A28)*(IFERROR(VALUE('[1]Capex CJI3'!$K$2:$K$433),0)=2026)*(LEN('[1]Capex CJI3'!$E$2:$E$433)=0)*ISERROR(SEARCH("Reclass internal hours",'[1]Capex CJI3'!$J$2:$J$433))*ISERROR(SEARCH("WBS Correction",'[1]Capex CJI3'!$J$2:$J$433))*('[1]Capex CJI3'!$D$2:$D$433<>"6405000000")*((($A28<>"O7941/2513")+('[1]Capex CJI3'!$D$2:$D$433<>"7405000000")+(IFERROR(VALUE('[1]Capex CJI3'!$L$2:$L$433),0)>=3))>0)*IFERROR(VALUE('[1]Capex CJI3'!$F$2:$F$433),0))-IF($A28="O7941/2517",'[1]Capex CJI3'!$F$132,0)-IF($A28="O9100/2601",'[1]Capex CJI3'!$F$429,0)} -> 0 | I28: =SUM(F28:H28) -> 329156 | J28: =E28+I28 -> 329156 | K28: 46265 | L28: {=SUMPRODUCT(('[1]Capex CJI3'!$A$2:$A$433=$A28)*(IFERROR(VALUE('[1]Capex CJI3'!$K$2:$K$433),0)>0)*((ISNUMBER(SEARCH("Reclass internal hours",'[1]Capex CJI3'!$J$2:$J$433)))+((LEN('[1]Capex CJI3'!$E$2:$E$433)>0)*ISERROR(SEARCH("Reclass internal hours",'[1]Capex CJI3'!$J$2:$J$433)))+((LEN('[1]Capex CJI3'!$E$2:$E$433)=0)*ISERROR(SEARCH("Reclass internal hours",'[1]Capex CJI3'!$J$2:$J$433))*ISERROR(SEARCH("WBS Correction",'[1]Capex CJI3'!$J$2:$J$433))*('[1]Capex CJI3'!$D$2:$D$433<>"6405000000"))>0))-IF($A28="O7941/2517",2,0)-IF($A28="O7941/2613",1,0)-IF($A28="O9100/2601",1,0)-IF($A28="O7941/2513",4,0)} -> 6 | M28: {=SUMPRODUCT(('[1]Capex CJI3'!$A$2:$A$433=$A28)*(IFERROR(VALUE('[1]Capex CJI3'!$K$2:$K$433),0)>0)*(LEN('[1]Capex CJI3'!$E$2:$E$433)>0)*ISERROR(SEARCH("Reclass internal hours",'[1]Capex CJI3'!$J$2:$J$433)))-IF($A28="O7941/2517",1,0)-IF($A28="O7941/2613",1,0)} -> 0 | N28: EUR | O28: 450000
A29: O7941/2611 | B29: =SUMIFS('[1]Capex CJI3'!$F$2:$F$433,'[1]Capex CJI3'!$A$2:$A$433,$A29,'[1]Capex CJI3'!$K$2:$K$433,2025,'[1]Capex CJI3'!$J$2:$J$433,"*Reclass internal hours*") -> 0 | C29: {=SUMPRODUCT(('[1]Capex CJI3'!$A$2:$A$433=$A29)*(IFERROR(VALUE('[1]Capex CJI3'!$K$2:$K$433),0)=2025)*(LEN('[1]Capex CJI3'!$E$2:$E$433)>0)*ISERROR(SEARCH("Reclass internal hours",'[1]Capex CJI3'!$J$2:$J$433))*IFERROR(VALUE('[1]Capex CJI3'!$F$2:$F$433),0))} -> 0 | D29: {=SUMPRODUCT(('[1]Capex CJI3'!$A$2:$A$433=$A29)*(IFERROR(VALUE('[1]Capex CJI3'!$K$2:$K$433),0)=2025)*(LEN('[1]Capex CJI3'!$E$2:$E$433)=0)*ISERROR(SEARCH("Reclass internal hours",'[1]Capex CJI3'!$J$2:$J$433))*ISERROR(SEARCH("WBS Correction",'[1]Capex CJI3'!$J$2:$J$433))*('[1]Capex CJI3'!$D$2:$D$433<>"6405000000")*IFERROR(VALUE('[1]Capex CJI3'!$F$2:$F$433),0))} -> 0 | E29: =SUM(B29:D29) -> 0 | F29: =SUMIFS('[1]Capex CJI3'!$F$2:$F$433,'[1]Capex CJI3'!$A$2:$A$433,$A29,'[1]Capex CJI3'!$K$2:$K$433,2026,'[1]Capex CJI3'!$J$2:$J$433,"*Reclass internal hours*") -> 38115 | G29: {=SUMPRODUCT(('[1]Capex CJI3'!$A$2:$A$433=$A29)*(IFERROR(VALUE('[1]Capex CJI3'!$K$2:$K$433),0)=2026)*(LEN('[1]Capex CJI3'!$E$2:$E$433)>0)*ISERROR(SEARCH("Reclass internal hours",'[1]Capex CJI3'!$J$2:$J$433))*IFERROR(VALUE('[1]Capex CJI3'!$F$2:$F$433),0))-IF($A29="O7941/2517",'[1]Capex CJI3'!$F$124,0)-IF($A29="O7941/2613",'[1]Capex CJI3'!$F$313,0)} -> 0 | H29: {=SUMPRODUCT(('[1]Capex CJI3'!$A$2:$A$433=$A29)*(IFERROR(VALUE('[1]Capex CJI3'!$K$2:$K$433),0)=2026)*(LEN('[1]Capex CJI3'!$E$2:$E$433)=0)*ISERROR(SEARCH("Reclass internal hours",'[1]Capex CJI3'!$J$2:$J$433))*ISERROR(SEARCH("WBS Correction",'[1]Capex CJI3'!$J$2:$J$433))*('[1]Capex CJI3'!$D$2:$D$433<>"6405000000")*((($A29<>"O7941/2513")+('[1]Capex CJI3'!$D$2:$D$433<>"7405000000")+(IFERROR(VALUE('[1]Capex CJI3'!$L$2:$L$433),0)>=3))>0)*IFERROR(VALUE('[1]Capex CJI3'!$F$2:$F$433),0))-IF($A29="O7941/2517",'[1]Capex CJI3'!$F$132,0)-IF($A29="O9100/2601",'[1]Capex CJI3'!$F$429,0)} -> 0 | I29: =SUM(F29:H29) -> 38115 | J29: =E29+I29 -> 38115 | K29: 46265 | L29: {=SUMPRODUCT(('[1]Capex CJI3'!$A$2:$A$433=$A29)*(IFERROR(VALUE('[1]Capex CJI3'!$K$2:$K$433),0)>0)*((ISNUMBER(SEARCH("Reclass internal hours",'[1]Capex CJI3'!$J$2:$J$433)))+((LEN('[1]Capex CJI3'!$E$2:$E$433)>0)*ISERROR(SEARCH("Reclass internal hours",'[1]Capex CJI3'!$J$2:$J$433)))+((LEN('[1]Capex CJI3'!$E$2:$E$433)=0)*ISERROR(SEARCH("Reclass internal hours",'[1]Capex CJI3'!$J$2:$J$433))*ISERROR(SEARCH("WBS Correction",'[1]Capex CJI3'!$J$2:$J$433))*('[1]Capex CJI3'!$D$2:$D$433<>"6405000000"))>0))-IF($A29="O7941/2517",2,0)-IF($A29="O7941/2613",1,0)-IF($A29="O9100/2601",1,0)-IF($A29="O7941/2513",4,0)} -> 4 | M29: {=SUMPRODUCT(('[1]Capex CJI3'!$A$2:$A$433=$A29)*(IFERROR(VALUE('[1]Capex CJI3'!$K$2:$K$433),0)>0)*(LEN('[1]Capex CJI3'!$E$2:$E$433)>0)*ISERROR(SEARCH("Reclass internal hours",'[1]Capex CJI3'!$J$2:$J$433)))-IF($A29="O7941/2517",1,0)-IF($A29="O7941/2613",1,0)} -> 0 | N29: EUR | O29: 38115
A30: O7941/2612 | B30: =SUMIFS('[1]Capex CJI3'!$F$2:$F$433,'[1]Capex CJI3'!$A$2:$A$433,$A30,'[1]Capex CJI3'!$K$2:$K$433,2025,'[1]Capex CJI3'!$J$2:$J$433,"*Reclass internal hours*") -> 0 | C30: {=SUMPRODUCT(('[1]Capex CJI3'!$A$2:$A$433=$A30)*(IFERROR(VALUE('[1]Capex CJI3'!$K$2:$K$433),0)=2025)*(LEN('[1]Capex CJI3'!$E$2:$E$433)>0)*ISERROR(SEARCH("Reclass internal hours",'[1]Capex CJI3'!$J$2:$J$433))*IFERROR(VALUE('[1]Capex CJI3'!$F$2:$F$433),0))} -> 0 | D30: {=SUMPRODUCT(('[1]Capex CJI3'!$A$2:$A$433=$A30)*(IFERROR(VALUE('[1]Capex CJI3'!$K$2:$K$433),0)=2025)*(LEN('[1]Capex CJI3'!$E$2:$E$433)=0)*ISERROR(SEARCH("Reclass internal hours",'[1]Capex CJI3'!$J$2:$J$433))*ISERROR(SEARCH("WBS Correction",'[1]Capex CJI3'!$J$2:$J$433))*('[1]Capex CJI3'!$D$2:$D$433<>"6405000000")*IFERROR(VALUE('[1]Capex CJI3'!$F$2:$F$433),0))} -> 0 | E30: =SUM(B30:D30) -> 0 | F30: =SUMIFS('[1]Capex CJI3'!$F$2:$F$433,'[1]Capex CJI3'!$A$2:$A$433,$A30,'[1]Capex CJI3'!$K$2:$K$433,2026,'[1]Capex CJI3'!$J$2:$J$433,"*Reclass internal hours*") -> 179947.6 | G30: {=SUMPRODUCT(('[1]Capex CJI3'!$A$2:$A$433=$A30)*(IFERROR(VALUE('[1]Capex CJI3'!$K$2:$K$433),0)=2026)*(LEN('[1]Capex CJI3'!$E$2:$E$433)>0)*ISERROR(SEARCH("Reclass internal hours",'[1]Capex CJI3'!$J$2:$J$433))*IFERROR(VALUE('[1]Capex CJI3'!$F$2:$F$433),0))-IF($A30="O7941/2517",'[1]Capex CJI3'!$F$124,0)-IF($A30="O7941/2613",'[1]Capex CJI3'!$F$313,0)} -> 0 | H30: {=SUMPRODUCT(('[1]Capex CJI3'!$A$2:$A$433=$A30)*(IFERROR(VALUE('[1]Capex CJI3'!$K$2:$K$433),0)=2026)*(LEN('[1]Capex CJI3'!$E$2:$E$433)=0)*ISERROR(SEARCH("Reclass internal hours",'[1]Capex CJI3'!$J$2:$J$433))*ISERROR(SEARCH("WBS Correction",'[1]Capex CJI3'!$J$2:$J$433))*('[1]Capex CJI3'!$D$2:$D$433<>"6405000000")*((($A30<>"O7941/2513")+('[1]Capex CJI3'!$D$2:$D$433<>"7405000000")+(IFERROR(VALUE('[1]Capex CJI3'!$L$2:$L$433),0)>=3))>0)*IFERROR(VALUE('[1]Capex CJI3'!$F$2:$F$433),0))-IF($A30="O7941/2517",'[1]Capex CJI3'!$F$132,0)-IF($A30="O9100/2601",'[1]Capex CJI3'!$F$429,0)} -> 0 | I30: =SUM(F30:H30) -> 179947.6 | J30: =E30+I30 -> 179947.6 | K30: 46265 | L30: {=SUMPRODUCT(('[1]Capex CJI3'!$A$2:$A$433=$A30)*(IFERROR(VALUE('[1]Capex CJI3'!$K$2:$K$433),0)>0)*((ISNUMBER(SEARCH("Reclass internal hours",'[1]Capex CJI3'!$J$2:$J$433)))+((LEN('[1]Capex CJI3'!$E$2:$E$433)>0)*ISERROR(SEARCH("Reclass internal hours",'[1]Capex CJI3'!$J$2:$J$433)))+((LEN('[1]Capex CJI3'!$E$2:$E$433)=0)*ISERROR(SEARCH("Reclass internal hours",'[1]Capex CJI3'!$J$2:$J$433))*ISERROR(SEARCH("WBS Correction",'[1]Capex CJI3'!$J$2:$J$433))*('[1]Capex CJI3'!$D$2:$D$433<>"6405000000"))>0))-IF($A30="O7941/2517",2,0)-IF($A30="O7941/2613",1,0)-IF($A30="O9100/2601",1,0)-IF($A30="O7941/2513",4,0)} -> 6 | M30: {=SUMPRODUCT(('[1]Capex CJI3'!$A$2:$A$433=$A30)*(IFERROR(VALUE('[1]Capex CJI3'!$K$2:$K$433),0)>0)*(LEN('[1]Capex CJI3'!$E$2:$E$433)>0)*ISERROR(SEARCH("Reclass internal hours",'[1]Capex CJI3'!$J$2:$J$433)))-IF($A30="O7941/2517",1,0)-IF($A30="O7941/2613",1,0)} -> 0 | N30: EUR | O30: 192154
A31: O7941/2613 | B31: =SUMIFS('[1]Capex CJI3'!$F$2:$F$433,'[1]Capex CJI3'!$A$2:$A$433,$A31,'[1]Capex CJI3'!$K$2:$K$433,2025,'[1]Capex CJI3'!$J$2:$J$433,"*Reclass internal hours*") -> 0 | C31: {=SUMPRODUCT(('[1]Capex CJI3'!$A$2:$A$433=$A31)*(IFERROR(VALUE('[1]Capex CJI3'!$K$2:$K$433),0)=2025)*(LEN('[1]Capex CJI3'!$E$2:$E$433)>0)*ISERROR(SEARCH("Reclass internal hours",'[1]Capex CJI3'!$J$2:$J$433))*IFERROR(VALUE('[1]Capex CJI3'!$F$2:$F$433),0))} -> 0 | D31: {=SUMPRODUCT(('[1]Capex CJI3'!$A$2:$A$433=$A31)*(IFERROR(VALUE('[1]Capex CJI3'!$K$2:$K$433),0)=2025)*(LEN('[1]Capex CJI3'!$E$2:$E$433)=0)*ISERROR(SEARCH("Reclass internal hours",'[1]Capex CJI3'!$J$2:$J$433))*ISERROR(SEARCH("WBS Correction",'[1]Capex CJI3'!$J$2:$J$433))*('[1]Capex CJI3'!$D$2:$D$433<>"6405000000")*IFERROR(VALUE('[1]Capex CJI3'!$F$2:$F$433),0))} -> 0 | E31: =SUM(B31:D31) -> 0 | F31: =SUMIFS('[1]Capex CJI3'!$F$2:$F$433,'[1]Capex CJI3'!$A$2:$A$433,$A31,'[1]Capex CJI3'!$K$2:$K$433,2026,'[1]Capex CJI3'!$J$2:$J$433,"*Reclass internal hours*") -> 53300.56 | G31: {=SUMPRODUCT(('[1]Capex CJI3'!$A$2:$A$433=$A31)*(IFERROR(VALUE('[1]Capex CJI3'!$K$2:$K$433),0)=2026)*(LEN('[1]Capex CJI3'!$E$2:$E$433)>0)*ISERROR(SEARCH("Reclass internal hours",'[1]Capex CJI3'!$J$2:$J$433))*IFERROR(VALUE('[1]Capex CJI3'!$F$2:$F$433),0))-IF($A31="O7941/2517",'[1]Capex CJI3'!$F$124,0)-IF($A31="O7941/2613",'[1]Capex CJI3'!$F$313,0)} -> 68750 | H31: {=SUMPRODUCT(('[1]Capex CJI3'!$A$2:$A$433=$A31)*(IFERROR(VALUE('[1]Capex CJI3'!$K$2:$K$433),0)=2026)*(LEN('[1]Capex CJI3'!$E$2:$E$433)=0)*ISERROR(SEARCH("Reclass internal hours",'[1]Capex CJI3'!$J$2:$J$433))*ISERROR(SEARCH("WBS Correction",'[1]Capex CJI3'!$J$2:$J$433))*('[1]Capex CJI3'!$D$2:$D$433<>"6405000000")*((($A31<>"O7941/2513")+('[1]Capex CJI3'!$D$2:$D$433<>"7405000000")+(IFERROR(VALUE('[1]Capex CJI3'!$L$2:$L$433),0)>=3))>0)*IFERROR(VALUE('[1]Capex CJI3'!$F$2:$F$433),0))-IF($A31="O7941/2517",'[1]Capex CJI3'!$F$132,0)-IF($A31="O9100/2601",'[1]Capex CJI3'!$F$429,0)} -> 0 | I31: =SUM(F31:H31) -> 122050.56 | J31: =E31+I31 -> 122050.56 | K31: 46248 | L31: {=SUMPRODUCT(('[1]Capex CJI3'!$A$2:$A$433=$A31)*(IFERROR(VALUE('[1]Capex CJI3'!$K$2:$K$433),0)>0)*((ISNUMBER(SEARCH("Reclass internal hours",'[1]Capex CJI3'!$J$2:$J$433)))+((LEN('[1]Capex CJI3'!$E$2:$E$433)>0)*ISERROR(SEARCH("Reclass internal hours",'[1]Capex CJI3'!$J$2:$J$433)))+((LEN('[1]Capex CJI3'!$E$2:$E$433)=0)*ISERROR(SEARCH("Reclass internal hours",'[1]Capex CJI3'!$J$2:$J$433))*ISERROR(SEARCH("WBS Correction",'[1]Capex CJI3'!$J$2:$J$433))*('[1]Capex CJI3'!$D$2:$D$433<>"6405000000"))>0))-IF($A31="O7941/2517",2,0)-IF($A31="O7941/2613",1,0)-IF($A31="O9100/2601",1,0)-IF($A31="O7941/2513",4,0)} -> 11 | M31: {=SUMPRODUCT(('[1]Capex CJI3'!$A$2:$A$433=$A31)*(IFERROR(VALUE('[1]Capex CJI3'!$K$2:$K$433),0)>0)*(LEN('[1]Capex CJI3'!$E$2:$E$433)>0)*ISERROR(SEARCH("Reclass internal hours",'[1]Capex CJI3'!$J$2:$J$433)))-IF($A31="O7941/2517",1,0)-IF($A31="O7941/2613",1,0)} -> 7 | N31: EUR | O31: 160500
A32: O7941/2614 | B32: =SUMIFS('[1]Capex CJI3'!$F$2:$F$433,'[1]Capex CJI3'!$A$2:$A$433,$A32,'[1]Capex CJI3'!$K$2:$K$433,2025,'[1]Capex CJI3'!$J$2:$J$433,"*Reclass internal hours*") -> 0 | C32: {=SUMPRODUCT(('[1]Capex CJI3'!$A$2:$A$433=$A32)*(IFERROR(VALUE('[1]Capex CJI3'!$K$2:$K$433),0)=2025)*(LEN('[1]Capex CJI3'!$E$2:$E$433)>0)*ISERROR(SEARCH("Reclass internal hours",'[1]Capex CJI3'!$J$2:$J$433))*IFERROR(VALUE('[1]Capex CJI3'!$F$2:$F$433),0))} -> 0 | D32: {=SUMPRODUCT(('[1]Capex CJI3'!$A$2:$A$433=$A32)*(IFERROR(VALUE('[1]Capex CJI3'!$K$2:$K$433),0)=2025)*(LEN('[1]Capex CJI3'!$E$2:$E$433)=0)*ISERROR(SEARCH("Reclass internal hours",'[1]Capex CJI3'!$J$2:$J$433))*ISERROR(SEARCH("WBS Correction",'[1]Capex CJI3'!$J$2:$J$433))*('[1]Capex CJI3'!$D$2:$D$433<>"6405000000")*IFERROR(VALUE('[1]Capex CJI3'!$F$2:$F$433),0))} -> 0 | E32: =SUM(B32:D32) -> 0 | F32: =SUMIFS('[1]Capex CJI3'!$F$2:$F$433,'[1]Capex CJI3'!$A$2:$A$433,$A32,'[1]Capex CJI3'!$K$2:$K$433,2026,'[1]Capex CJI3'!$J$2:$J$433,"*Reclass internal hours*") -> 29455 | G32: {=SUMPRODUCT(('[1]Capex CJI3'!$A$2:$A$433=$A32)*(IFERROR(VALUE('[1]Capex CJI3'!$K$2:$K$433),0)=2026)*(LEN('[1]Capex CJI3'!$E$2:$E$433)>0)*ISERROR(SEARCH("Reclass internal hours",'[1]Capex CJI3'!$J$2:$J$433))*IFERROR(VALUE('[1]Capex CJI3'!$F$2:$F$433),0))-IF($A32="O7941/2517",'[1]Capex CJI3'!$F$124,0)-IF($A32="O7941/2613",'[1]Capex CJI3'!$F$313,0)} -> 30750 | H32: 28441.75 | I32: =SUM(F32:H32) -> 88646.75 | J32: =E32+I32 -> 88646.75 | K32: 46268 | L32: {=SUMPRODUCT(('[1]Capex CJI3'!$A$2:$A$433=$A32)*(IFERROR(VALUE('[1]Capex CJI3'!$K$2:$K$433),0)>0)*((ISNUMBER(SEARCH("Reclass internal hours",'[1]Capex CJI3'!$J$2:$J$433)))+((LEN('[1]Capex CJI3'!$E$2:$E$433)>0)*ISERROR(SEARCH("Reclass internal hours",'[1]Capex CJI3'!$J$2:$J$433)))+((LEN('[1]Capex CJI3'!$E$2:$E$433)=0)*ISERROR(SEARCH("Reclass internal hours",'[1]Capex CJI3'!$J$2:$J$433))*ISERROR(SEARCH("WBS Correction",'[1]Capex CJI3'!$J$2:$J$433))*('[1]Capex CJI3'!$D$2:$D$433<>"6405000000"))>0))-IF($A32="O7941/2517",2,0)-IF($A32="O7941/2613",1,0)-IF($A32="O9100/2601",1,0)-IF($A32="O7941/2513",4,0)} -> 13 | M32: {=SUMPRODUCT(('[1]Capex CJI3'!$A$2:$A$433=$A32)*(IFERROR(VALUE('[1]Capex CJI3'!$K$2:$K$433),0)>0)*(LEN('[1]Capex CJI3'!$E$2:$E$433)>0)*ISERROR(SEARCH("Reclass internal hours",'[1]Capex CJI3'!$J$2:$J$433)))-IF($A32="O7941/2517",1,0)-IF($A32="O7941/2613",1,0)} -> 5 | N32: EUR | O32: 160000
A33: O7941/2615 | B33: =SUMIFS('[1]Capex CJI3'!$F$2:$F$433,'[1]Capex CJI3'!$A$2:$A$433,$A33,'[1]Capex CJI3'!$K$2:$K$433,2025,'[1]Capex CJI3'!$J$2:$J$433,"*Reclass internal hours*") -> 0 | C33: {=SUMPRODUCT(('[1]Capex CJI3'!$A$2:$A$433=$A33)*(IFERROR(VALUE('[1]Capex CJI3'!$K$2:$K$433),0)=2025)*(LEN('[1]Capex CJI3'!$E$2:$E$433)>0)*ISERROR(SEARCH("Reclass internal hours",'[1]Capex CJI3'!$J$2:$J$433))*IFERROR(VALUE('[1]Capex CJI3'!$F$2:$F$433),0))} -> 0 | D33: {=SUMPRODUCT(('[1]Capex CJI3'!$A$2:$A$433=$A33)*(IFERROR(VALUE('[1]Capex CJI3'!$K$2:$K$433),0)=2025)*(LEN('[1]Capex CJI3'!$E$2:$E$433)=0)*ISERROR(SEARCH("Reclass internal hours",'[1]Capex CJI3'!$J$2:$J$433))*ISERROR(SEARCH("WBS Correction",'[1]Capex CJI3'!$J$2:$J$433))*('[1]Capex CJI3'!$D$2:$D$433<>"6405000000")*IFERROR(VALUE('[1]Capex CJI3'!$F$2:$F$433),0))} -> 0 | E33: =SUM(B33:D33) -> 0 | F33: =SUMIFS('[1]Capex CJI3'!$F$2:$F$433,'[1]Capex CJI3'!$A$2:$A$433,$A33,'[1]Capex CJI3'!$K$2:$K$433,2026,'[1]Capex CJI3'!$J$2:$J$433,"*Reclass internal hours*") -> 135855 | G33: {=SUMPRODUCT(('[1]Capex CJI3'!$A$2:$A$433=$A33)*(IFERROR(VALUE('[1]Capex CJI3'!$K$2:$K$433),0)=2026)*(LEN('[1]Capex CJI3'!$E$2:$E$433)>0)*ISERROR(SEARCH("Reclass internal hours",'[1]Capex CJI3'!$J$2:$J$433))*IFERROR(VALUE('[1]Capex CJI3'!$F$2:$F$433),0))-IF($A33="O7941/2517",'[1]Capex CJI3'!$F$124,0)-IF($A33="O7941/2613",'[1]Capex CJI3'!$F$313,0)} -> 0 | H33: {=SUMPRODUCT(('[1]Capex CJI3'!$A$2:$A$433=$A33)*(IFERROR(VALUE('[1]Capex CJI3'!$K$2:$K$433),0)=2026)*(LEN('[1]Capex CJI3'!$E$2:$E$433)=0)*ISERROR(SEARCH("Reclass internal hours",'[1]Capex CJI3'!$J$2:$J$433))*ISERROR(SEARCH("WBS Correction",'[1]Capex CJI3'!$J$2:$J$433))*('[1]Capex CJI3'!$D$2:$D$433<>"6405000000")*((($A33<>"O7941/2513")+('[1]Capex CJI3'!$D$2:$D$433<>"7405000000")+(IFERROR(VALUE('[1]Capex CJI3'!$L$2:$L$433),0)>=3))>0)*IFERROR(VALUE('[1]Capex CJI3'!$F$2:$F$433),0))-IF($A33="O7941/2517",'[1]Capex CJI3'!$F$132,0)-IF($A33="O9100/2601",'[1]Capex CJI3'!$F$429,0)} -> 0 | I33: =SUM(F33:H33) -> 135855 | J33: =E33+I33 -> 135855 | K33: 46265 | L33: {=SUMPRODUCT(('[1]Capex CJI3'!$A$2:$A$433=$A33)*(IFERROR(VALUE('[1]Capex CJI3'!$K$2:$K$433),0)>0)*((ISNUMBER(SEARCH("Reclass internal hours",'[1]Capex CJI3'!$J$2:$J$433)))+((LEN('[1]Capex CJI3'!$E$2:$E$433)>0)*ISERROR(SEARCH("Reclass internal hours",'[1]Capex CJI3'!$J$2:$J$433)))+((LEN('[1]Capex CJI3'!$E$2:$E$433)=0)*ISERROR(SEARCH("Reclass internal hours",'[1]Capex CJI3'!$J$2:$J$433))*ISERROR(SEARCH("WBS Correction",'[1]Capex CJI3'!$J$2:$J$433))*('[1]Capex CJI3'!$D$2:$D$433<>"6405000000"))>0))-IF($A33="O7941/2517",2,0)-IF($A33="O7941/2613",1,0)-IF($A33="O9100/2601",1,0)-IF($A33="O7941/2513",4,0)} -> 6 | M33: {=SUMPRODUCT(('[1]Capex CJI3'!$A$2:$A$433=$A33)*(IFERROR(VALUE('[1]Capex CJI3'!$K$2:$K$433),0)>0)*(LEN('[1]Capex CJI3'!$E$2:$E$433)>0)*ISERROR(SEARCH("Reclass internal hours",'[1]Capex CJI3'!$J$2:$J$433)))-IF($A33="O7941/2517",1,0)-IF($A33="O7941/2613",1,0)} -> 0 | N33: EUR | O33: 144716
A34: O7941/2616 | B34: =SUMIFS('[1]Capex CJI3'!$F$2:$F$433,'[1]Capex CJI3'!$A$2:$A$433,$A34,'[1]Capex CJI3'!$K$2:$K$433,2025,'[1]Capex CJI3'!$J$2:$J$433,"*Reclass internal hours*") -> 0 | C34: {=SUMPRODUCT(('[1]Capex CJI3'!$A$2:$A$433=$A34)*(IFERROR(VALUE('[1]Capex CJI3'!$K$2:$K$433),0)=2025)*(LEN('[1]Capex CJI3'!$E$2:$E$433)>0)*ISERROR(SEARCH("Reclass internal hours",'[1]Capex CJI3'!$J$2:$J$433))*IFERROR(VALUE('[1]Capex CJI3'!$F$2:$F$433),0))} -> 0 | D34: {=SUMPRODUCT(('[1]Capex CJI3'!$A$2:$A$433=$A34)*(IFERROR(VALUE('[1]Capex CJI3'!$K$2:$K$433),0)=2025)*(LEN('[1]Capex CJI3'!$E$2:$E$433)=0)*ISERROR(SEARCH("Reclass internal hours",'[1]Capex CJI3'!$J$2:$J$433))*ISERROR(SEARCH("WBS Correction",'[1]Capex CJI3'!$J$2:$J$433))*('[1]Capex CJI3'!$D$2:$D$433<>"6405000000")*IFERROR(VALUE('[1]Capex CJI3'!$F$2:$F$433),0))} -> 0 | E34: =SUM(B34:D34) -> 0 | F34: =SUMIFS('[1]Capex CJI3'!$F$2:$F$433,'[1]Capex CJI3'!$A$2:$A$433,$A34,'[1]Capex CJI3'!$K$2:$K$433,2026,'[1]Capex CJI3'!$J$2:$J$433,"*Reclass internal hours*") -> 42705 | G34: {=SUMPRODUCT(('[1]Capex CJI3'!$A$2:$A$433=$A34)*(IFERROR(VALUE('[1]Capex CJI3'!$K$2:$K$433),0)=2026)*(LEN('[1]Capex CJI3'!$E$2:$E$433)>0)*ISERROR(SEARCH("Reclass internal hours",'[1]Capex CJI3'!$J$2:$J$433))*IFERROR(VALUE('[1]Capex CJI3'!$F$2:$F$433),0))-IF($A34="O7941/2517",'[1]Capex CJI3'!$F$124,0)-IF($A34="O7941/2613",'[1]Capex CJI3'!$F$313,0)} -> 0 | H34: {=SUMPRODUCT(('[1]Capex CJI3'!$A$2:$A$433=$A34)*(IFERROR(VALUE('[1]Capex CJI3'!$K$2:$K$433),0)=2026)*(LEN('[1]Capex CJI3'!$E$2:$E$433)=0)*ISERROR(SEARCH("Reclass internal hours",'[1]Capex CJI3'!$J$2:$J$433))*ISERROR(SEARCH("WBS Correction",'[1]Capex CJI3'!$J$2:$J$433))*('[1]Capex CJI3'!$D$2:$D$433<>"6405000000")*((($A34<>"O7941/2513")+('[1]Capex CJI3'!$D$2:$D$433<>"7405000000")+(IFERROR(VALUE('[1]Capex CJI3'!$L$2:$L$433),0)>=3))>0)*IFERROR(VALUE('[1]Capex CJI3'!$F$2:$F$433),0))-IF($A34="O7941/2517",'[1]Capex CJI3'!$F$132,0)-IF($A34="O9100/2601",'[1]Capex CJI3'!$F$429,0)} -> 0 | I34: =SUM(F34:H34) -> 42705 | J34: =E34+I34 -> 42705 | K34: 46265 | L34: {=SUMPRODUCT(('[1]Capex CJI3'!$A$2:$A$433=$A34)*(IFERROR(VALUE('[1]Capex CJI3'!$K$2:$K$433),0)>0)*((ISNUMBER(SEARCH("Reclass internal hours",'[1]Capex CJI3'!$J$2:$J$433)))+((LEN('[1]Capex CJI3'!$E$2:$E$433)>0)*ISERROR(SEARCH("Reclass internal hours",'[1]Capex CJI3'!$J$2:$J$433)))+((LEN('[1]Capex CJI3'!$E$2:$E$433)=0)*ISERROR(SEARCH("Reclass internal hours",'[1]Capex CJI3'!$J$2:$J$433))*ISERROR(SEARCH("WBS Correction",'[1]Capex CJI3'!$J$2:$J$433))*('[1]Capex CJI3'!$D$2:$D$433<>"6405000000"))>0))-IF($A34="O7941/2517",2,0)-IF($A34="O7941/2613",1,0)-IF($A34="O9100/2601",1,0)-IF($A34="O7941/2513",4,0)} -> 4 | M34: {=SUMPRODUCT(('[1]Capex CJI3'!$A$2:$A$433=$A34)*(IFERROR(VALUE('[1]Capex CJI3'!$K$2:$K$433),0)>0)*(LEN('[1]Capex CJI3'!$E$2:$E$433)>0)*ISERROR(SEARCH("Reclass internal hours",'[1]Capex CJI3'!$J$2:$J$433)))-IF($A34="O7941/2517",1,0)-IF($A34="O7941/2613",1,0)} -> 0 | N34: EUR | O34: 79224
A35: O7941/2617 | B35: =SUMIFS('[1]Capex CJI3'!$F$2:$F$433,'[1]Capex CJI3'!$A$2:$A$433,$A35,'[1]Capex CJI3'!$K$2:$K$433,2025,'[1]Capex CJI3'!$J$2:$J$433,"*Reclass internal hours*") -> 0 | C35: {=SUMPRODUCT(('[1]Capex CJI3'!$A$2:$A$433=$A35)*(IFERROR(VALUE('[1]Capex CJI3'!$K$2:$K$433),0)=2025)*(LEN('[1]Capex CJI3'!$E$2:$E$433)>0)*ISERROR(SEARCH("Reclass internal hours",'[1]Capex CJI3'!$J$2:$J$433))*IFERROR(VALUE('[1]Capex CJI3'!$F$2:$F$433),0))} -> 0 | D35: {=SUMPRODUCT(('[1]Capex CJI3'!$A$2:$A$433=$A35)*(IFERROR(VALUE('[1]Capex CJI3'!$K$2:$K$433),0)=2025)*(LEN('[1]Capex CJI3'!$E$2:$E$433)=0)*ISERROR(SEARCH("Reclass internal hours",'[1]Capex CJI3'!$J$2:$J$433))*ISERROR(SEARCH("WBS Correction",'[1]Capex CJI3'!$J$2:$J$433))*('[1]Capex CJI3'!$D$2:$D$433<>"6405000000")*IFERROR(VALUE('[1]Capex CJI3'!$F$2:$F$433),0))} -> 0 | E35: =SUM(B35:D35) -> 0 | F35: =SUMIFS('[1]Capex CJI3'!$F$2:$F$433,'[1]Capex CJI3'!$A$2:$A$433,$A35,'[1]Capex CJI3'!$K$2:$K$433,2026,'[1]Capex CJI3'!$J$2:$J$433,"*Reclass internal hours*") -> 0 | G35: {=SUMPRODUCT(('[1]Capex CJI3'!$A$2:$A$433=$A35)*(IFERROR(VALUE('[1]Capex CJI3'!$K$2:$K$433),0)=2026)*(LEN('[1]Capex CJI3'!$E$2:$E$433)>0)*ISERROR(SEARCH("Reclass internal hours",'[1]Capex CJI3'!$J$2:$J$433))*IFERROR(VALUE('[1]Capex CJI3'!$F$2:$F$433),0))-IF($A35="O7941/2517",'[1]Capex CJI3'!$F$124,0)-IF($A35="O7941/2613",'[1]Capex CJI3'!$F$313,0)} -> 37803 | H35: {=SUMPRODUCT(('[1]Capex CJI3'!$A$2:$A$433=$A35)*(IFERROR(VALUE('[1]Capex CJI3'!$K$2:$K$433),0)=2026)*(LEN('[1]Capex CJI3'!$E$2:$E$433)=0)*ISERROR(SEARCH("Reclass internal hours",'[1]Capex CJI3'!$J$2:$J$433))*ISERROR(SEARCH("WBS Correction",'[1]Capex CJI3'!$J$2:$J$433))*('[1]Capex CJI3'!$D$2:$D$433<>"6405000000")*((($A35<>"O7941/2513")+('[1]Capex CJI3'!$D$2:$D$433<>"7405000000")+(IFERROR(VALUE('[1]Capex CJI3'!$L$2:$L$433),0)>=3))>0)*IFERROR(VALUE('[1]Capex CJI3'!$F$2:$F$433),0))-IF($A35="O7941/2517",'[1]Capex CJI3'!$F$132,0)-IF($A35="O9100/2601",'[1]Capex CJI3'!$F$429,0)} -> 0 | I35: =SUM(F35:H35) -> 37803 | J35: =E35+I35 -> 37803 | K35: 46275 | L35: {=SUMPRODUCT(('[1]Capex CJI3'!$A$2:$A$433=$A35)*(IFERROR(VALUE('[1]Capex CJI3'!$K$2:$K$433),0)>0)*((ISNUMBER(SEARCH("Reclass internal hours",'[1]Capex CJI3'!$J$2:$J$433)))+((LEN('[1]Capex CJI3'!$E$2:$E$433)>0)*ISERROR(SEARCH("Reclass internal hours",'[1]Capex CJI3'!$J$2:$J$433)))+((LEN('[1]Capex CJI3'!$E$2:$E$433)=0)*ISERROR(SEARCH("Reclass internal hours",'[1]Capex CJI3'!$J$2:$J$433))*ISERROR(SEARCH("WBS Correction",'[1]Capex CJI3'!$J$2:$J$433))*('[1]Capex CJI3'!$D$2:$D$433<>"6405000000"))>0))-IF($A35="O7941/2517",2,0)-IF($A35="O7941/2613",1,0)-IF($A35="O9100/2601",1,0)-IF($A35="O7941/2513",4,0)} -> 3 | M35: {=SUMPRODUCT(('[1]Capex CJI3'!$A$2:$A$433=$A35)*(IFERROR(VALUE('[1]Capex CJI3'!$K$2:$K$433),0)>0)*(LEN('[1]Capex CJI3'!$E$2:$E$433)>0)*ISERROR(SEARCH("Reclass internal hours",'[1]Capex CJI3'!$J$2:$J$433)))-IF($A35="O7941/2517",1,0)-IF($A35="O7941/2613",1,0)} -> 3 | N35: EUR | O35: 41584
A36: O7941/2618 | B36: =SUMIFS('[1]Capex CJI3'!$F$2:$F$433,'[1]Capex CJI3'!$A$2:$A$433,$A36,'[1]Capex CJI3'!$K$2:$K$433,2025,'[1]Capex CJI3'!$J$2:$J$433,"*Reclass internal hours*") -> 0 | C36: {=SUMPRODUCT(('[1]Capex CJI3'!$A$2:$A$433=$A36)*(IFERROR(VALUE('[1]Capex CJI3'!$K$2:$K$433),0)=2025)*(LEN('[1]Capex CJI3'!$E$2:$E$433)>0)*ISERROR(SEARCH("Reclass internal hours",'[1]Capex CJI3'!$J$2:$J$433))*IFERROR(VALUE('[1]Capex CJI3'!$F$2:$F$433),0))} -> 0 | D36: {=SUMPRODUCT(('[1]Capex CJI3'!$A$2:$A$433=$A36)*(IFERROR(VALUE('[1]Capex CJI3'!$K$2:$K$433),0)=2025)*(LEN('[1]Capex CJI3'!$E$2:$E$433)=0)*ISERROR(SEARCH("Reclass internal hours",'[1]Capex CJI3'!$J$2:$J$433))*ISERROR(SEARCH("WBS Correction",'[1]Capex CJI3'!$J$2:$J$433))*('[1]Capex CJI3'!$D$2:$D$433<>"6405000000")*IFERROR(VALUE('[1]Capex CJI3'!$F$2:$F$433),0))} -> 0 | E36: =SUM(B36:D36) -> 0 | F36: =SUMIFS('[1]Capex CJI3'!$F$2:$F$433,'[1]Capex CJI3'!$A$2:$A$433,$A36,'[1]Capex CJI3'!$K$2:$K$433,2026,'[1]Capex CJI3'!$J$2:$J$433,"*Reclass internal hours*") -> 0 | G36: {=SUMPRODUCT(('[1]Capex CJI3'!$A$2:$A$433=$A36)*(IFERROR(VALUE('[1]Capex CJI3'!$K$2:$K$433),0)=2026)*(LEN('[1]Capex CJI3'!$E$2:$E$433)>0)*ISERROR(SEARCH("Reclass internal hours",'[1]Capex CJI3'!$J$2:$J$433))*IFERROR(VALUE('[1]Capex CJI3'!$F$2:$F$433),0))-IF($A36="O7941/2517",'[1]Capex CJI3'!$F$124,0)-IF($A36="O7941/2613",'[1]Capex CJI3'!$F$313,0)} -> 18752.66 | H36: {=SUMPRODUCT(('[1]Capex CJI3'!$A$2:$A$433=$A36)*(IFERROR(VALUE('[1]Capex CJI3'!$K$2:$K$433),0)=2026)*(LEN('[1]Capex CJI3'!$E$2:$E$433)=0)*ISERROR(SEARCH("Reclass internal hours",'[1]Capex CJI3'!$J$2:$J$433))*ISERROR(SEARCH("WBS Correction",'[1]Capex CJI3'!$J$2:$J$433))*('[1]Capex CJI3'!$D$2:$D$433<>"6405000000")*((($A36<>"O7941/2513")+('[1]Capex CJI3'!$D$2:$D$433<>"7405000000")+(IFERROR(VALUE('[1]Capex CJI3'!$L$2:$L$433),0)>=3))>0)*IFERROR(VALUE('[1]Capex CJI3'!$F$2:$F$433),0))-IF($A36="O7941/2517",'[1]Capex CJI3'!$F$132,0)-IF($A36="O9100/2601",'[1]Capex CJI3'!$F$429,0)} -> 0 | I36: =SUM(F36:H36) -> 18752.66 | J36: =E36+I36 -> 18752.66 | K36: 46206 | L36: {=SUMPRODUCT(('[1]Capex CJI3'!$A$2:$A$433=$A36)*(IFERROR(VALUE('[1]Capex CJI3'!$K$2:$K$433),0)>0)*((ISNUMBER(SEARCH("Reclass internal hours",'[1]Capex CJI3'!$J$2:$J$433)))+((LEN('[1]Capex CJI3'!$E$2:$E$433)>0)*ISERROR(SEARCH("Reclass internal hours",'[1]Capex CJI3'!$J$2:$J$433)))+((LEN('[1]Capex CJI3'!$E$2:$E$433)=0)*ISERROR(SEARCH("Reclass internal hours",'[1]Capex CJI3'!$J$2:$J$433))*ISERROR(SEARCH("WBS Correction",'[1]Capex CJI3'!$J$2:$J$433))*('[1]Capex CJI3'!$D$2:$D$433<>"6405000000"))>0))-IF($A36="O7941/2517",2,0)-IF($A36="O7941/2613",1,0)-IF($A36="O9100/2601",1,0)-IF($A36="O7941/2513",4,0)} -> 2 | M36: {=SUMPRODUCT(('[1]Capex CJI3'!$A$2:$A$433=$A36)*(IFERROR(VALUE('[1]Capex CJI3'!$K$2:$K$433),0)>0)*(LEN('[1]Capex CJI3'!$E$2:$E$433)>0)*ISERROR(SEARCH("Reclass internal hours",'[1]Capex CJI3'!$J$2:$J$433)))-IF($A36="O7941/2517",1,0)-IF($A36="O7941/2613",1,0)} -> 2 | N36: EUR | O36: 30941
A37: O7941/2620 | B37: =SUMIFS('[1]Capex CJI3'!$F$2:$F$433,'[1]Capex CJI3'!$A$2:$A$433,$A37,'[1]Capex CJI3'!$K$2:$K$433,2025,'[1]Capex CJI3'!$J$2:$J$433,"*Reclass internal hours*") -> 0 | C37: {=SUMPRODUCT(('[1]Capex CJI3'!$A$2:$A$433=$A37)*(IFERROR(VALUE('[1]Capex CJI3'!$K$2:$K$433),0)=2025)*(LEN('[1]Capex CJI3'!$E$2:$E$433)>0)*ISERROR(SEARCH("Reclass internal hours",'[1]Capex CJI3'!$J$2:$J$433))*IFERROR(VALUE('[1]Capex CJI3'!$F$2:$F$433),0))} -> 0 | D37: {=SUMPRODUCT(('[1]Capex CJI3'!$A$2:$A$433=$A37)*(IFERROR(VALUE('[1]Capex CJI3'!$K$2:$K$433),0)=2025)*(LEN('[1]Capex CJI3'!$E$2:$E$433)=0)*ISERROR(SEARCH("Reclass internal hours",'[1]Capex CJI3'!$J$2:$J$433))*ISERROR(SEARCH("WBS Correction",'[1]Capex CJI3'!$J$2:$J$433))*('[1]Capex CJI3'!$D$2:$D$433<>"6405000000")*IFERROR(VALUE('[1]Capex CJI3'!$F$2:$F$433),0))} -> 0 | E37: =SUM(B37:D37) -> 0 | F37: =SUMIFS('[1]Capex CJI3'!$F$2:$F$433,'[1]Capex CJI3'!$A$2:$A$433,$A37,'[1]Capex CJI3'!$K$2:$K$433,2026,'[1]Capex CJI3'!$J$2:$J$433,"*Reclass internal hours*") -> 416686 | G37: {=SUMPRODUCT(('[1]Capex CJI3'!$A$2:$A$433=$A37)*(IFERROR(VALUE('[1]Capex CJI3'!$K$2:$K$433),0)=2026)*(LEN('[1]Capex CJI3'!$E$2:$E$433)>0)*ISERROR(SEARCH("Reclass internal hours",'[1]Capex CJI3'!$J$2:$J$433))*IFERROR(VALUE('[1]Capex CJI3'!$F$2:$F$433),0))-IF($A37="O7941/2517",'[1]Capex CJI3'!$F$124,0)-IF($A37="O7941/2613",'[1]Capex CJI3'!$F$313,0)} -> 98100 | H37: {=SUMPRODUCT(('[1]Capex CJI3'!$A$2:$A$433=$A37)*(IFERROR(VALUE('[1]Capex CJI3'!$K$2:$K$433),0)=2026)*(LEN('[1]Capex CJI3'!$E$2:$E$433)=0)*ISERROR(SEARCH("Reclass internal hours",'[1]Capex CJI3'!$J$2:$J$433))*ISERROR(SEARCH("WBS Correction",'[1]Capex CJI3'!$J$2:$J$433))*('[1]Capex CJI3'!$D$2:$D$433<>"6405000000")*((($A37<>"O7941/2513")+('[1]Capex CJI3'!$D$2:$D$433<>"7405000000")+(IFERROR(VALUE('[1]Capex CJI3'!$L$2:$L$433),0)>=3))>0)*IFERROR(VALUE('[1]Capex CJI3'!$F$2:$F$433),0))-IF($A37="O7941/2517",'[1]Capex CJI3'!$F$132,0)-IF($A37="O9100/2601",'[1]Capex CJI3'!$F$429,0)} -> 35625 | I37: =SUM(F37:H37) -> 550411 | J37: =E37+I37 -> 550411 | K37: 46265 | L37: {=SUMPRODUCT(('[1]Capex CJI3'!$A$2:$A$433=$A37)*(IFERROR(VALUE('[1]Capex CJI3'!$K$2:$K$433),0)>0)*((ISNUMBER(SEARCH("Reclass internal hours",'[1]Capex CJI3'!$J$2:$J$433)))+((LEN('[1]Capex CJI3'!$E$2:$E$433)>0)*ISERROR(SEARCH("Reclass internal hours",'[1]Capex CJI3'!$J$2:$J$433)))+((LEN('[1]Capex CJI3'!$E$2:$E$433)=0)*ISERROR(SEARCH("Reclass internal hours",'[1]Capex CJI3'!$J$2:$J$433))*ISERROR(SEARCH("WBS Correction",'[1]Capex CJI3'!$J$2:$J$433))*('[1]Capex CJI3'!$D$2:$D$433<>"6405000000"))>0))-IF($A37="O7941/2517",2,0)-IF($A37="O7941/2613",1,0)-IF($A37="O9100/2601",1,0)-IF($A37="O7941/2513",4,0)} -> 11 | M37: {=SUMPRODUCT(('[1]Capex CJI3'!$A$2:$A$433=$A37)*(IFERROR(VALUE('[1]Capex CJI3'!$K$2:$K$433),0)>0)*(LEN('[1]Capex CJI3'!$E$2:$E$433)>0)*ISERROR(SEARCH("Reclass internal hours",'[1]Capex CJI3'!$J$2:$J$433)))-IF($A37="O7941/2517",1,0)-IF($A37="O7941/2613",1,0)} -> 5 | N37: EUR | O37: 571200
A38: O7941/2622 | B38: =SUMIFS('[1]Capex CJI3'!$F$2:$F$433,'[1]Capex CJI3'!$A$2:$A$433,$A38,'[1]Capex CJI3'!$K$2:$K$433,2025,'[1]Capex CJI3'!$J$2:$J$433,"*Reclass internal hours*") -> 0 | C38: {=SUMPRODUCT(('[1]Capex CJI3'!$A$2:$A$433=$A38)*(IFERROR(VALUE('[1]Capex CJI3'!$K$2:$K$433),0)=2025)*(LEN('[1]Capex CJI3'!$E$2:$E$433)>0)*ISERROR(SEARCH("Reclass internal hours",'[1]Capex CJI3'!$J$2:$J$433))*IFERROR(VALUE('[1]Capex CJI3'!$F$2:$F$433),0))} -> 0 | D38: {=SUMPRODUCT(('[1]Capex CJI3'!$A$2:$A$433=$A38)*(IFERROR(VALUE('[1]Capex CJI3'!$K$2:$K$433),0)=2025)*(LEN('[1]Capex CJI3'!$E$2:$E$433)=0)*ISERROR(SEARCH("Reclass internal hours",'[1]Capex CJI3'!$J$2:$J$433))*ISERROR(SEARCH("WBS Correction",'[1]Capex CJI3'!$J$2:$J$433))*('[1]Capex CJI3'!$D$2:$D$433<>"6405000000")*IFERROR(VALUE('[1]Capex CJI3'!$F$2:$F$433),0))} -> 0 | E38: =SUM(B38:D38) -> 0 | F38: =SUMIFS('[1]Capex CJI3'!$F$2:$F$433,'[1]Capex CJI3'!$A$2:$A$433,$A38,'[1]Capex CJI3'!$K$2:$K$433,2026,'[1]Capex CJI3'!$J$2:$J$433,"*Reclass internal hours*") -> 0 | G38: {=SUMPRODUCT(('[1]Capex CJI3'!$A$2:$A$433=$A38)*(IFERROR(VALUE('[1]Capex CJI3'!$K$2:$K$433),0)=2026)*(LEN('[1]Capex CJI3'!$E$2:$E$433)>0)*ISERROR(SEARCH("Reclass internal hours",'[1]Capex CJI3'!$J$2:$J$433))*IFERROR(VALUE('[1]Capex CJI3'!$F$2:$F$433),0))-IF($A38="O7941/2517",'[1]Capex CJI3'!$F$124,0)-IF($A38="O7941/2613",'[1]Capex CJI3'!$F$313,0)} -> 0 | H38: {=SUMPRODUCT(('[1]Capex CJI3'!$A$2:$A$433=$A38)*(IFERROR(VALUE('[1]Capex CJI3'!$K$2:$K$433),0)=2026)*(LEN('[1]Capex CJI3'!$E$2:$E$433)=0)*ISERROR(SEARCH("Reclass internal hours",'[1]Capex CJI3'!$J$2:$J$433))*ISERROR(SEARCH("WBS Correction",'[1]Capex CJI3'!$J$2:$J$433))*('[1]Capex CJI3'!$D$2:$D$433<>"6405000000")*((($A38<>"O7941/2513")+('[1]Capex CJI3'!$D$2:$D$433<>"7405000000")+(IFERROR(VALUE('[1]Capex CJI3'!$L$2:$L$433),0)>=3))>0)*IFERROR(VALUE('[1]Capex CJI3'!$F$2:$F$433),0))-IF($A38="O7941/2517",'[1]Capex CJI3'!$F$132,0)-IF($A38="O9100/2601",'[1]Capex CJI3'!$F$429,0)} -> 162500 | I38: =SUM(F38:H38) -> 162500 | J38: =E38+I38 -> 162500 | K38: 46265 | L38: {=SUMPRODUCT(('[1]Capex CJI3'!$A$2:$A$433=$A38)*(IFERROR(VALUE('[1]Capex CJI3'!$K$2:$K$433),0)>0)*((ISNUMBER(SEARCH("Reclass internal hours",'[1]Capex CJI3'!$J$2:$J$433)))+((LEN('[1]Capex CJI3'!$E$2:$E$433)>0)*ISERROR(SEARCH("Reclass internal hours",'[1]Capex CJI3'!$J$2:$J$433)))+((LEN('[1]Capex CJI3'!$E$2:$E$433)=0)*ISERROR(SEARCH("Reclass internal hours",'[1]Capex CJI3'!$J$2:$J$433))*ISERROR(SEARCH("WBS Correction",'[1]Capex CJI3'!$J$2:$J$433))*('[1]Capex CJI3'!$D$2:$D$433<>"6405000000"))>0))-IF($A38="O7941/2517",2,0)-IF($A38="O7941/2613",1,0)-IF($A38="O9100/2601",1,0)-IF($A38="O7941/2513",4,0)} -> 4 | M38: {=SUMPRODUCT(('[1]Capex CJI3'!$A$2:$A$433=$A38)*(IFERROR(VALUE('[1]Capex CJI3'!$K$2:$K$433),0)>0)*(LEN('[1]Capex CJI3'!$E$2:$E$433)>0)*ISERROR(SEARCH("Reclass internal hours",'[1]Capex CJI3'!$J$2:$J$433)))-IF($A38="O7941/2517",1,0)-IF($A38="O7941/2613",1,0)} -> 0 | N38: EUR | O38: 285000
A39: O7941/2623 | B39: =SUMIFS('[1]Capex CJI3'!$F$2:$F$433,'[1]Capex CJI3'!$A$2:$A$433,$A39,'[1]Capex CJI3'!$K$2:$K$433,2025,'[1]Capex CJI3'!$J$2:$J$433,"*Reclass internal hours*") -> 0 | C39: {=SUMPRODUCT(('[1]Capex CJI3'!$A$2:$A$433=$A39)*(IFERROR(VALUE('[1]Capex CJI3'!$K$2:$K$433),0)=2025)*(LEN('[1]Capex CJI3'!$E$2:$E$433)>0)*ISERROR(SEARCH("Reclass internal hours",'[1]Capex CJI3'!$J$2:$J$433))*IFERROR(VALUE('[1]Capex CJI3'!$F$2:$F$433),0))} -> 0 | D39: {=SUMPRODUCT(('[1]Capex CJI3'!$A$2:$A$433=$A39)*(IFERROR(VALUE('[1]Capex CJI3'!$K$2:$K$433),0)=2025)*(LEN('[1]Capex CJI3'!$E$2:$E$433)=0)*ISERROR(SEARCH("Reclass internal hours",'[1]Capex CJI3'!$J$2:$J$433))*ISERROR(SEARCH("WBS Correction",'[1]Capex CJI3'!$J$2:$J$433))*('[1]Capex CJI3'!$D$2:$D$433<>"6405000000")*IFERROR(VALUE('[1]Capex CJI3'!$F$2:$F$433),0))} -> 0 | E39: =SUM(B39:D39) -> 0 | F39: =SUMIFS('[1]Capex CJI3'!$F$2:$F$433,'[1]Capex CJI3'!$A$2:$A$433,$A39,'[1]Capex CJI3'!$K$2:$K$433,2026,'[1]Capex CJI3'!$J$2:$J$433,"*Reclass internal hours*") -> 47350 | G39: {=SUMPRODUCT(('[1]Capex CJI3'!$A$2:$A$433=$A39)*(IFERROR(VALUE('[1]Capex CJI3'!$K$2:$K$433),0)=2026)*(LEN('[1]Capex CJI3'!$E$2:$E$433)>0)*ISERROR(SEARCH("Reclass internal hours",'[1]Capex CJI3'!$J$2:$J$433))*IFERROR(VALUE('[1]Capex CJI3'!$F$2:$F$433),0))-IF($A39="O7941/2517",'[1]Capex CJI3'!$F$124,0)-IF($A39="O7941/2613",'[1]Capex CJI3'!$F$313,0)} -> 976.1 | H39: {=SUMPRODUCT(('[1]Capex CJI3'!$A$2:$A$433=$A39)*(IFERROR(VALUE('[1]Capex CJI3'!$K$2:$K$433),0)=2026)*(LEN('[1]Capex CJI3'!$E$2:$E$433)=0)*ISERROR(SEARCH("Reclass internal hours",'[1]Capex CJI3'!$J$2:$J$433))*ISERROR(SEARCH("WBS Correction",'[1]Capex CJI3'!$J$2:$J$433))*('[1]Capex CJI3'!$D$2:$D$433<>"6405000000")*((($A39<>"O7941/2513")+('[1]Capex CJI3'!$D$2:$D$433<>"7405000000")+(IFERROR(VALUE('[1]Capex CJI3'!$L$2:$L$433),0)>=3))>0)*IFERROR(VALUE('[1]Capex CJI3'!$F$2:$F$433),0))-IF($A39="O7941/2517",'[1]Capex CJI3'!$F$132,0)-IF($A39="O9100/2601",'[1]Capex CJI3'!$F$429,0)} -> 0 | I39: =SUM(F39:H39) -> 48326.1 | J39: =E39+I39 -> 48326.1 | K39: 46273 | L39: {=SUMPRODUCT(('[1]Capex CJI3'!$A$2:$A$433=$A39)*(IFERROR(VALUE('[1]Capex CJI3'!$K$2:$K$433),0)>0)*((ISNUMBER(SEARCH("Reclass internal hours",'[1]Capex CJI3'!$J$2:$J$433)))+((LEN('[1]Capex CJI3'!$E$2:$E$433)>0)*ISERROR(SEARCH("Reclass internal hours",'[1]Capex CJI3'!$J$2:$J$433)))+((LEN('[1]Capex CJI3'!$E$2:$E$433)=0)*ISERROR(SEARCH("Reclass internal hours",'[1]Capex CJI3'!$J$2:$J$433))*ISERROR(SEARCH("WBS Correction",'[1]Capex CJI3'!$J$2:$J$433))*('[1]Capex CJI3'!$D$2:$D$433<>"6405000000"))>0))-IF($A39="O7941/2517",2,0)-IF($A39="O7941/2613",1,0)-IF($A39="O9100/2601",1,0)-IF($A39="O7941/2513",4,0)} -> 4 | M39: {=SUMPRODUCT(('[1]Capex CJI3'!$A$2:$A$433=$A39)*(IFERROR(VALUE('[1]Capex CJI3'!$K$2:$K$433),0)>0)*(LEN('[1]Capex CJI3'!$E$2:$E$433)>0)*ISERROR(SEARCH("Reclass internal hours",'[1]Capex CJI3'!$J$2:$J$433)))-IF($A39="O7941/2517",1,0)-IF($A39="O7941/2613",1,0)} -> 1 | N39: EUR | O39: 305670
A40: O7941/2624 | B40: =SUMIFS('[1]Capex CJI3'!$F$2:$F$433,'[1]Capex CJI3'!$A$2:$A$433,$A40,'[1]Capex CJI3'!$K$2:$K$433,2025,'[1]Capex CJI3'!$J$2:$J$433,"*Reclass internal hours*") -> 0 | C40: {=SUMPRODUCT(('[1]Capex CJI3'!$A$2:$A$433=$A40)*(IFERROR(VALUE('[1]Capex CJI3'!$K$2:$K$433),0)=2025)*(LEN('[1]Capex CJI3'!$E$2:$E$433)>0)*ISERROR(SEARCH("Reclass internal hours",'[1]Capex CJI3'!$J$2:$J$433))*IFERROR(VALUE('[1]Capex CJI3'!$F$2:$F$433),0))} -> 0 | D40: {=SUMPRODUCT(('[1]Capex CJI3'!$A$2:$A$433=$A40)*(IFERROR(VALUE('[1]Capex CJI3'!$K$2:$K$433),0)=2025)*(LEN('[1]Capex CJI3'!$E$2:$E$433)=0)*ISERROR(SEARCH("Reclass internal hours",'[1]Capex CJI3'!$J$2:$J$433))*ISERROR(SEARCH("WBS Correction",'[1]Capex CJI3'!$J$2:$J$433))*('[1]Capex CJI3'!$D$2:$D$433<>"6405000000")*IFERROR(VALUE('[1]Capex CJI3'!$F$2:$F$433),0))} -> 0 | E40: =SUM(B40:D40) -> 0 | F40: =SUMIFS('[1]Capex CJI3'!$F$2:$F$433,'[1]Capex CJI3'!$A$2:$A$433,$A40,'[1]Capex CJI3'!$K$2:$K$433,2026,'[1]Capex CJI3'!$J$2:$J$433,"*Reclass internal hours*") -> 0 | G40: {=SUMPRODUCT(('[1]Capex CJI3'!$A$2:$A$433=$A40)*(IFERROR(VALUE('[1]Capex CJI3'!$K$2:$K$433),0)=2026)*(LEN('[1]Capex CJI3'!$E$2:$E$433)>0)*ISERROR(SEARCH("Reclass internal hours",'[1]Capex CJI3'!$J$2:$J$433))*IFERROR(VALUE('[1]Capex CJI3'!$F$2:$F$433),0))-IF($A40="O7941/2517",'[1]Capex CJI3'!$F$124,0)-IF($A40="O7941/2613",'[1]Capex CJI3'!$F$313,0)} -> 0 | H40: {=SUMPRODUCT(('[1]Capex CJI3'!$A$2:$A$433=$A40)*(IFERROR(VALUE('[1]Capex CJI3'!$K$2:$K$433),0)=2026)*(LEN('[1]Capex CJI3'!$E$2:$E$433)=0)*ISERROR(SEARCH("Reclass internal hours",'[1]Capex CJI3'!$J$2:$J$433))*ISERROR(SEARCH("WBS Correction",'[1]Capex CJI3'!$J$2:$J$433))*('[1]Capex CJI3'!$D$2:$D$433<>"6405000000")*((($A40<>"O7941/2513")+('[1]Capex CJI3'!$D$2:$D$433<>"7405000000")+(IFERROR(VALUE('[1]Capex CJI3'!$L$2:$L$433),0)>=3))>0)*IFERROR(VALUE('[1]Capex CJI3'!$F$2:$F$433),0))-IF($A40="O7941/2517",'[1]Capex CJI3'!$F$132,0)-IF($A40="O9100/2601",'[1]Capex CJI3'!$F$429,0)} -> 360000 | I40: =SUM(F40:H40) -> 360000 | J40: =E40+I40 -> 360000 | K40: 46203 | L40: {=SUMPRODUCT(('[1]Capex CJI3'!$A$2:$A$433=$A40)*(IFERROR(VALUE('[1]Capex CJI3'!$K$2:$K$433),0)>0)*((ISNUMBER(SEARCH("Reclass internal hours",'[1]Capex CJI3'!$J$2:$J$433)))+((LEN('[1]Capex CJI3'!$E$2:$E$433)>0)*ISERROR(SEARCH("Reclass internal hours",'[1]Capex CJI3'!$J$2:$J$433)))+((LEN('[1]Capex CJI3'!$E$2:$E$433)=0)*ISERROR(SEARCH("Reclass internal hours",'[1]Capex CJI3'!$J$2:$J$433))*ISERROR(SEARCH("WBS Correction",'[1]Capex CJI3'!$J$2:$J$433))*('[1]Capex CJI3'!$D$2:$D$433<>"6405000000"))>0))-IF($A40="O7941/2517",2,0)-IF($A40="O7941/2613",1,0)-IF($A40="O9100/2601",1,0)-IF($A40="O7941/2513",4,0)} -> 2 | M40: {=SUMPRODUCT(('[1]Capex CJI3'!$A$2:$A$433=$A40)*(IFERROR(VALUE('[1]Capex CJI3'!$K$2:$K$433),0)>0)*(LEN('[1]Capex CJI3'!$E$2:$E$433)>0)*ISERROR(SEARCH("Reclass internal hours",'[1]Capex CJI3'!$J$2:$J$433)))-IF($A40="O7941/2517",1,0)-IF($A40="O7941/2613",1,0)} -> 0 | N40: EUR | O40: 360000
A41: O7941/2625 | B41: =SUMIFS('[1]Capex CJI3'!$F$2:$F$433,'[1]Capex CJI3'!$A$2:$A$433,$A41,'[1]Capex CJI3'!$K$2:$K$433,2025,'[1]Capex CJI3'!$J$2:$J$433,"*Reclass internal hours*") -> 0 | C41: {=SUMPRODUCT(('[1]Capex CJI3'!$A$2:$A$433=$A41)*(IFERROR(VALUE('[1]Capex CJI3'!$K$2:$K$433),0)=2025)*(LEN('[1]Capex CJI3'!$E$2:$E$433)>0)*ISERROR(SEARCH("Reclass internal hours",'[1]Capex CJI3'!$J$2:$J$433))*IFERROR(VALUE('[1]Capex CJI3'!$F$2:$F$433),0))} -> 0 | D41: {=SUMPRODUCT(('[1]Capex CJI3'!$A$2:$A$433=$A41)*(IFERROR(VALUE('[1]Capex CJI3'!$K$2:$K$433),0)=2025)*(LEN('[1]Capex CJI3'!$E$2:$E$433)=0)*ISERROR(SEARCH("Reclass internal hours",'[1]Capex CJI3'!$J$2:$J$433))*ISERROR(SEARCH("WBS Correction",'[1]Capex CJI3'!$J$2:$J$433))*('[1]Capex CJI3'!$D$2:$D$433<>"6405000000")*IFERROR(VALUE('[1]Capex CJI3'!$F$2:$F$433),0))} -> 0 | E41: =SUM(B41:D41) -> 0 | F41: =SUMIFS('[1]Capex CJI3'!$F$2:$F$433,'[1]Capex CJI3'!$A$2:$A$433,$A41,'[1]Capex CJI3'!$K$2:$K$433,2026,'[1]Capex CJI3'!$J$2:$J$433,"*Reclass internal hours*") -> 0 | G41: {=SUMPRODUCT(('[1]Capex CJI3'!$A$2:$A$433=$A41)*(IFERROR(VALUE('[1]Capex CJI3'!$K$2:$K$433),0)=2026)*(LEN('[1]Capex CJI3'!$E$2:$E$433)>0)*ISERROR(SEARCH("Reclass internal hours",'[1]Capex CJI3'!$J$2:$J$433))*IFERROR(VALUE('[1]Capex CJI3'!$F$2:$F$433),0))-IF($A41="O7941/2517",'[1]Capex CJI3'!$F$124,0)-IF($A41="O7941/2613",'[1]Capex CJI3'!$F$313,0)} -> 0 | H41: {=SUMPRODUCT(('[1]Capex CJI3'!$A$2:$A$433=$A41)*(IFERROR(VALUE('[1]Capex CJI3'!$K$2:$K$433),0)=2026)*(LEN('[1]Capex CJI3'!$E$2:$E$433)=0)*ISERROR(SEARCH("Reclass internal hours",'[1]Capex CJI3'!$J$2:$J$433))*ISERROR(SEARCH("WBS Correction",'[1]Capex CJI3'!$J$2:$J$433))*('[1]Capex CJI3'!$D$2:$D$433<>"6405000000")*((($A41<>"O7941/2513")+('[1]Capex CJI3'!$D$2:$D$433<>"7405000000")+(IFERROR(VALUE('[1]Capex CJI3'!$L$2:$L$433),0)>=3))>0)*IFERROR(VALUE('[1]Capex CJI3'!$F$2:$F$433),0))-IF($A41="O7941/2517",'[1]Capex CJI3'!$F$132,0)-IF($A41="O9100/2601",'[1]Capex CJI3'!$F$429,0)} -> 115143 | I41: =SUM(F41:H41) -> 115143 | J41: =E41+I41 -> 115143 | K41: 46265 | L41: {=SUMPRODUCT(('[1]Capex CJI3'!$A$2:$A$433=$A41)*(IFERROR(VALUE('[1]Capex CJI3'!$K$2:$K$433),0)>0)*((ISNUMBER(SEARCH("Reclass internal hours",'[1]Capex CJI3'!$J$2:$J$433)))+((LEN('[1]Capex CJI3'!$E$2:$E$433)>0)*ISERROR(SEARCH("Reclass internal hours",'[1]Capex CJI3'!$J$2:$J$433)))+((LEN('[1]Capex CJI3'!$E$2:$E$433)=0)*ISERROR(SEARCH("Reclass internal hours",'[1]Capex CJI3'!$J$2:$J$433))*ISERROR(SEARCH("WBS Correction",'[1]Capex CJI3'!$J$2:$J$433))*('[1]Capex CJI3'!$D$2:$D$433<>"6405000000"))>0))-IF($A41="O7941/2517",2,0)-IF($A41="O7941/2613",1,0)-IF($A41="O9100/2601",1,0)-IF($A41="O7941/2513",4,0)} -> 4 | M41: {=SUMPRODUCT(('[1]Capex CJI3'!$A$2:$A$433=$A41)*(IFERROR(VALUE('[1]Capex CJI3'!$K$2:$K$433),0)>0)*(LEN('[1]Capex CJI3'!$E$2:$E$433)>0)*ISERROR(SEARCH("Reclass internal hours",'[1]Capex CJI3'!$J$2:$J$433)))-IF($A41="O7941/2517",1,0)-IF($A41="O7941/2613",1,0)} -> 0 | N41: EUR | O41: 125000
A42: O7941/2627 | B42: =SUMIFS('[1]Capex CJI3'!$F$2:$F$433,'[1]Capex CJI3'!$A$2:$A$433,$A42,'[1]Capex CJI3'!$K$2:$K$433,2025,'[1]Capex CJI3'!$J$2:$J$433,"*Reclass internal hours*") -> 0 | C42: {=SUMPRODUCT(('[1]Capex CJI3'!$A$2:$A$433=$A42)*(IFERROR(VALUE('[1]Capex CJI3'!$K$2:$K$433),0)=2025)*(LEN('[1]Capex CJI3'!$E$2:$E$433)>0)*ISERROR(SEARCH("Reclass internal hours",'[1]Capex CJI3'!$J$2:$J$433))*IFERROR(VALUE('[1]Capex CJI3'!$F$2:$F$433),0))} -> 0 | D42: {=SUMPRODUCT(('[1]Capex CJI3'!$A$2:$A$433=$A42)*(IFERROR(VALUE('[1]Capex CJI3'!$K$2:$K$433),0)=2025)*(LEN('[1]Capex CJI3'!$E$2:$E$433)=0)*ISERROR(SEARCH("Reclass internal hours",'[1]Capex CJI3'!$J$2:$J$433))*ISERROR(SEARCH("WBS Correction",'[1]Capex CJI3'!$J$2:$J$433))*('[1]Capex CJI3'!$D$2:$D$433<>"6405000000")*IFERROR(VALUE('[1]Capex CJI3'!$F$2:$F$433),0))} -> 0 | E42: =SUM(B42:D42) -> 0 | F42: =SUMIFS('[1]Capex CJI3'!$F$2:$F$433,'[1]Capex CJI3'!$A$2:$A$433,$A42,'[1]Capex CJI3'!$K$2:$K$433,2026,'[1]Capex CJI3'!$J$2:$J$433,"*Reclass internal hours*") -> 100000 | G42: {=SUMPRODUCT(('[1]Capex CJI3'!$A$2:$A$433=$A42)*(IFERROR(VALUE('[1]Capex CJI3'!$K$2:$K$433),0)=2026)*(LEN('[1]Capex CJI3'!$E$2:$E$433)>0)*ISERROR(SEARCH("Reclass internal hours",'[1]Capex CJI3'!$J$2:$J$433))*IFERROR(VALUE('[1]Capex CJI3'!$F$2:$F$433),0))-IF($A42="O7941/2517",'[1]Capex CJI3'!$F$124,0)-IF($A42="O7941/2613",'[1]Capex CJI3'!$F$313,0)} -> 0 | H42: {=SUMPRODUCT(('[1]Capex CJI3'!$A$2:$A$433=$A42)*(IFERROR(VALUE('[1]Capex CJI3'!$K$2:$K$433),0)=2026)*(LEN('[1]Capex CJI3'!$E$2:$E$433)=0)*ISERROR(SEARCH("Reclass internal hours",'[1]Capex CJI3'!$J$2:$J$433))*ISERROR(SEARCH("WBS Correction",'[1]Capex CJI3'!$J$2:$J$433))*('[1]Capex CJI3'!$D$2:$D$433<>"6405000000")*((($A42<>"O7941/2513")+('[1]Capex CJI3'!$D$2:$D$433<>"7405000000")+(IFERROR(VALUE('[1]Capex CJI3'!$L$2:$L$433),0)>=3))>0)*IFERROR(VALUE('[1]Capex CJI3'!$F$2:$F$433),0))-IF($A42="O7941/2517",'[1]Capex CJI3'!$F$132,0)-IF($A42="O9100/2601",'[1]Capex CJI3'!$F$429,0)} -> 0 | I42: =SUM(F42:H42) -> 100000 | J42: =E42+I42 -> 100000 | K42: 46203 | L42: {=SUMPRODUCT(('[1]Capex CJI3'!$A$2:$A$433=$A42)*(IFERROR(VALUE('[1]Capex CJI3'!$K$2:$K$433),0)>0)*((ISNUMBER(SEARCH("Reclass internal hours",'[1]Capex CJI3'!$J$2:$J$433)))+((LEN('[1]Capex CJI3'!$E$2:$E$433)>0)*ISERROR(SEARCH("Reclass internal hours",'[1]Capex CJI3'!$J$2:$J$433)))+((LEN('[1]Capex CJI3'!$E$2:$E$433)=0)*ISERROR(SEARCH("Reclass internal hours",'[1]Capex CJI3'!$J$2:$J$433))*ISERROR(SEARCH("WBS Correction",'[1]Capex CJI3'!$J$2:$J$433))*('[1]Capex CJI3'!$D$2:$D$433<>"6405000000"))>0))-IF($A42="O7941/2517",2,0)-IF($A42="O7941/2613",1,0)-IF($A42="O9100/2601",1,0)-IF($A42="O7941/2513",4,0)} -> 1 | M42: {=SUMPRODUCT(('[1]Capex CJI3'!$A$2:$A$433=$A42)*(IFERROR(VALUE('[1]Capex CJI3'!$K$2:$K$433),0)>0)*(LEN('[1]Capex CJI3'!$E$2:$E$433)>0)*ISERROR(SEARCH("Reclass internal hours",'[1]Capex CJI3'!$J$2:$J$433)))-IF($A42="O7941/2517",1,0)-IF($A42="O7941/2613",1,0)} -> 0 | N42: EUR | O42: 150000
A43: O7941/2628 | B43: =SUMIFS('[1]Capex CJI3'!$F$2:$F$433,'[1]Capex CJI3'!$A$2:$A$433,$A43,'[1]Capex CJI3'!$K$2:$K$433,2025,'[1]Capex CJI3'!$J$2:$J$433,"*Reclass internal hours*") -> 0 | C43: {=SUMPRODUCT(('[1]Capex CJI3'!$A$2:$A$433=$A43)*(IFERROR(VALUE('[1]Capex CJI3'!$K$2:$K$433),0)=2025)*(LEN('[1]Capex CJI3'!$E$2:$E$433)>0)*ISERROR(SEARCH("Reclass internal hours",'[1]Capex CJI3'!$J$2:$J$433))*IFERROR(VALUE('[1]Capex CJI3'!$F$2:$F$433),0))} -> 0 | D43: {=SUMPRODUCT(('[1]Capex CJI3'!$A$2:$A$433=$A43)*(IFERROR(VALUE('[1]Capex CJI3'!$K$2:$K$433),0)=2025)*(LEN('[1]Capex CJI3'!$E$2:$E$433)=0)*ISERROR(SEARCH("Reclass internal hours",'[1]Capex CJI3'!$J$2:$J$433))*ISERROR(SEARCH("WBS Correction",'[1]Capex CJI3'!$J$2:$J$433))*('[1]Capex CJI3'!$D$2:$D$433<>"6405000000")*IFERROR(VALUE('[1]Capex CJI3'!$F$2:$F$433),0))} -> 0 | E43: =SUM(B43:D43) -> 0 | F43: =SUMIFS('[1]Capex CJI3'!$F$2:$F$433,'[1]Capex CJI3'!$A$2:$A$433,$A43,'[1]Capex CJI3'!$K$2:$K$433,2026,'[1]Capex CJI3'!$J$2:$J$433,"*Reclass internal hours*") -> 12500 | G43: {=SUMPRODUCT(('[1]Capex CJI3'!$A$2:$A$433=$A43)*(IFERROR(VALUE('[1]Capex CJI3'!$K$2:$K$433),0)=2026)*(LEN('[1]Capex CJI3'!$E$2:$E$433)>0)*ISERROR(SEARCH("Reclass internal hours",'[1]Capex CJI3'!$J$2:$J$433))*IFERROR(VALUE('[1]Capex CJI3'!$F$2:$F$433),0))-IF($A43="O7941/2517",'[1]Capex CJI3'!$F$124,0)-IF($A43="O7941/2613",'[1]Capex CJI3'!$F$313,0)} -> 84000 | H43: {=SUMPRODUCT(('[1]Capex CJI3'!$A$2:$A$433=$A43)*(IFERROR(VALUE('[1]Capex CJI3'!$K$2:$K$433),0)=2026)*(LEN('[1]Capex CJI3'!$E$2:$E$433)=0)*ISERROR(SEARCH("Reclass internal hours",'[1]Capex CJI3'!$J$2:$J$433))*ISERROR(SEARCH("WBS Correction",'[1]Capex CJI3'!$J$2:$J$433))*('[1]Capex CJI3'!$D$2:$D$433<>"6405000000")*((($A43<>"O7941/2513")+('[1]Capex CJI3'!$D$2:$D$433<>"7405000000")+(IFERROR(VALUE('[1]Capex CJI3'!$L$2:$L$433),0)>=3))>0)*IFERROR(VALUE('[1]Capex CJI3'!$F$2:$F$433),0))-IF($A43="O7941/2517",'[1]Capex CJI3'!$F$132,0)-IF($A43="O9100/2601",'[1]Capex CJI3'!$F$429,0)} -> 0 | I43: =SUM(F43:H43) -> 96500 | J43: =E43+I43 -> 96500 | K43: 46265 | L43: {=SUMPRODUCT(('[1]Capex CJI3'!$A$2:$A$433=$A43)*(IFERROR(VALUE('[1]Capex CJI3'!$K$2:$K$433),0)>0)*((ISNUMBER(SEARCH("Reclass internal hours",'[1]Capex CJI3'!$J$2:$J$433)))+((LEN('[1]Capex CJI3'!$E$2:$E$433)>0)*ISERROR(SEARCH("Reclass internal hours",'[1]Capex CJI3'!$J$2:$J$433)))+((LEN('[1]Capex CJI3'!$E$2:$E$433)=0)*ISERROR(SEARCH("Reclass internal hours",'[1]Capex CJI3'!$J$2:$J$433))*ISERROR(SEARCH("WBS Correction",'[1]Capex CJI3'!$J$2:$J$433))*('[1]Capex CJI3'!$D$2:$D$433<>"6405000000"))>0))-IF($A43="O7941/2517",2,0)-IF($A43="O7941/2613",1,0)-IF($A43="O9100/2601",1,0)-IF($A43="O7941/2513",4,0)} -> 4 | M43: {=SUMPRODUCT(('[1]Capex CJI3'!$A$2:$A$433=$A43)*(IFERROR(VALUE('[1]Capex CJI3'!$K$2:$K$433),0)>0)*(LEN('[1]Capex CJI3'!$E$2:$E$433)>0)*ISERROR(SEARCH("Reclass internal hours",'[1]Capex CJI3'!$J$2:$J$433)))-IF($A43="O7941/2517",1,0)-IF($A43="O7941/2613",1,0)} -> 1 | N43: EUR | O43: 162000
A44: O7941/2629 | B44: =SUMIFS('[1]Capex CJI3'!$F$2:$F$433,'[1]Capex CJI3'!$A$2:$A$433,$A44,'[1]Capex CJI3'!$K$2:$K$433,2025,'[1]Capex CJI3'!$J$2:$J$433,"*Reclass internal hours*") -> 0 | C44: {=SUMPRODUCT(('[1]Capex CJI3'!$A$2:$A$433=$A44)*(IFERROR(VALUE('[1]Capex CJI3'!$K$2:$K$433),0)=2025)*(LEN('[1]Capex CJI3'!$E$2:$E$433)>0)*ISERROR(SEARCH("Reclass internal hours",'[1]Capex CJI3'!$J$2:$J$433))*IFERROR(VALUE('[1]Capex CJI3'!$F$2:$F$433),0))} -> 0 | D44: {=SUMPRODUCT(('[1]Capex CJI3'!$A$2:$A$433=$A44)*(IFERROR(VALUE('[1]Capex CJI3'!$K$2:$K$433),0)=2025)*(LEN('[1]Capex CJI3'!$E$2:$E$433)=0)*ISERROR(SEARCH("Reclass internal hours",'[1]Capex CJI3'!$J$2:$J$433))*ISERROR(SEARCH("WBS Correction",'[1]Capex CJI3'!$J$2:$J$433))*('[1]Capex CJI3'!$D$2:$D$433<>"6405000000")*IFERROR(VALUE('[1]Capex CJI3'!$F$2:$F$433),0))} -> 0 | E44: =SUM(B44:D44) -> 0 | F44: =SUMIFS('[1]Capex CJI3'!$F$2:$F$433,'[1]Capex CJI3'!$A$2:$A$433,$A44,'[1]Capex CJI3'!$K$2:$K$433,2026,'[1]Capex CJI3'!$J$2:$J$433,"*Reclass internal hours*") -> 1700.64 | G44: {=SUMPRODUCT(('[1]Capex CJI3'!$A$2:$A$433=$A44)*(IFERROR(VALUE('[1]Capex CJI3'!$K$2:$K$433),0)=2026)*(LEN('[1]Capex CJI3'!$E$2:$E$433)>0)*ISERROR(SEARCH("Reclass internal hours",'[1]Capex CJI3'!$J$2:$J$433))*IFERROR(VALUE('[1]Capex CJI3'!$F$2:$F$433),0))-IF($A44="O7941/2517",'[1]Capex CJI3'!$F$124,0)-IF($A44="O7941/2613",'[1]Capex CJI3'!$F$313,0)} -> 0 | H44: {=SUMPRODUCT(('[1]Capex CJI3'!$A$2:$A$433=$A44)*(IFERROR(VALUE('[1]Capex CJI3'!$K$2:$K$433),0)=2026)*(LEN('[1]Capex CJI3'!$E$2:$E$433)=0)*ISERROR(SEARCH("Reclass internal hours",'[1]Capex CJI3'!$J$2:$J$433))*ISERROR(SEARCH("WBS Correction",'[1]Capex CJI3'!$J$2:$J$433))*('[1]Capex CJI3'!$D$2:$D$433<>"6405000000")*((($A44<>"O7941/2513")+('[1]Capex CJI3'!$D$2:$D$433<>"7405000000")+(IFERROR(VALUE('[1]Capex CJI3'!$L$2:$L$433),0)>=3))>0)*IFERROR(VALUE('[1]Capex CJI3'!$F$2:$F$433),0))-IF($A44="O7941/2517",'[1]Capex CJI3'!$F$132,0)-IF($A44="O9100/2601",'[1]Capex CJI3'!$F$429,0)} -> 607764 | I44: =SUM(F44:H44) -> 609464.64 | J44: =E44+I44 -> 609464.64 | K44: 46265 | L44: {=SUMPRODUCT(('[1]Capex CJI3'!$A$2:$A$433=$A44)*(IFERROR(VALUE('[1]Capex CJI3'!$K$2:$K$433),0)>0)*((ISNUMBER(SEARCH("Reclass internal hours",'[1]Capex CJI3'!$J$2:$J$433)))+((LEN('[1]Capex CJI3'!$E$2:$E$433)>0)*ISERROR(SEARCH("Reclass internal hours",'[1]Capex CJI3'!$J$2:$J$433)))+((LEN('[1]Capex CJI3'!$E$2:$E$433)=0)*ISERROR(SEARCH("Reclass internal hours",'[1]Capex CJI3'!$J$2:$J$433))*ISERROR(SEARCH("WBS Correction",'[1]Capex CJI3'!$J$2:$J$433))*('[1]Capex CJI3'!$D$2:$D$433<>"6405000000"))>0))-IF($A44="O7941/2517",2,0)-IF($A44="O7941/2613",1,0)-IF($A44="O9100/2601",1,0)-IF($A44="O7941/2513",4,0)} -> 10 | M44: {=SUMPRODUCT(('[1]Capex CJI3'!$A$2:$A$433=$A44)*(IFERROR(VALUE('[1]Capex CJI3'!$K$2:$K$433),0)>0)*(LEN('[1]Capex CJI3'!$E$2:$E$433)>0)*ISERROR(SEARCH("Reclass internal hours",'[1]Capex CJI3'!$J$2:$J$433)))-IF($A44="O7941/2517",1,0)-IF($A44="O7941/2613",1,0)} -> 0 | N44: EUR | O44: 875000
... A54: O9100/2601 | B54: =SUMIFS('[1]Capex CJI3'!$F$2:$F$433,'[1]Capex CJI3'!$A$2:$A$433,$A54,'[1]Capex CJI3'!$K$2:$K$433,2025,'[1]Capex CJI3'!$J$2:$J$433,"*Reclass internal hours*") -> 0 | C54: {=SUMPRODUCT(('[1]Capex CJI3'!$A$2:$A$433=$A54)*(IFERROR(VALUE('[1]Capex CJI3'!$K$2:$K$433),0)=2025)*(LEN('[1]Capex CJI3'!$E$2:$E$433)>0)*ISERROR(SEARCH("Reclass internal hours",'[1]Capex CJI3'!$J$2:$J$433))*IFERROR(VALUE('[1]Capex CJI3'!$F$2:$F$433),0))} -> 0 | D54: {=SUMPRODUCT(('[1]Capex CJI3'!$A$2:$A$433=$A54)*(IFERROR(VALUE('[1]Capex CJI3'!$K$2:$K$433),0)=2025)*(LEN('[1]Capex CJI3'!$E$2:$E$433)=0)*ISERROR(SEARCH("Reclass internal hours",'[1]Capex CJI3'!$J$2:$J$433))*ISERROR(SEARCH("WBS Correction",'[1]Capex CJI3'!$J$2:$J$433))*('[1]Capex CJI3'!$D$2:$D$433<>"6405000000")*IFERROR(VALUE('[1]Capex CJI3'!$F$2:$F$433),0))} -> 0 | E54: =SUM(B54:D54) -> 0 | F54: =SUMIFS('[1]Capex CJI3'!$F$2:$F$433,'[1]Capex CJI3'!$A$2:$A$433,$A54,'[1]Capex CJI3'!$K$2:$K$433,2026,'[1]Capex CJI3'!$J$2:$J$433,"*Reclass internal hours*") -> 0 | G54: {=SUMPRODUCT(('[1]Capex CJI3'!$A$2:$A$433=$A54)*(IFERROR(VALUE('[1]Capex CJI3'!$K$2:$K$433),0)=2026)*(LEN('[1]Capex CJI3'!$E$2:$E$433)>0)*ISERROR(SEARCH("Reclass internal hours",'[1]Capex CJI3'!$J$2:$J$433))*IFERROR(VALUE('[1]Capex CJI3'!$F$2:$F$433),0))-IF($A54="O7941/2517",'[1]Capex CJI3'!$F$124,0)-IF($A54="O7941/2613",'[1]Capex CJI3'!$F$313,0)} -> 1565.28 | H54: {=SUMPRODUCT(('[1]Capex CJI3'!$A$2:$A$433=$A54)*(IFERROR(VALUE('[1]Capex CJI3'!$K$2:$K$433),0)=2026)*(LEN('[1]Capex CJI3'!$E$2:$E$433)=0)*ISERROR(SEARCH("Reclass internal hours",'[1]Capex CJI3'!$J$2:$J$433))*ISERROR(SEARCH("WBS Correction",'[1]Capex CJI3'!$J$2:$J$433))*('[1]Capex CJI3'!$D$2:$D$433<>"6405000000")*((($A54<>"O7941/2513")+('[1]Capex CJI3'!$D$2:$D$433<>"7405000000")+(IFERROR(VALUE('[1]Capex CJI3'!$L$2:$L$433),0)>=3))>0)*IFERROR(VALUE('[1]Capex CJI3'!$F$2:$F$433),0))-IF($A54="O7941/2517",'[1]Capex CJI3'!$F$132,0)-IF($A54="O9100/2601",'[1]Capex CJI3'!$F$429,0)} -> 0 | I54: =SUM(F54:H54) -> 1565.28 | J54: =E54+I54 -> 1565.28 | K54: 46139 | L54: {=SUMPRODUCT(('[1]Capex CJI3'!$A$2:$A$433=$A54)*(IFERROR(VALUE('[1]Capex CJI3'!$K$2:$K$433),0)>0)*((ISNUMBER(SEARCH("Reclass internal hours",'[1]Capex CJI3'!$J$2:$J$433)))+((LEN('[1]Capex CJI3'!$E$2:$E$433)>0)*ISERROR(SEARCH("Reclass internal hours",'[1]Capex CJI3'!$J$2:$J$433)))+((LEN('[1]Capex CJI3'!$E$2:$E$433)=0)*ISERROR(SEARCH("Reclass internal hours",'[1]Capex CJI3'!$J$2:$J$433))*ISERROR(SEARCH("WBS Correction",'[1]Capex CJI3'!$J$2:$J$433))*('[1]Capex CJI3'!$D$2:$D$433<>"6405000000"))>0))-IF($A54="O7941/2517",2,0)-IF($A54="O7941/2613",1,0)-IF($A54="O9100/2601",1,0)-IF($A54="O7941/2513",4,0)} -> 1 | M54: {=SUMPRODUCT(('[1]Capex CJI3'!$A$2:$A$433=$A54)*(IFERROR(VALUE('[1]Capex CJI3'!$K$2:$K$433),0)>0)*(LEN('[1]Capex CJI3'!$E$2:$E$433)>0)*ISERROR(SEARCH("Reclass internal hours",'[1]Capex CJI3'!$J$2:$J$433)))-IF($A54="O7941/2517",1,0)-IF($A54="O7941/2613",1,0)} -> 1 | N54: EUR | O54: 22000
A57: EXTERNAL VENDOR SPEND BY PROJECT
A58: CAPEX WBS | B58: Vendor | C58: 2025 External | D58: 2026 External | E58: Vendor Total | F58: PO Lines
A59: N7941/2507 | B59: SAP BELGIUM NV | C59: {=SUMPRODUCT(('[1]Capex CJI3'!$A$2:$A$433=$A59)*(IFERROR(VALUE('[1]Capex CJI3'!$K$2:$K$433),0)=2025)*(LEN('[1]Capex CJI3'!$E$2:$E$433)>0)*ISERROR(SEARCH("Reclass internal hours",'[1]Capex CJI3'!$J$2:$J$433))*(_xlfn.LET(_xlpm.n,IF('[1]Capex CJI3'!$J$2:$J$433="","Unknown vendor",IFERROR(LEFT('[1]Capex CJI3'!$J$2:$J$433,FIND("/",'[1]Capex CJI3'!$J$2:$J$433)-1),'[1]Capex CJI3'!$J$2:$J$433)),_xlfn.SWITCH(_xlpm.n,"SAP BELGIUM N","SAP BELGIUM NV","PLANISWARE BELGIUM SR","PLANISWARE BELGIUM SRL","ERNST & YOUNG CONSUL","ERNST & YOUNG CONSULTING","ERNST & YOUNG CONSULTI","ERNST & YOUNG CONSULTING","ERNST & YOUNG CONSULTIN","ERNST & YOUNG CONSULTING","FLEXSO SUPPLY CHAI","FLEXSO SUPPLY CHAIN NV",_xlpm.n))=$B59)*IFERROR(VALUE('[1]Capex CJI3'!$F$2:$F$433),0))} -> 8015 | D59: {=SUMPRODUCT(('[1]Capex CJI3'!$A$2:$A$433=$A59)*(IFERROR(VALUE('[1]Capex CJI3'!$K$2:$K$433),0)=2026)*(LEN('[1]Capex CJI3'!$E$2:$E$433)>0)*ISERROR(SEARCH("Reclass internal hours",'[1]Capex CJI3'!$J$2:$J$433))*(_xlfn.LET(_xlpm.n,IF('[1]Capex CJI3'!$J$2:$J$433="","Unknown vendor",IFERROR(LEFT('[1]Capex CJI3'!$J$2:$J$433,FIND("/",'[1]Capex CJI3'!$J$2:$J$433)-1),'[1]Capex CJI3'!$J$2:$J$433)),_xlfn.SWITCH(_xlpm.n,"SAP BELGIUM N","SAP BELGIUM NV","PLANISWARE BELGIUM SR","PLANISWARE BELGIUM SRL","ERNST & YOUNG CONSUL","ERNST & YOUNG CONSULTING","ERNST & YOUNG CONSULTI","ERNST & YOUNG CONSULTING","ERNST & YOUNG CONSULTIN","ERNST & YOUNG CONSULTING","FLEXSO SUPPLY CHAI","FLEXSO SUPPLY CHAIN NV",_xlpm.n))=$B59)*IFERROR(VALUE('[1]Capex CJI3'!$F$2:$F$433),0))-IF(AND($A59="O7941/2517",$B59="ERNST & YOUNG CONSULTING"),'[1]Capex CJI3'!$F$124,0)-IF(AND($A59="O7941/2613",$B59="ERNST & YOUNG CONSULTING"),'[1]Capex CJI3'!$F$313,0)} -> 2290 | E59: =C59+D59 -> 10305 | F59: {=SUMPRODUCT(('[1]Capex CJI3'!$A$2:$A$433=$A59)*(LEN('[1]Capex CJI3'!$E$2:$E$433)>0)*ISERROR(SEARCH("Reclass internal hours",'[1]Capex CJI3'!$J$2:$J$433))*(_xlfn.LET(_xlpm.n,IF('[1]Capex CJI3'!$J$2:$J$433="","Unknown vendor",IFERROR(LEFT('[1]Capex CJI3'!$J$2:$J$433,FIND("/",'[1]Capex CJI3'!$J$2:$J$433)-1),'[1]Capex CJI3'!$J$2:$J$433)),_xlfn.SWITCH(_xlpm.n,"SAP BELGIUM N","SAP BELGIUM NV","PLANISWARE BELGIUM SR","PLANISWARE BELGIUM SRL","ERNST & YOUNG CONSUL","ERNST & YOUNG CONSULTING","ERNST & YOUNG CONSULTI","ERNST & YOUNG CONSULTING","ERNST & YOUNG CONSULTIN","ERNST & YOUNG CONSULTING","FLEXSO SUPPLY CHAI","FLEXSO SUPPLY CHAIN NV",_xlpm.n))=$B59))-IF(AND($A59="O7941/2517",$B59="ERNST & YOUNG CONSULTING"),1,0)-IF(AND($A59="O7941/2613",$B59="ERNST & YOUNG CONSULTING"),1,0)} -> 5
A60: O6300/2603 | B60: COMPUTACENTER NV | C60: {=SUMPRODUCT(('[1]Capex CJI3'!$A$2:$A$433=$A60)*(IFERROR(VALUE('[1]Capex CJI3'!$K$2:$K$433),0)=2025)*(LEN('[1]Capex CJI3'!$E$2:$E$433)>0)*ISERROR(SEARCH("Reclass internal hours",'[1]Capex CJI3'!$J$2:$J$433))*(_xlfn.LET(_xlpm.n,IF('[1]Capex CJI3'!$J$2:$J$433="","Unknown vendor",IFERROR(LEFT('[1]Capex CJI3'!$J$2:$J$433,FIND("/",'[1]Capex CJI3'!$J$2:$J$433)-1),'[1]Capex CJI3'!$J$2:$J$433)),_xlfn.SWITCH(_xlpm.n,"SAP BELGIUM N","SAP BELGIUM NV","PLANISWARE BELGIUM SR","PLANISWARE BELGIUM SRL","ERNST & YOUNG CONSUL","ERNST & YOUNG CONSULTING","ERNST & YOUNG CONSULTI","ERNST & YOUNG CONSULTING","ERNST & YOUNG CONSULTIN","ERNST & YOUNG CONSULTING","FLEXSO SUPPLY CHAI","FLEXSO SUPPLY CHAIN NV",_xlpm.n))=$B60)*IFERROR(VALUE('[1]Capex CJI3'!$F$2:$F$433),0))} -> 0 | D60: {=SUMPRODUCT(('[1]Capex CJI3'!$A$2:$A$433=$A60)*(IFERROR(VALUE('[1]Capex CJI3'!$K$2:$K$433),0)=2026)*(LEN('[1]Capex CJI3'!$E$2:$E$433)>0)*ISERROR(SEARCH("Reclass internal hours",'[1]Capex CJI3'!$J$2:$J$433))*(_xlfn.LET(_xlpm.n,IF('[1]Capex CJI3'!$J$2:$J$433="","Unknown vendor",IFERROR(LEFT('[1]Capex CJI3'!$J$2:$J$433,FIND("/",'[1]Capex CJI3'!$J$2:$J$433)-1),'[1]Capex CJI3'!$J$2:$J$433)),_xlfn.SWITCH(_xlpm.n,"SAP BELGIUM N","SAP BELGIUM NV","PLANISWARE BELGIUM SR","PLANISWARE BELGIUM SRL","ERNST & YOUNG CONSUL","ERNST & YOUNG CONSULTING","ERNST & YOUNG CONSULTI","ERNST & YOUNG CONSULTING","ERNST & YOUNG CONSULTIN","ERNST & YOUNG CONSULTING","FLEXSO SUPPLY CHAI","FLEXSO SUPPLY CHAIN NV",_xlpm.n))=$B60)*IFERROR(VALUE('[1]Capex CJI3'!$F$2:$F$433),0))-IF(AND($A60="O7941/2517",$B60="ERNST & YOUNG CONSULTING"),'[1]Capex CJI3'!$F$124,0)-IF(AND($A60="O7941/2613",$B60="ERNST & YOUNG CONSULTING"),'[1]Capex CJI3'!$F$313,0)} -> 571.85 | E60: =C60+D60 -> 571.85 | F60: {=SUMPRODUCT(('[1]Capex CJI3'!$A$2:$A$433=$A60)*(LEN('[1]Capex CJI3'!$E$2:$E$433)>0)*ISERROR(SEARCH("Reclass internal hours",'[1]Capex CJI3'!$J$2:$J$433))*(_xlfn.LET(_xlpm.n,IF('[1]Capex CJI3'!$J$2:$J$433="","Unknown vendor",IFERROR(LEFT('[1]Capex CJI3'!$J$2:$J$433,FIND("/",'[1]Capex CJI3'!$J$2:$J$433)-1),'[1]Capex CJI3'!$J$2:$J$433)),_xlfn.SWITCH(_xlpm.n,"SAP BELGIUM N","SAP BELGIUM NV","PLANISWARE BELGIUM SR","PLANISWARE BELGIUM SRL","ERNST & YOUNG CONSUL","ERNST & YOUNG CONSULTING","ERNST & YOUNG CONSULTI","ERNST & YOUNG CONSULTING","ERNST & YOUNG CONSULTIN","ERNST & YOUNG CONSULTING","FLEXSO SUPPLY CHAI","FLEXSO SUPPLY CHAIN NV",_xlpm.n))=$B60))-IF(AND($A60="O7941/2517",$B60="ERNST & YOUNG CONSULTING"),1,0)-IF(AND($A60="O7941/2613",$B60="ERNST & YOUNG CONSULTING"),1,0)} -> 1
A61: O7941/2513 | B61: PLANISWARE BELGIUM SRL | C61: {=SUMPRODUCT(('[1]Capex CJI3'!$A$2:$A$433=$A61)*(IFERROR(VALUE('[1]Capex CJI3'!$K$2:$K$433),0)=2025)*(LEN('[1]Capex CJI3'!$E$2:$E$433)>0)*ISERROR(SEARCH("Reclass internal hours",'[1]Capex CJI3'!$J$2:$J$433))*(_xlfn.LET(_xlpm.n,IF('[1]Capex CJI3'!$J$2:$J$433="","Unknown vendor",IFERROR(LEFT('[1]Capex CJI3'!$J$2:$J$433,FIND("/",'[1]Capex CJI3'!$J$2:$J$433)-1),'[1]Capex CJI3'!$J$2:$J$433)),_xlfn.SWITCH(_xlpm.n,"SAP BELGIUM N","SAP BELGIUM NV","PLANISWARE BELGIUM SR","PLANISWARE BELGIUM SRL","ERNST & YOUNG CONSUL","ERNST & YOUNG CONSULTING","ERNST & YOUNG CONSULTI","ERNST & YOUNG CONSULTING","ERNST & YOUNG CONSULTIN","ERNST & YOUNG CONSULTING","FLEXSO SUPPLY CHAI","FLEXSO SUPPLY CHAIN NV",_xlpm.n))=$B61)*IFERROR(VALUE('[1]Capex CJI3'!$F$2:$F$433),0))} -> 116687.8 | D61: {=SUMPRODUCT(('[1]Capex CJI3'!$A$2:$A$433=$A61)*(IFERROR(VALUE('[1]Capex CJI3'!$K$2:$K$433),0)=2026)*(LEN('[1]Capex CJI3'!$E$2:$E$433)>0)*ISERROR(SEARCH("Reclass internal hours",'[1]Capex CJI3'!$J$2:$J$433))*(_xlfn.LET(_xlpm.n,IF('[1]Capex CJI3'!$J$2:$J$433="","Unknown vendor",IFERROR(LEFT('[1]Capex CJI3'!$J$2:$J$433,FIND("/",'[1]Capex CJI3'!$J$2:$J$433)-1),'[1]Capex CJI3'!$J$2:$J$433)),_xlfn.SWITCH(_xlpm.n,"SAP BELGIUM N","SAP BELGIUM NV","PLANISWARE BELGIUM SR","PLANISWARE BELGIUM SRL","ERNST & YOUNG CONSUL","ERNST & YOUNG CONSULTING","ERNST & YOUNG CONSULTI","ERNST & YOUNG CONSULTING","ERNST & YOUNG CONSULTIN","ERNST & YOUNG CONSULTING","FLEXSO SUPPLY CHAI","FLEXSO SUPPLY CHAIN NV",_xlpm.n))=$B61)*IFERROR(VALUE('[1]Capex CJI3'!$F$2:$F$433),0))-IF(AND($A61="O7941/2517",$B61="ERNST & YOUNG CONSULTING"),'[1]Capex CJI3'!$F$124,0)-IF(AND($A61="O7941/2613",$B61="ERNST & YOUNG CONSULTING"),'[1]Capex CJI3'!$F$313,0)} -> 159850.65 | E61: =C61+D61 -> 276538.45 | F61: {=SUMPRODUCT(('[1]Capex CJI3'!$A$2:$A$433=$A61)*(LEN('[1]Capex CJI3'!$E$2:$E$433)>0)*ISERROR(SEARCH("Reclass internal hours",'[1]Capex CJI3'!$J$2:$J$433))*(_xlfn.LET(_xlpm.n,IF('[1]Capex CJI3'!$J$2:$J$433="","Unknown vendor",IFERROR(LEFT('[1]Capex CJI3'!$J$2:$J$433,FIND("/",'[1]Capex CJI3'!$J$2:$J$433)-1),'[1]Capex CJI3'!$J$2:$J$433)),_xlfn.SWITCH(_xlpm.n,"SAP BELGIUM N","SAP BELGIUM NV","PLANISWARE BELGIUM SR","PLANISWARE BELGIUM SRL","ERNST & YOUNG CONSUL","ERNST & YOUNG CONSULTING","ERNST & YOUNG CONSULTI","ERNST & YOUNG CONSULTING","ERNST & YOUNG CONSULTIN","ERNST & YOUNG CONSULTING","FLEXSO SUPPLY CHAI","FLEXSO SUPPLY CHAIN NV",_xlpm.n))=$B61))-IF(AND($A61="O7941/2517",$B61="ERNST & YOUNG CONSULTING"),1,0)-IF(AND($A61="O7941/2613",$B61="ERNST & YOUNG CONSULTING"),1,0)} -> 14
A62: O7941/2513 | B62: TEAM4P | C62: {=SUMPRODUCT(('[1]Capex CJI3'!$A$2:$A$433=$A62)*(IFERROR(VALUE('[1]Capex CJI3'!$K$2:$K$433),0)=2025)*(LEN('[1]Capex CJI3'!$E$2:$E$433)>0)*ISERROR(SEARCH("Reclass internal hours",'[1]Capex CJI3'!$J$2:$J$433))*(_xlfn.LET(_xlpm.n,IF('[1]Capex CJI3'!$J$2:$J$433="","Unknown vendor",IFERROR(LEFT('[1]Capex CJI3'!$J$2:$J$433,FIND("/",'[1]Capex CJI3'!$J$2:$J$433)-1),'[1]Capex CJI3'!$J$2:$J$433)),_xlfn.SWITCH(_xlpm.n,"SAP BELGIUM N","SAP BELGIUM NV","PLANISWARE BELGIUM SR","PLANISWARE BELGIUM SRL","ERNST & YOUNG CONSUL","ERNST & YOUNG CONSULTING","ERNST & YOUNG CONSULTI","ERNST & YOUNG CONSULTING","ERNST & YOUNG CONSULTIN","ERNST & YOUNG CONSULTING","FLEXSO SUPPLY CHAI","FLEXSO SUPPLY CHAIN NV",_xlpm.n))=$B62)*IFERROR(VALUE('[1]Capex CJI3'!$F$2:$F$433),0))} -> 11760 | D62: {=SUMPRODUCT(('[1]Capex CJI3'!$A$2:$A$433=$A62)*(IFERROR(VALUE('[1]Capex CJI3'!$K$2:$K$433),0)=2026)*(LEN('[1]Capex CJI3'!$E$2:$E$433)>0)*ISERROR(SEARCH("Reclass internal hours",'[1]Capex CJI3'!$J$2:$J$433))*(_xlfn.LET(_xlpm.n,IF('[1]Capex CJI3'!$J$2:$J$433="","Unknown vendor",IFERROR(LEFT('[1]Capex CJI3'!$J$2:$J$433,FIND("/",'[1]Capex CJI3'!$J$2:$J$433)-1),'[1]Capex CJI3'!$J$2:$J$433)),_xlfn.SWITCH(_xlpm.n,"SAP BELGIUM N","SAP BELGIUM NV","PLANISWARE BELGIUM SR","PLANISWARE BELGIUM SRL","ERNST & YOUNG CONSUL","ERNST & YOUNG CONSULTING","ERNST & YOUNG CONSULTI","ERNST & YOUNG CONSULTING","ERNST & YOUNG CONSULTIN","ERNST & YOUNG CONSULTING","FLEXSO SUPPLY CHAI","FLEXSO SUPPLY CHAIN NV",_xlpm.n))=$B62)*IFERROR(VALUE('[1]Capex CJI3'!$F$2:$F$433),0))-IF(AND($A62="O7941/2517",$B62="ERNST & YOUNG CONSULTING"),'[1]Capex CJI3'!$F$124,0)-IF(AND($A62="O7941/2613",$B62="ERNST & YOUNG CONSULTING"),'[1]Capex CJI3'!$F$313,0)} -> 28229.4 | E62: =C62+D62 -> 39989.4 | F62: {=SUMPRODUCT(('[1]Capex CJI3'!$A$2:$A$433=$A62)*(LEN('[1]Capex CJI3'!$E$2:$E$433)>0)*ISERROR(SEARCH("Reclass internal hours",'[1]Capex CJI3'!$J$2:$J$433))*(_xlfn.LET(_xlpm.n,IF('[1]Capex CJI3'!$J$2:$J$433="","Unknown vendor",IFERROR(LEFT('[1]Capex CJI3'!$J$2:$J$433,FIND("/",'[1]Capex CJI3'!$J$2:$J$433)-1),'[1]Capex CJI3'!$J$2:$J$433)),_xlfn.SWITCH(_xlpm.n,"SAP BELGIUM N","SAP BELGIUM NV","PLANISWARE BELGIUM SR","PLANISWARE BELGIUM SRL","ERNST & YOUNG CONSUL","ERNST & YOUNG CONSULTING","ERNST & YOUNG CONSULTI","ERNST & YOUNG CONSULTING","ERNST & YOUNG CONSULTIN","ERNST & YOUNG CONSULTING","FLEXSO SUPPLY CHAI","FLEXSO SUPPLY CHAIN NV",_xlpm.n))=$B62))-IF(AND($A62="O7941/2517",$B62="ERNST & YOUNG CONSULTING"),1,0)-IF(AND($A62="O7941/2613",$B62="ERNST & YOUNG CONSULTING"),1,0)} -> 9
A63: O7941/2517 | B63: ERNST & YOUNG CONSULTING | C63: {=SUMPRODUCT(('[1]Capex CJI3'!$A$2:$A$433=$A63)*(IFERROR(VALUE('[1]Capex CJI3'!$K$2:$K$433),0)=2025)*(LEN('[1]Capex CJI3'!$E$2:$E$433)>0)*ISERROR(SEARCH("Reclass internal hours",'[1]Capex CJI3'!$J$2:$J$433))*(_xlfn.LET(_xlpm.n,IF('[1]Capex CJI3'!$J$2:$J$433="","Unknown vendor",IFERROR(LEFT('[1]Capex CJI3'!$J$2:$J$433,FIND("/",'[1]Capex CJI3'!$J$2:$J$433)-1),'[1]Capex CJI3'!$J$2:$J$433)),_xlfn.SWITCH(_xlpm.n,"SAP BELGIUM N","SAP BELGIUM NV","PLANISWARE BELGIUM SR","PLANISWARE BELGIUM SRL","ERNST & YOUNG CONSUL","ERNST & YOUNG CONSULTING","ERNST & YOUNG CONSULTI","ERNST & YOUNG CONSULTING","ERNST & YOUNG CONSULTIN","ERNST & YOUNG CONSULTING","FLEXSO SUPPLY CHAI","FLEXSO SUPPLY CHAIN NV",_xlpm.n))=$B63)*IFERROR(VALUE('[1]Capex CJI3'!$F$2:$F$433),0))} -> 121088 | D63: {=SUMPRODUCT(('[1]Capex CJI3'!$A$2:$A$433=$A63)*(IFERROR(VALUE('[1]Capex CJI3'!$K$2:$K$433),0)=2026)*(LEN('[1]Capex CJI3'!$E$2:$E$433)>0)*ISERROR(SEARCH("Reclass internal hours",'[1]Capex CJI3'!$J$2:$J$433))*(_xlfn.LET(_xlpm.n,IF('[1]Capex CJI3'!$J$2:$J$433="","Unknown vendor",IFERROR(LEFT('[1]Capex CJI3'!$J$2:$J$433,FIND("/",'[1]Capex CJI3'!$J$2:$J$433)-1),'[1]Capex CJI3'!$J$2:$J$433)),_xlfn.SWITCH(_xlpm.n,"SAP BELGIUM N","SAP BELGIUM NV","PLANISWARE BELGIUM SR","PLANISWARE BELGIUM SRL","ERNST & YOUNG CONSUL","ERNST & YOUNG CONSULTING","ERNST & YOUNG CONSULTI","ERNST & YOUNG CONSULTING","ERNST & YOUNG CONSULTIN","ERNST & YOUNG CONSULTING","FLEXSO SUPPLY CHAI","FLEXSO SUPPLY CHAIN NV",_xlpm.n))=$B63)*IFERROR(VALUE('[1]Capex CJI3'!$F$2:$F$433),0))-IF(AND($A63="O7941/2517",$B63="ERNST & YOUNG CONSULTING"),'[1]Capex CJI3'!$F$124,0)-IF(AND($A63="O7941/2613",$B63="ERNST & YOUNG CONSULTING"),'[1]Capex CJI3'!$F$313,0)} -> 164692.23 | E63: =C63+D63 -> 285780.23 | F63: {=SUMPRODUCT(('[1]Capex CJI3'!$A$2:$A$433=$A63)*(LEN('[1]Capex CJI3'!$E$2:$E$433)>0)*ISERROR(SEARCH("Reclass internal hours",'[1]Capex CJI3'!$J$2:$J$433))*(_xlfn.LET(_xlpm.n,IF('[1]Capex CJI3'!$J$2:$J$433="","Unknown vendor",IFERROR(LEFT('[1]Capex CJI3'!$J$2:$J$433,FIND("/",'[1]Capex CJI3'!$J$2:$J$433)-1),'[1]Capex CJI3'!$J$2:$J$433)),_xlfn.SWITCH(_xlpm.n,"SAP BELGIUM N","SAP BELGIUM NV","PLANISWARE BELGIUM SR","PLANISWARE BELGIUM SRL","ERNST & YOUNG CONSUL","ERNST & YOUNG CONSULTING","ERNST & YOUNG CONSULTI","ERNST & YOUNG CONSULTING","ERNST & YOUNG CONSULTIN","ERNST & YOUNG CONSULTING","FLEXSO SUPPLY CHAI","FLEXSO SUPPLY CHAIN NV",_xlpm.n))=$B63))-IF(AND($A63="O7941/2517",$B63="ERNST & YOUNG CONSULTING"),1,0)-IF(AND($A63="O7941/2613",$B63="ERNST & YOUNG CONSULTING"),1,0)} -> 11
A64: O7941/2519 | B64: AVVALE SPA | C64: {=SUMPRODUCT(('[1]Capex CJI3'!$A$2:$A$433=$A64)*(IFERROR(VALUE('[1]Capex CJI3'!$K$2:$K$433),0)=2025)*(LEN('[1]Capex CJI3'!$E$2:$E$433)>0)*ISERROR(SEARCH("Reclass internal hours",'[1]Capex CJI3'!$J$2:$J$433))*(_xlfn.LET(_xlpm.n,IF('[1]Capex CJI3'!$J$2:$J$433="","Unknown vendor",IFERROR(LEFT('[1]Capex CJI3'!$J$2:$J$433,FIND("/",'[1]Capex CJI3'!$J$2:$J$433)-1),'[1]Capex CJI3'!$J$2:$J$433)),_xlfn.SWITCH(_xlpm.n,"SAP BELGIUM N","SAP BELGIUM NV","PLANISWARE BELGIUM SR","PLANISWARE BELGIUM SRL","ERNST & YOUNG CONSUL","ERNST & YOUNG CONSULTING","ERNST & YOUNG CONSULTI","ERNST & YOUNG CONSULTING","ERNST & YOUNG CONSULTIN","ERNST & YOUNG CONSULTING","FLEXSO SUPPLY CHAI","FLEXSO SUPPLY CHAIN NV",_xlpm.n))=$B64)*IFERROR(VALUE('[1]Capex CJI3'!$F$2:$F$433),0))} -> 10000 | D64: {=SUMPRODUCT(('[1]Capex CJI3'!$A$2:$A$433=$A64)*(IFERROR(VALUE('[1]Capex CJI3'!$K$2:$K$433),0)=2026)*(LEN('[1]Capex CJI3'!$E$2:$E$433)>0)*ISERROR(SEARCH("Reclass internal hours",'[1]Capex CJI3'!$J$2:$J$433))*(_xlfn.LET(_xlpm.n,IF('[1]Capex CJI3'!$J$2:$J$433="","Unknown vendor",IFERROR(LEFT('[1]Capex CJI3'!$J$2:$J$433,FIND("/",'[1]Capex CJI3'!$J$2:$J$433)-1),'[1]Capex CJI3'!$J$2:$J$433)),_xlfn.SWITCH(_xlpm.n,"SAP BELGIUM N","SAP BELGIUM NV","PLANISWARE BELGIUM SR","PLANISWARE BELGIUM SRL","ERNST & YOUNG CONSUL","ERNST & YOUNG CONSULTING","ERNST & YOUNG CONSULTI","ERNST & YOUNG CONSULTING","ERNST & YOUNG CONSULTIN","ERNST & YOUNG CONSULTING","FLEXSO SUPPLY CHAI","FLEXSO SUPPLY CHAIN NV",_xlpm.n))=$B64)*IFERROR(VALUE('[1]Capex CJI3'!$F$2:$F$433),0))-IF(AND($A64="O7941/2517",$B64="ERNST & YOUNG CONSULTING"),'[1]Capex CJI3'!$F$124,0)-IF(AND($A64="O7941/2613",$B64="ERNST & YOUNG CONSULTING"),'[1]Capex CJI3'!$F$313,0)} -> 30002 | E64: =C64+D64 -> 40002 | F64: {=SUMPRODUCT(('[1]Capex CJI3'!$A$2:$A$433=$A64)*(LEN('[1]Capex CJI3'!$E$2:$E$433)>0)*ISERROR(SEARCH("Reclass internal hours",'[1]Capex CJI3'!$J$2:$J$433))*(_xlfn.LET(_xlpm.n,IF('[1]Capex CJI3'!$J$2:$J$433="","Unknown vendor",IFERROR(LEFT('[1]Capex CJI3'!$J$2:$J$433,FIND("/",'[1]Capex CJI3'!$J$2:$J$433)-1),'[1]Capex CJI3'!$J$2:$J$433)),_xlfn.SWITCH(_xlpm.n,"SAP BELGIUM N","SAP BELGIUM NV","PLANISWARE BELGIUM SR","PLANISWARE BELGIUM SRL","ERNST & YOUNG CONSUL","ERNST & YOUNG CONSULTING","ERNST & YOUNG CONSULTI","ERNST & YOUNG CONSULTING","ERNST & YOUNG CONSULTIN","ERNST & YOUNG CONSULTING","FLEXSO SUPPLY CHAI","FLEXSO SUPPLY CHAIN NV",_xlpm.n))=$B64))-IF(AND($A64="O7941/2517",$B64="ERNST & YOUNG CONSULTING"),1,0)-IF(AND($A64="O7941/2613",$B64="ERNST & YOUNG CONSULTING"),1,0)} -> 3
A65: O7941/2519 | B65: ROCKWELL AUTOMATION | C65: {=SUMPRODUCT(('[1]Capex CJI3'!$A$2:$A$433=$A65)*(IFERROR(VALUE('[1]Capex CJI3'!$K$2:$K$433),0)=2025)*(LEN('[1]Capex CJI3'!$E$2:$E$433)>0)*ISERROR(SEARCH("Reclass internal hours",'[1]Capex CJI3'!$J$2:$J$433))*(_xlfn.LET(_xlpm.n,IF('[1]Capex CJI3'!$J$2:$J$433="","Unknown vendor",IFERROR(LEFT('[1]Capex CJI3'!$J$2:$J$433,FIND("/",'[1]Capex CJI3'!$J$2:$J$433)-1),'[1]Capex CJI3'!$J$2:$J$433)),_xlfn.SWITCH(_xlpm.n,"SAP BELGIUM N","SAP BELGIUM NV","PLANISWARE BELGIUM SR","PLANISWARE BELGIUM SRL","ERNST & YOUNG CONSUL","ERNST & YOUNG CONSULTING","ERNST & YOUNG CONSULTI","ERNST & YOUNG CONSULTING","ERNST & YOUNG CONSULTIN","ERNST & YOUNG CONSULTING","FLEXSO SUPPLY CHAI","FLEXSO SUPPLY CHAIN NV",_xlpm.n))=$B65)*IFERROR(VALUE('[1]Capex CJI3'!$F$2:$F$433),0))} -> 0 | D65: {=SUMPRODUCT(('[1]Capex CJI3'!$A$2:$A$433=$A65)*(IFERROR(VALUE('[1]Capex CJI3'!$K$2:$K$433),0)=2026)*(LEN('[1]Capex CJI3'!$E$2:$E$433)>0)*ISERROR(SEARCH("Reclass internal hours",'[1]Capex CJI3'!$J$2:$J$433))*(_xlfn.LET(_xlpm.n,IF('[1]Capex CJI3'!$J$2:$J$433="","Unknown vendor",IFERROR(LEFT('[1]Capex CJI3'!$J$2:$J$433,FIND("/",'[1]Capex CJI3'!$J$2:$J$433)-1),'[1]Capex CJI3'!$J$2:$J$433)),_xlfn.SWITCH(_xlpm.n,"SAP BELGIUM N","SAP BELGIUM NV","PLANISWARE BELGIUM SR","PLANISWARE BELGIUM SRL","ERNST & YOUNG CONSUL","ERNST & YOUNG CONSULTING","ERNST & YOUNG CONSULTI","ERNST & YOUNG CONSULTING","ERNST & YOUNG CONSULTIN","ERNST & YOUNG CONSULTING","FLEXSO SUPPLY CHAI","FLEXSO SUPPLY CHAIN NV",_xlpm.n))=$B65)*IFERROR(VALUE('[1]Capex CJI3'!$F$2:$F$433),0))-IF(AND($A65="O7941/2517",$B65="ERNST & YOUNG CONSULTING"),'[1]Capex CJI3'!$F$124,0)-IF(AND($A65="O7941/2613",$B65="ERNST & YOUNG CONSULTING"),'[1]Capex CJI3'!$F$313,0)} -> 28733.15 | E65: =C65+D65 -> 28733.15 | F65: {=SUMPRODUCT(('[1]Capex CJI3'!$A$2:$A$433=$A65)*(LEN('[1]Capex CJI3'!$E$2:$E$433)>0)*ISERROR(SEARCH("Reclass internal hours",'[1]Capex CJI3'!$J$2:$J$433))*(_xlfn.LET(_xlpm.n,IF('[1]Capex CJI3'!$J$2:$J$433="","Unknown vendor",IFERROR(LEFT('[1]Capex CJI3'!$J$2:$J$433,FIND("/",'[1]Capex CJI3'!$J$2:$J$433)-1),'[1]Capex CJI3'!$J$2:$J$433)),_xlfn.SWITCH(_xlpm.n,"SAP BELGIUM N","SAP BELGIUM NV","PLANISWARE BELGIUM SR","PLANISWARE BELGIUM SRL","ERNST & YOUNG CONSUL","ERNST & YOUNG CONSULTING","ERNST & YOUNG CONSULTI","ERNST & YOUNG CONSULTING","ERNST & YOUNG CONSULTIN","ERNST & YOUNG CONSULTING","FLEXSO SUPPLY CHAI","FLEXSO SUPPLY CHAIN NV",_xlpm.n))=$B65))-IF(AND($A65="O7941/2517",$B65="ERNST & YOUNG CONSULTING"),1,0)-IF(AND($A65="O7941/2613",$B65="ERNST & YOUNG CONSULTING"),1,0)} -> 1
A66: O7941/2519 | B66: ROCKWELL AUTOMATION INC | C66: {=SUMPRODUCT(('[1]Capex CJI3'!$A$2:$A$433=$A66)*(IFERROR(VALUE('[1]Capex CJI3'!$K$2:$K$433),0)=2025)*(LEN('[1]Capex CJI3'!$E$2:$E$433)>0)*ISERROR(SEARCH("Reclass internal hours",'[1]Capex CJI3'!$J$2:$J$433))*(_xlfn.LET(_xlpm.n,IF('[1]Capex CJI3'!$J$2:$J$433="","Unknown vendor",IFERROR(LEFT('[1]Capex CJI3'!$J$2:$J$433,FIND("/",'[1]Capex CJI3'!$J$2:$J$433)-1),'[1]Capex CJI3'!$J$2:$J$433)),_xlfn.SWITCH(_xlpm.n,"SAP BELGIUM N","SAP BELGIUM NV","PLANISWARE BELGIUM SR","PLANISWARE BELGIUM SRL","ERNST & YOUNG CONSUL","ERNST & YOUNG CONSULTING","ERNST & YOUNG CONSULTI","ERNST & YOUNG CONSULTING","ERNST & YOUNG CONSULTIN","ERNST & YOUNG CONSULTING","FLEXSO SUPPLY CHAI","FLEXSO SUPPLY CHAIN NV",_xlpm.n))=$B66)*IFERROR(VALUE('[1]Capex CJI3'!$F$2:$F$433),0))} -> 90000 | D66: {=SUMPRODUCT(('[1]Capex CJI3'!$A$2:$A$433=$A66)*(IFERROR(VALUE('[1]Capex CJI3'!$K$2:$K$433),0)=2026)*(LEN('[1]Capex CJI3'!$E$2:$E$433)>0)*ISERROR(SEARCH("Reclass internal hours",'[1]Capex CJI3'!$J$2:$J$433))*(_xlfn.LET(_xlpm.n,IF('[1]Capex CJI3'!$J$2:$J$433="","Unknown vendor",IFERROR(LEFT('[1]Capex CJI3'!$J$2:$J$433,FIND("/",'[1]Capex CJI3'!$J$2:$J$433)-1),'[1]Capex CJI3'!$J$2:$J$433)),_xlfn.SWITCH(_xlpm.n,"SAP BELGIUM N","SAP BELGIUM NV","PLANISWARE BELGIUM SR","PLANISWARE BELGIUM SRL","ERNST & YOUNG CONSUL","ERNST & YOUNG CONSULTING","ERNST & YOUNG CONSULTI","ERNST & YOUNG CONSULTING","ERNST & YOUNG CONSULTIN","ERNST & YOUNG CONSULTING","FLEXSO SUPPLY CHAI","FLEXSO SUPPLY CHAIN NV",_xlpm.n))=$B66)*IFERROR(VALUE('[1]Capex CJI3'!$F$2:$F$433),0))-IF(AND($A66="O7941/2517",$B66="ERNST & YOUNG CONSULTING"),'[1]Capex CJI3'!$F$124,0)-IF(AND($A66="O7941/2613",$B66="ERNST & YOUNG CONSULTING"),'[1]Capex CJI3'!$F$313,0)} -> 217817.95 | E66: =C66+D66 -> 307817.95 | F66: {=SUMPRODUCT(('[1]Capex CJI3'!$A$2:$A$433=$A66)*(LEN('[1]Capex CJI3'!$E$2:$E$433)>0)*ISERROR(SEARCH("Reclass internal hours",'[1]Capex CJI3'!$J$2:$J$433))*(_xlfn.LET(_xlpm.n,IF('[1]Capex CJI3'!$J$2:$J$433="","Unknown vendor",IFERROR(LEFT('[1]Capex CJI3'!$J$2:$J$433,FIND("/",'[1]Capex CJI3'!$J$2:$J$433)-1),'[1]Capex CJI3'!$J$2:$J$433)),_xlfn.SWITCH(_xlpm.n,"SAP BELGIUM N","SAP BELGIUM NV","PLANISWARE BELGIUM SR","PLANISWARE BELGIUM SRL","ERNST & YOUNG CONSUL","ERNST & YOUNG CONSULTING","ERNST & YOUNG CONSULTI","ERNST & YOUNG CONSULTING","ERNST & YOUNG CONSULTIN","ERNST & YOUNG CONSULTING","FLEXSO SUPPLY CHAI","FLEXSO SUPPLY CHAIN NV",_xlpm.n))=$B66))-IF(AND($A66="O7941/2517",$B66="ERNST & YOUNG CONSULTING"),1,0)-IF(AND($A66="O7941/2613",$B66="ERNST & YOUNG CONSULTING"),1,0)} -> 5
A67: O7941/2519 | B67: ROCKWELL AUTOMATION INC - PLE | C67: {=SUMPRODUCT(('[1]Capex CJI3'!$A$2:$A$433=$A67)*(IFERROR(VALUE('[1]Capex CJI3'!$K$2:$K$433),0)=2025)*(LEN('[1]Capex CJI3'!$E$2:$E$433)>0)*ISERROR(SEARCH("Reclass internal hours",'[1]Capex CJI3'!$J$2:$J$433))*(_xlfn.LET(_xlpm.n,IF('[1]Capex CJI3'!$J$2:$J$433="","Unknown vendor",IFERROR(LEFT('[1]Capex CJI3'!$J$2:$J$433,FIND("/",'[1]Capex CJI3'!$J$2:$J$433)-1),'[1]Capex CJI3'!$J$2:$J$433)),_xlfn.SWITCH(_xlpm.n,"SAP BELGIUM N","SAP BELGIUM NV","PLANISWARE BELGIUM SR","PLANISWARE BELGIUM SRL","ERNST & YOUNG CONSUL","ERNST & YOUNG CONSULTING","ERNST & YOUNG CONSULTI","ERNST & YOUNG CONSULTING","ERNST & YOUNG CONSULTIN","ERNST & YOUNG CONSULTING","FLEXSO SUPPLY CHAI","FLEXSO SUPPLY CHAIN NV",_xlpm.n))=$B67)*IFERROR(VALUE('[1]Capex CJI3'!$F$2:$F$433),0))} -> 0 | D67: {=SUMPRODUCT(('[1]Capex CJI3'!$A$2:$A$433=$A67)*(IFERROR(VALUE('[1]Capex CJI3'!$K$2:$K$433),0)=2026)*(LEN('[1]Capex CJI3'!$E$2:$E$433)>0)*ISERROR(SEARCH("Reclass internal hours",'[1]Capex CJI3'!$J$2:$J$433))*(_xlfn.LET(_xlpm.n,IF('[1]Capex CJI3'!$J$2:$J$433="","Unknown vendor",IFERROR(LEFT('[1]Capex CJI3'!$J$2:$J$433,FIND("/",'[1]Capex CJI3'!$J$2:$J$433)-1),'[1]Capex CJI3'!$J$2:$J$433)),_xlfn.SWITCH(_xlpm.n,"SAP BELGIUM N","SAP BELGIUM NV","PLANISWARE BELGIUM SR","PLANISWARE BELGIUM SRL","ERNST & YOUNG CONSUL","ERNST & YOUNG CONSULTING","ERNST & YOUNG CONSULTI","ERNST & YOUNG CONSULTING","ERNST & YOUNG CONSULTIN","ERNST & YOUNG CONSULTING","FLEXSO SUPPLY CHAI","FLEXSO SUPPLY CHAIN NV",_xlpm.n))=$B67)*IFERROR(VALUE('[1]Capex CJI3'!$F$2:$F$433),0))-IF(AND($A67="O7941/2517",$B67="ERNST & YOUNG CONSULTING"),'[1]Capex CJI3'!$F$124,0)-IF(AND($A67="O7941/2613",$B67="ERNST & YOUNG CONSULTING"),'[1]Capex CJI3'!$F$313,0)} -> 952 | E67: =C67+D67 -> 952 | F67: {=SUMPRODUCT(('[1]Capex CJI3'!$A$2:$A$433=$A67)*(LEN('[1]Capex CJI3'!$E$2:$E$433)>0)*ISERROR(SEARCH("Reclass internal hours",'[1]Capex CJI3'!$J$2:$J$433))*(_xlfn.LET(_xlpm.n,IF('[1]Capex CJI3'!$J$2:$J$433="","Unknown vendor",IFERROR(LEFT('[1]Capex CJI3'!$J$2:$J$433,FIND("/",'[1]Capex CJI3'!$J$2:$J$433)-1),'[1]Capex CJI3'!$J$2:$J$433)),_xlfn.SWITCH(_xlpm.n,"SAP BELGIUM N","SAP BELGIUM NV","PLANISWARE BELGIUM SR","PLANISWARE BELGIUM SRL","ERNST & YOUNG CONSUL","ERNST & YOUNG CONSULTING","ERNST & YOUNG CONSULTI","ERNST & YOUNG CONSULTING","ERNST & YOUNG CONSULTIN","ERNST & YOUNG CONSULTING","FLEXSO SUPPLY CHAI","FLEXSO SUPPLY CHAIN NV",_xlpm.n))=$B67))-IF(AND($A67="O7941/2517",$B67="ERNST & YOUNG CONSULTING"),1,0)-IF(AND($A67="O7941/2613",$B67="ERNST & YOUNG CONSULTING"),1,0)} -> 1
A68: O7941/2523 | B68: SOTERICS NV | C68: {=SUMPRODUCT(('[1]Capex CJI3'!$A$2:$A$433=$A68)*(IFERROR(VALUE('[1]Capex CJI3'!$K$2:$K$433),0)=2025)*(LEN('[1]Capex CJI3'!$E$2:$E$433)>0)*ISERROR(SEARCH("Reclass internal hours",'[1]Capex CJI3'!$J$2:$J$433))*(_xlfn.LET(_xlpm.n,IF('[1]Capex CJI3'!$J$2:$J$433="","Unknown vendor",IFERROR(LEFT('[1]Capex CJI3'!$J$2:$J$433,FIND("/",'[1]Capex CJI3'!$J$2:$J$433)-1),'[1]Capex CJI3'!$J$2:$J$433)),_xlfn.SWITCH(_xlpm.n,"SAP BELGIUM N","SAP BELGIUM NV","PLANISWARE BELGIUM SR","PLANISWARE BELGIUM SRL","ERNST & YOUNG CONSUL","ERNST & YOUNG CONSULTING","ERNST & YOUNG CONSULTI","ERNST & YOUNG CONSULTING","ERNST & YOUNG CONSULTIN","ERNST & YOUNG CONSULTING","FLEXSO SUPPLY CHAI","FLEXSO SUPPLY CHAIN NV",_xlpm.n))=$B68)*IFERROR(VALUE('[1]Capex CJI3'!$F$2:$F$433),0))} -> 31990.6 | D68: {=SUMPRODUCT(('[1]Capex CJI3'!$A$2:$A$433=$A68)*(IFERROR(VALUE('[1]Capex CJI3'!$K$2:$K$433),0)=2026)*(LEN('[1]Capex CJI3'!$E$2:$E$433)>0)*ISERROR(SEARCH("Reclass internal hours",'[1]Capex CJI3'!$J$2:$J$433))*(_xlfn.LET(_xlpm.n,IF('[1]Capex CJI3'!$J$2:$J$433="","Unknown vendor",IFERROR(LEFT('[1]Capex CJI3'!$J$2:$J$433,FIND("/",'[1]Capex CJI3'!$J$2:$J$433)-1),'[1]Capex CJI3'!$J$2:$J$433)),_xlfn.SWITCH(_xlpm.n,"SAP BELGIUM N","SAP BELGIUM NV","PLANISWARE BELGIUM SR","PLANISWARE BELGIUM SRL","ERNST & YOUNG CONSUL","ERNST & YOUNG CONSULTING","ERNST & YOUNG CONSULTI","ERNST & YOUNG CONSULTING","ERNST & YOUNG CONSULTIN","ERNST & YOUNG CONSULTING","FLEXSO SUPPLY CHAI","FLEXSO SUPPLY CHAIN NV",_xlpm.n))=$B68)*IFERROR(VALUE('[1]Capex CJI3'!$F$2:$F$433),0))-IF(AND($A68="O7941/2517",$B68="ERNST & YOUNG CONSULTING"),'[1]Capex CJI3'!$F$124,0)-IF(AND($A68="O7941/2613",$B68="ERNST & YOUNG CONSULTING"),'[1]Capex CJI3'!$F$313,0)} -> 39646 | E68: =C68+D68 -> 71636.6 | F68: {=SUMPRODUCT(('[1]Capex CJI3'!$A$2:$A$433=$A68)*(LEN('[1]Capex CJI3'!$E$2:$E$433)>0)*ISERROR(SEARCH("Reclass internal hours",'[1]Capex CJI3'!$J$2:$J$433))*(_xlfn.LET(_xlpm.n,IF('[1]Capex CJI3'!$J$2:$J$433="","Unknown vendor",IFERROR(LEFT('[1]Capex CJI3'!$J$2:$J$433,FIND("/",'[1]Capex CJI3'!$J$2:$J$433)-1),'[1]Capex CJI3'!$J$2:$J$433)),_xlfn.SWITCH(_xlpm.n,"SAP BELGIUM N","SAP BELGIUM NV","PLANISWARE BELGIUM SR","PLANISWARE BELGIUM SRL","ERNST & YOUNG CONSUL","ERNST & YOUNG CONSULTING","ERNST & YOUNG CONSULTI","ERNST & YOUNG CONSULTING","ERNST & YOUNG CONSULTIN","ERNST & YOUNG CONSULTING","FLEXSO SUPPLY CHAI","FLEXSO SUPPLY CHAIN NV",_xlpm.n))=$B68))-IF(AND($A68="O7941/2517",$B68="ERNST & YOUNG CONSULTING"),1,0)-IF(AND($A68="O7941/2613",$B68="ERNST & YOUNG CONSULTING"),1,0)} -> 3
A69: O7941/2524 | B69: IO BELGIUM | C69: {=SUMPRODUCT(('[1]Capex CJI3'!$A$2:$A$433=$A69)*(IFERROR(VALUE('[1]Capex CJI3'!$K$2:$K$433),0)=2025)*(LEN('[1]Capex CJI3'!$E$2:$E$433)>0)*ISERROR(SEARCH("Reclass internal hours",'[1]Capex CJI3'!$J$2:$J$433))*(_xlfn.LET(_xlpm.n,IF('[1]Capex CJI3'!$J$2:$J$433="","Unknown vendor",IFERROR(LEFT('[1]Capex CJI3'!$J$2:$J$433,FIND("/",'[1]Capex CJI3'!$J$2:$J$433)-1),'[1]Capex CJI3'!$J$2:$J$433)),_xlfn.SWITCH(_xlpm.n,"SAP BELGIUM N","SAP BELGIUM NV","PLANISWARE BELGIUM SR","PLANISWARE BELGIUM SRL","ERNST & YOUNG CONSUL","ERNST & YOUNG CONSULTING","ERNST & YOUNG CONSULTI","ERNST & YOUNG CONSULTING","ERNST & YOUNG CONSULTIN","ERNST & YOUNG CONSULTING","FLEXSO SUPPLY CHAI","FLEXSO SUPPLY CHAIN NV",_xlpm.n))=$B69)*IFERROR(VALUE('[1]Capex CJI3'!$F$2:$F$433),0))} -> 0 | D69: {=SUMPRODUCT(('[1]Capex CJI3'!$A$2:$A$433=$A69)*(IFERROR(VALUE('[1]Capex CJI3'!$K$2:$K$433),0)=2026)*(LEN('[1]Capex CJI3'!$E$2:$E$433)>0)*ISERROR(SEARCH("Reclass internal hours",'[1]Capex CJI3'!$J$2:$J$433))*(_xlfn.LET(_xlpm.n,IF('[1]Capex CJI3'!$J$2:$J$433="","Unknown vendor",IFERROR(LEFT('[1]Capex CJI3'!$J$2:$J$433,FIND("/",'[1]Capex CJI3'!$J$2:$J$433)-1),'[1]Capex CJI3'!$J$2:$J$433)),_xlfn.SWITCH(_xlpm.n,"SAP BELGIUM N","SAP BELGIUM NV","PLANISWARE BELGIUM SR","PLANISWARE BELGIUM SRL","ERNST & YOUNG CONSUL","ERNST & YOUNG CONSULTING","ERNST & YOUNG CONSULTI","ERNST & YOUNG CONSULTING","ERNST & YOUNG CONSULTIN","ERNST & YOUNG CONSULTING","FLEXSO SUPPLY CHAI","FLEXSO SUPPLY CHAIN NV",_xlpm.n))=$B69)*IFERROR(VALUE('[1]Capex CJI3'!$F$2:$F$433),0))-IF(AND($A69="O7941/2517",$B69="ERNST & YOUNG CONSULTING"),'[1]Capex CJI3'!$F$124,0)-IF(AND($A69="O7941/2613",$B69="ERNST & YOUNG CONSULTING"),'[1]Capex CJI3'!$F$313,0)} -> 169189 | E69: =C69+D69 -> 169189 | F69: {=SUMPRODUCT(('[1]Capex CJI3'!$A$2:$A$433=$A69)*(LEN('[1]Capex CJI3'!$E$2:$E$433)>0)*ISERROR(SEARCH("Reclass internal hours",'[1]Capex CJI3'!$J$2:$J$433))*(_xlfn.LET(_xlpm.n,IF('[1]Capex CJI3'!$J$2:$J$433="","Unknown vendor",IFERROR(LEFT('[1]Capex CJI3'!$J$2:$J$433,FIND("/",'[1]Capex CJI3'!$J$2:$J$433)-1),'[1]Capex CJI3'!$J$2:$J$433)),_xlfn.SWITCH(_xlpm.n,"SAP BELGIUM N","SAP BELGIUM NV","PLANISWARE BELGIUM SR","PLANISWARE BELGIUM SRL","ERNST & YOUNG CONSUL","ERNST & YOUNG CONSULTING","ERNST & YOUNG CONSULTI","ERNST & YOUNG CONSULTING","ERNST & YOUNG CONSULTIN","ERNST & YOUNG CONSULTING","FLEXSO SUPPLY CHAI","FLEXSO SUPPLY CHAIN NV",_xlpm.n))=$B69))-IF(AND($A69="O7941/2517",$B69="ERNST & YOUNG CONSULTING"),1,0)-IF(AND($A69="O7941/2613",$B69="ERNST & YOUNG CONSULTING"),1,0)} -> 5
A70: O7941/2524/1 | B70: IO BELGIUM | C70: {=SUMPRODUCT(('[1]Capex CJI3'!$A$2:$A$433=$A70)*(IFERROR(VALUE('[1]Capex CJI3'!$K$2:$K$433),0)=2025)*(LEN('[1]Capex CJI3'!$E$2:$E$433)>0)*ISERROR(SEARCH("Reclass internal hours",'[1]Capex CJI3'!$J$2:$J$433))*(_xlfn.LET(_xlpm.n,IF('[1]Capex CJI3'!$J$2:$J$433="","Unknown vendor",IFERROR(LEFT('[1]Capex CJI3'!$J$2:$J$433,FIND("/",'[1]Capex CJI3'!$J$2:$J$433)-1),'[1]Capex CJI3'!$J$2:$J$433)),_xlfn.SWITCH(_xlpm.n,"SAP BELGIUM N","SAP BELGIUM NV","PLANISWARE BELGIUM SR","PLANISWARE BELGIUM SRL","ERNST & YOUNG CONSUL","ERNST & YOUNG CONSULTING","ERNST & YOUNG CONSULTI","ERNST & YOUNG CONSULTING","ERNST & YOUNG CONSULTIN","ERNST & YOUNG CONSULTING","FLEXSO SUPPLY CHAI","FLEXSO SUPPLY CHAIN NV",_xlpm.n))=$B70)*IFERROR(VALUE('[1]Capex CJI3'!$F$2:$F$433),0))} -> 0 | D70: {=SUMPRODUCT(('[1]Capex CJI3'!$A$2:$A$433=$A70)*(IFERROR(VALUE('[1]Capex CJI3'!$K$2:$K$433),0)=2026)*(LEN('[1]Capex CJI3'!$E$2:$E$433)>0)*ISERROR(SEARCH("Reclass internal hours",'[1]Capex CJI3'!$J$2:$J$433))*(_xlfn.LET(_xlpm.n,IF('[1]Capex CJI3'!$J$2:$J$433="","Unknown vendor",IFERROR(LEFT('[1]Capex CJI3'!$J$2:$J$433,FIND("/",'[1]Capex CJI3'!$J$2:$J$433)-1),'[1]Capex CJI3'!$J$2:$J$433)),_xlfn.SWITCH(_xlpm.n,"SAP BELGIUM N","SAP BELGIUM NV","PLANISWARE BELGIUM SR","PLANISWARE BELGIUM SRL","ERNST & YOUNG CONSUL","ERNST & YOUNG CONSULTING","ERNST & YOUNG CONSULTI","ERNST & YOUNG CONSULTING","ERNST & YOUNG CONSULTIN","ERNST & YOUNG CONSULTING","FLEXSO SUPPLY CHAI","FLEXSO SUPPLY CHAIN NV",_xlpm.n))=$B70)*IFERROR(VALUE('[1]Capex CJI3'!$F$2:$F$433),0))-IF(AND($A70="O7941/2517",$B70="ERNST & YOUNG CONSULTING"),'[1]Capex CJI3'!$F$124,0)-IF(AND($A70="O7941/2613",$B70="ERNST & YOUNG CONSULTING"),'[1]Capex CJI3'!$F$313,0)} -> 632000 | E70: =C70+D70 -> 632000 | F70: {=SUMPRODUCT(('[1]Capex CJI3'!$A$2:$A$433=$A70)*(LEN('[1]Capex CJI3'!$E$2:$E$433)>0)*ISERROR(SEARCH("Reclass internal hours",'[1]Capex CJI3'!$J$2:$J$433))*(_xlfn.LET(_xlpm.n,IF('[1]Capex CJI3'!$J$2:$J$433="","Unknown vendor",IFERROR(LEFT('[1]Capex CJI3'!$J$2:$J$433,FIND("/",'[1]Capex CJI3'!$J$2:$J$433)-1),'[1]Capex CJI3'!$J$2:$J$433)),_xlfn.SWITCH(_xlpm.n,"SAP BELGIUM N","SAP BELGIUM NV","PLANISWARE BELGIUM SR","PLANISWARE BELGIUM SRL","ERNST & YOUNG CONSUL","ERNST & YOUNG CONSULTING","ERNST & YOUNG CONSULTI","ERNST & YOUNG CONSULTING","ERNST & YOUNG CONSULTIN","ERNST & YOUNG CONSULTING","FLEXSO SUPPLY CHAI","FLEXSO SUPPLY CHAIN NV",_xlpm.n))=$B70))-IF(AND($A70="O7941/2517",$B70="ERNST & YOUNG CONSULTING"),1,0)-IF(AND($A70="O7941/2613",$B70="ERNST & YOUNG CONSULTING"),1,0)} -> 6
... A89: O9100/2601 | B89: Unknown vendor | C89: {=SUMPRODUCT(('[1]Capex CJI3'!$A$2:$A$433=$A89)*(IFERROR(VALUE('[1]Capex CJI3'!$K$2:$K$433),0)=2025)*(LEN('[1]Capex CJI3'!$E$2:$E$433)>0)*ISERROR(SEARCH("Reclass internal hours",'[1]Capex CJI3'!$J$2:$J$433))*(_xlfn.LET(_xlpm.n,IF('[1]Capex CJI3'!$J$2:$J$433="","Unknown vendor",IFERROR(LEFT('[1]Capex CJI3'!$J$2:$J$433,FIND("/",'[1]Capex CJI3'!$J$2:$J$433)-1),'[1]Capex CJI3'!$J$2:$J$433)),_xlfn.SWITCH(_xlpm.n,"SAP BELGIUM N","SAP BELGIUM NV","PLANISWARE BELGIUM SR","PLANISWARE BELGIUM SRL","ERNST & YOUNG CONSUL","ERNST & YOUNG CONSULTING","ERNST & YOUNG CONSULTI","ERNST & YOUNG CONSULTING","ERNST & YOUNG CONSULTIN","ERNST & YOUNG CONSULTING","FLEXSO SUPPLY CHAI","FLEXSO SUPPLY CHAIN NV",_xlpm.n))=$B89)*IFERROR(VALUE('[1]Capex CJI3'!$F$2:$F$433),0))} -> 0 | D89: {=SUMPRODUCT(('[1]Capex CJI3'!$A$2:$A$433=$A89)*(IFERROR(VALUE('[1]Capex CJI3'!$K$2:$K$433),0)=2026)*(LEN('[1]Capex CJI3'!$E$2:$E$433)>0)*ISERROR(SEARCH("Reclass internal hours",'[1]Capex CJI3'!$J$2:$J$433))*(_xlfn.LET(_xlpm.n,IF('[1]Capex CJI3'!$J$2:$J$433="","Unknown vendor",IFERROR(LEFT('[1]Capex CJI3'!$J$2:$J$433,FIND("/",'[1]Capex CJI3'!$J$2:$J$433)-1),'[1]Capex CJI3'!$J$2:$J$433)),_xlfn.SWITCH(_xlpm.n,"SAP BELGIUM N","SAP BELGIUM NV","PLANISWARE BELGIUM SR","PLANISWARE BELGIUM SRL","ERNST & YOUNG CONSUL","ERNST & YOUNG CONSULTING","ERNST & YOUNG CONSULTI","ERNST & YOUNG CONSULTING","ERNST & YOUNG CONSULTIN","ERNST & YOUNG CONSULTING","FLEXSO SUPPLY CHAI","FLEXSO SUPPLY CHAIN NV",_xlpm.n))=$B89)*IFERROR(VALUE('[1]Capex CJI3'!$F$2:$F$433),0))-IF(AND($A89="O7941/2517",$B89="ERNST & YOUNG CONSULTING"),'[1]Capex CJI3'!$F$124,0)-IF(AND($A89="O7941/2613",$B89="ERNST & YOUNG CONSULTING"),'[1]Capex CJI3'!$F$313,0)} -> 1565.28 | E89: =C89+D89 -> 1565.28 | F89: {=SUMPRODUCT(('[1]Capex CJI3'!$A$2:$A$433=$A89)*(LEN('[1]Capex CJI3'!$E$2:$E$433)>0)*ISERROR(SEARCH("Reclass internal hours",'[1]Capex CJI3'!$J$2:$J$433))*(_xlfn.LET(_xlpm.n,IF('[1]Capex CJI3'!$J$2:$J$433="","Unknown vendor",IFERROR(LEFT('[1]Capex CJI3'!$J$2:$J$433,FIND("/",'[1]Capex CJI3'!$J$2:$J$433)-1),'[1]Capex CJI3'!$J$2:$J$433)),_xlfn.SWITCH(_xlpm.n,"SAP BELGIUM N","SAP BELGIUM NV","PLANISWARE BELGIUM SR","PLANISWARE BELGIUM SRL","ERNST & YOUNG CONSUL","ERNST & YOUNG CONSULTING","ERNST & YOUNG CONSULTI","ERNST & YOUNG CONSULTING","ERNST & YOUNG CONSULTIN","ERNST & YOUNG CONSULTING","FLEXSO SUPPLY CHAI","FLEXSO SUPPLY CHAIN NV",_xlpm.n))=$B89))-IF(AND($A89="O7941/2517",$B89="ERNST & YOUNG CONSULTING"),1,0)-IF(AND($A89="O7941/2613",$B89="ERNST & YOUNG CONSULTING"),1,0)} -> 1

Sheet Opex Tables
A1: Project ID | B1: 2021 Internal | C1: 2022 Internal | D1: 2023 Internal | E1: 2024 Internal | F1: 2025 Internal | G1: Update Status | H1: Before 2025 Internal Total | I1: 2026 Internal (Through May 31) | J1: 2026 Internal (From Jun 1) | K1: Internal Budget | L1: Internal Total | M1: 2021 External | N1: 2022 External | O1: 2023 External | P1: 2024 External | Q1: 2025 External | R1: Before 2025 Total External | S1: 2026 External | T1: External Budget | U1: External Total | V1: 2021 Invoicing | W1: 2022 Invoicing | X1: 2023 Invoicing | Y1: 2024 Invoicing | Z1: 2025 Invoicing | AA1: 2026 Invoicing | AB1: Invoicing Total | AC1: Total Project Costs | AD1: Net Project Actual | AE1: Total Project Budget | AP1: Project ID | AQ1: Vendor | AR1: 2021 External | AS1: 2022 External | AT1: 2023 External | AU1: 2024 External | AV1: 2025 External | AW1: Before 2026 External Total | AX1: 2026 External | AY1: Total Vendor Spend | AZ1: Update Status
A2: C7941/1896 | B2: 400 | C2: 99584.77 | D2: 12600 | E2: 46200 | F2: 0 | G2: Done | H2: =SUM(B2:F2) -> 158784.77 | I2: 0 | J2: 0 | K2: =_xlfn.LET(_xlpm.x,_xlfn.XLOOKUP(A2&"/2/1",'[1]S_ALR Export'!$O$1:$O$777,'[1]S_ALR Export'!$I$1:$I$777,"",0),IF(_xlpm.x="",0,IF(ISNUMBER(_xlpm.x),_xlpm.x,_xlfn.NUMBERVALUE(_xlpm.x,",",".")))) -> 158785 | L2: =H2+I2+J2 -> 158784.77 | M2: 0 | N2: 40000 | O2: 12245 | P2: 66391.76 | Q2: 1027.8 | R2: =SUM(M2:Q2) -> 119664.56 | S2: 0 | T2: =_xlfn.LET(_xlpm.x,_xlfn.XLOOKUP(A2&"/2/2",'[1]S_ALR Export'!$O$1:$O$777,'[1]S_ALR Export'!$I$1:$I$777,"",0),IF(_xlpm.x="",0,IF(ISNUMBER(_xlpm.x),_xlpm.x,_xlfn.NUMBERVALUE(_xlpm.x,",",".")))) -> 119665 | U2: 119664.56 | V2: 0 | W2: -68000 | X2: -51000 | Y2: -60000 | Z2: 0 | AA2: 0 | AB2: =SUM(V2:AA2) -> -179000 | AC2: =SUM(L2,U2) -> 278449.33 | AD2: =AC2+AB2 -> 99449.33 | AE2: =_xlfn.XLOOKUP(A2,'[1]S_ALR Export'!$O$1:$O$777,'[1]S_ALR Export'!$I$1:$I$777,"",0) -> 278.450,00 | AP2: C7941/1896 | AQ2: eMaint EMEA | AR2: 0 | AS2: 40000 | AT2: 12245 | AU2: 66391.76 | AV2: 1027.8 | AW2: =SUM(AR2:AV2) -> 119664.56 | AX2: 0 | AY2: 119664.56 | AZ2: Done
A3: C7941/2023 | B3: 0 | C3: 400 | D3: 700 | E3: 8150 | F3: 0 | G3: Check | H3: =SUM(B3:F3) -> 9250 | I3: 0 | J3: 0 | K3: =_xlfn.LET(_xlpm.x,_xlfn.XLOOKUP(A3&"/2/1",'[1]S_ALR Export'!$O$1:$O$777,'[1]S_ALR Export'!$I$1:$I$777,"",0),IF(_xlpm.x="",0,IF(ISNUMBER(_xlpm.x),_xlpm.x,_xlfn.NUMBERVALUE(_xlpm.x,",",".")))) -> 70000 | L3: =H3+I3+J3 -> 9250 | M3: 0 | N3: 0 | O3: 0 | P3: 0 | Q3: 0 | R3: =SUM(M3:Q3) -> 0 | S3: 0 | T3: =_xlfn.LET(_xlpm.x,_xlfn.XLOOKUP(A3&"/2/2",'[1]S_ALR Export'!$O$1:$O$777,'[1]S_ALR Export'!$I$1:$I$777,"",0),IF(_xlpm.x="",0,IF(ISNUMBER(_xlpm.x),_xlpm.x,_xlfn.NUMBERVALUE(_xlpm.x,",",".")))) -> 2500 | U3: 0 | V3: 0 | W3: 0 | X3: 0 | Y3: 0 | Z3: 0 | AA3: 0 | AB3: =SUM(V3:AA3) -> 0 | AC3: =SUM(L3,U3) -> 9250 | AD3: =AC3+AB3 -> 9250 | AE3: =_xlfn.XLOOKUP(A3,'[1]S_ALR Export'!$O$1:$O$777,'[1]S_ALR Export'!$I$1:$I$777,"",0) -> 72.500,00 | AP3: C7941/2036 | AQ3: 2036 - France Payroll Project | AR3: 0 | AS3: 0 | AT3: 0 | AU3: 0 | AV3: 87841 | AW3: =SUM(AR3:AV3) -> 87841 | AX3: 0 | AY3: 87841 | AZ3: Done
A4: C7941/2036 | B4: 0 | C4: 0 | D4: 25300 | E4: 15350 | F4: 17450 | G4: Done | H4: =SUM(B4:F4) -> 58100 | I4: 250 | J4: 0 | K4: =_xlfn.LET(_xlpm.x,_xlfn.XLOOKUP(A4&"/2/1",'[1]S_ALR Export'!$O$1:$O$777,'[1]S_ALR Export'!$I$1:$I$777,"",0),IF(_xlpm.x="",0,IF(ISNUMBER(_xlpm.x),_xlpm.x,_xlfn.NUMBERVALUE(_xlpm.x,",",".")))) -> 58350 | L4: =H4+I4+J4 -> 58350 | M4: 0 | N4: 0 | O4: 127330.01 | P4: 121964.62 | Q4: 106748.42 | R4: =SUM(M4:Q4) -> 356043.05 | S4: 0 | T4: =_xlfn.LET(_xlpm.x,_xlfn.XLOOKUP(A4&"/2/2",'[1]S_ALR Export'!$O$1:$O$777,'[1]S_ALR Export'!$I$1:$I$777,"",0),IF(_xlpm.x="",0,IF(ISNUMBER(_xlpm.x),_xlpm.x,_xlfn.NUMBERVALUE(_xlpm.x,",",".")))) -> 356044 | U4: 356043.05 | V4: 0 | W4: 0 | X4: -133757 | Y4: -123547 | Z4: -126420.34 | AA4: 0 | AB4: =SUM(V4:AA4) -> -383724.34 | AC4: =SUM(L4,U4) -> 414393.05 | AD4: =AC4+AB4 -> 30668.71 | AE4: =_xlfn.XLOOKUP(A4,'[1]S_ALR Export'!$O$1:$O$777,'[1]S_ALR Export'!$I$1:$I$777,"",0) -> 414.394,00 | AP4: C7941/2036 | AQ4: Datatune BV | AR4: 0 | AS4: 0 | AT4: 0 | AU4: 0 | AV4: 15333 | AW4: =SUM(AR4:AV4) -> 15333 | AX4: 0 | AY4: 15333 | AZ4: Done
A5: C7941/2130 | B5: 0 | C5: 0 | D5: 0 | E5: 0 | F5: 14100 | G5: Done | H5: =SUM(B5:F5) -> 14100 | I5: 2700 | J5: 0 | K5: =_xlfn.LET(_xlpm.x,_xlfn.XLOOKUP(A5&"/2/1",'[1]S_ALR Export'!$O$1:$O$777,'[1]S_ALR Export'!$I$1:$I$777,"",0),IF(_xlpm.x="",0,IF(ISNUMBER(_xlpm.x),_xlpm.x,_xlfn.NUMBERVALUE(_xlpm.x,",",".")))) -> 40700 | L5: =H5+I5+J5 -> 16800 | M5: 0 | N5: 0 | O5: 0 | P5: 0 | Q5: 0 | R5: =SUM(M5:Q5) -> 0 | S5: 0 | T5: =_xlfn.LET(_xlpm.x,_xlfn.XLOOKUP(A5&"/2/2",'[1]S_ALR Export'!$O$1:$O$777,'[1]S_ALR Export'!$I$1:$I$777,"",0),IF(_xlpm.x="",0,IF(ISNUMBER(_xlpm.x),_xlpm.x,_xlfn.NUMBERVALUE(_xlpm.x,",",".")))) -> 0 | U5: 0 | V5: 0 | W5: 0 | X5: 0 | Y5: 0 | Z5: 0 | AA5: 0 | AB5: =SUM(V5:AA5) -> 0 | AC5: =SUM(L5,U5) -> 16800 | AD5: =AC5+AB5 -> 16800 | AE5: =_xlfn.XLOOKUP(A5,'[1]S_ALR Export'!$O$1:$O$777,'[1]S_ALR Export'!$I$1:$I$777,"",0) -> 40.700,00 | AP5: C7941/2036 | AQ5: Deloitte | AR5: 0 | AS5: 0 | AT5: 17514.99 | AU5: 38964.62 | AV5: 3574.42 | AW5: =SUM(AR5:AV5) -> 60054.03 | AX5: 0 | AY5: 60054.03 | AZ5: Done
A6: C7941/2133 | B6: 0 | C6: 0 | D6: 0 | E6: 6800 | F6: 44000 | G6: Done | H6: =SUM(B6:F6) -> 50800 | I6: 0 | J6: 10799.44 | K6: =_xlfn.LET(_xlpm.x,_xlfn.XLOOKUP(A6&"/2/1",'[1]S_ALR Export'!$O$1:$O$777,'[1]S_ALR Export'!$I$1:$I$777,"",0),IF(_xlpm.x="",0,IF(ISNUMBER(_xlpm.x),_xlpm.x,_xlfn.NUMBERVALUE(_xlpm.x,",",".")))) -> 140900 | L6: =H6+I6+J6 -> 61599.44 | M6: 0 | N6: 0 | O6: 0 | P6: 0 | Q6: 12500 | R6: =SUM(M6:Q6) -> 12500 | S6: 10791.67 | T6: =_xlfn.LET(_xlpm.x,_xlfn.XLOOKUP(A6&"/2/2",'[1]S_ALR Export'!$O$1:$O$777,'[1]S_ALR Export'!$I$1:$I$777,"",0),IF(_xlpm.x="",0,IF(ISNUMBER(_xlpm.x),_xlpm.x,_xlfn.NUMBERVALUE(_xlpm.x,",",".")))) -> 23300 | U6: 23291.67 | V6: 0 | W6: 0 | X6: 0 | Y6: 0 | Z6: 0 | AA6: 0 | AB6: =SUM(V6:AA6) -> 0 | AC6: =SUM(L6,U6) -> 84891.11 | AD6: =AC6+AB6 -> 84891.11 | AE6: =_xlfn.XLOOKUP(A6,'[1]S_ALR Export'!$O$1:$O$777,'[1]S_ALR Export'!$I$1:$I$777,"",0) -> 164.200,00 | AP6: C7941/2036 | AQ6: EPI USE NV | AR6: 0 | AS6: 0 | AT6: 24271.6 | AU6: 0 | AV6: 0 | AW6: =SUM(AR6:AV6) -> 24271.6 | AX6: 0 | AY6: 24271.6 | AZ6: Done
A7: C7941/2134 | B7: 0 | C7: 0 | D7: 0 | E7: 15880 | F7: 9051 | G7: Done | H7: =SUM(B7:F7) -> 24931 | I7: 1350 | J7: 50 | K7: =_xlfn.LET(_xlpm.x,_xlfn.XLOOKUP(A7&"/2/1",'[1]S_ALR Export'!$O$1:$O$777,'[1]S_ALR Export'!$I$1:$I$777,"",0),IF(_xlpm.x="",0,IF(ISNUMBER(_xlpm.x),_xlpm.x,_xlfn.NUMBERVALUE(_xlpm.x,",",".")))) -> 26600 | L7: =H7+I7+J7 -> 26331 | M7: 0 | N7: 0 | O7: 0 | P7: 0 | Q7: 0 | R7: =SUM(M7:Q7) -> 0 | S7: 0 | T7: =_xlfn.LET(_xlpm.x,_xlfn.XLOOKUP(A7&"/2/2",'[1]S_ALR Export'!$O$1:$O$777,'[1]S_ALR Export'!$I$1:$I$777,"",0),IF(_xlpm.x="",0,IF(ISNUMBER(_xlpm.x),_xlpm.x,_xlfn.NUMBERVALUE(_xlpm.x,",",".")))) -> 0 | U7: 0 | V7: 0 | W7: 0 | X7: 0 | Y7: 0 | Z7: 0 | AA7: 0 | AB7: =SUM(V7:AA7) -> 0 | AC7: =SUM(L7,U7) -> 26331 | AD7: =AC7+AB7 -> 26331 | AE7: =_xlfn.XLOOKUP(A7,'[1]S_ALR Export'!$O$1:$O$777,'[1]S_ALR Export'!$I$1:$I$777,"",0) -> 26.600,00 | AP7: C7941/2036 | AQ7: SAP | AR7: 0 | AS7: 0 | AT7: 85543.42 | AU7: 83000 | AV7: 0 | AW7: =SUM(AR7:AV7) -> 168543.42 | AX7: 0 | AY7: 168543.42 | AZ7: Done
A8: C7941/2150 | B8: 0 | C8: 0 | D8: 0 | E8: 1950 | F8: 17160 | G8: Done | H8: =SUM(B8:F8) -> 19110 | I8: 1250 | J8: 0 | K8: =_xlfn.LET(_xlpm.x,_xlfn.XLOOKUP(A8&"/2/1",'[1]S_ALR Export'!$O$1:$O$777,'[1]S_ALR Export'!$I$1:$I$777,"",0),IF(_xlpm.x="",0,IF(ISNUMBER(_xlpm.x),_xlpm.x,_xlfn.NUMBERVALUE(_xlpm.x,",",".")))) -> 20360 | L8: =H8+I8+J8 -> 20360 | M8: 0 | N8: 0 | O8: 0 | P8: 0 | Q8: 0 | R8: =SUM(M8:Q8) -> 0 | S8: 0 | T8: =_xlfn.LET(_xlpm.x,_xlfn.XLOOKUP(A8&"/2/2",'[1]S_ALR Export'!$O$1:$O$777,'[1]S_ALR Export'!$I$1:$I$777,"",0),IF(_xlpm.x="",0,IF(ISNUMBER(_xlpm.x),_xlpm.x,_xlfn.NUMBERVALUE(_xlpm.x,",",".")))) -> 0 | U8: 0 | V8: 0 | W8: 0 | X8: 0 | Y8: 0 | Z8: 0 | AA8: 0 | AB8: =SUM(V8:AA8) -> 0 | AC8: =SUM(L8,U8) -> 20360 | AD8: =AC8+AB8 -> 20360 | AE8: =_xlfn.XLOOKUP(A8,'[1]S_ALR Export'!$O$1:$O$777,'[1]S_ALR Export'!$I$1:$I$777,"",0) -> 20.360,00 | AP8: C7941/2133 | AQ8: Tagetik / CCH | AR8: 0 | AS8: 0 | AT8: 0 | AU8: 0 | AV8: 12500 | AW8: =SUM(AR8:AV8) -> 12500 | AX8: 10791.67 | AY8: 23291.67 | AZ8: Done
A9: C7941/2329 | B9: 0 | C9: 0 | D9: 0 | E9: 0 | F9: 0 | G9: Done | H9: =SUM(B9:F9) -> 0 | I9: 0 | J9: 532.5 | K9: =_xlfn.LET(_xlpm.x,_xlfn.XLOOKUP(A9&"/2/1",'[1]S_ALR Export'!$O$1:$O$777,'[1]S_ALR Export'!$I$1:$I$777,"",0),IF(_xlpm.x="",0,IF(ISNUMBER(_xlpm.x),_xlpm.x,_xlfn.NUMBERVALUE(_xlpm.x,",",".")))) -> 7900 | L9: =H9+I9+J9 -> 532.5 | M9: 0 | N9: 0 | O9: 0 | P9: 0 | Q9: 0 | R9: =SUM(M9:Q9) -> 0 | S9: 0 | T9: =_xlfn.LET(_xlpm.x,_xlfn.XLOOKUP(A9&"/2/2",'[1]S_ALR Export'!$O$1:$O$777,'[1]S_ALR Export'!$I$1:$I$777,"",0),IF(_xlpm.x="",0,IF(ISNUMBER(_xlpm.x),_xlpm.x,_xlfn.NUMBERVALUE(_xlpm.x,",",".")))) -> 0 | U9: 0 | V9: 0 | W9: 0 | X9: 0 | Y9: 0 | Z9: 0 | AA9: 0 | AB9: =SUM(V9:AA9) -> 0 | AC9: =SUM(L9,U9) -> 532.5 | AD9: =AC9+AB9 -> 532.5 | AE9: =_xlfn.XLOOKUP(A9,'[1]S_ALR Export'!$O$1:$O$777,'[1]S_ALR Export'!$I$1:$I$777,"",0) -> 7.900,00 | AP9: C7941/2439 | AQ9: Vonage | AR9: 0 | AS9: 0 | AT9: 0 | AU9: 0 | AV9: 0 | AW9: =SUM(AR9:AV9) -> 0 | AX9: 23800 | AY9: 23800 | AZ9: Done
A10: C7941/2383 | B10: 0 | C10: 0 | D10: 0 | E10: 0 | F10: 0 | G10: Done | H10: =SUM(B10:F10) -> 0 | I10: 0 | J10: 22300 | K10: =_xlfn.LET(_xlpm.x,_xlfn.XLOOKUP(A10&"/2/1",'[1]S_ALR Export'!$O$1:$O$777,'[1]S_ALR Export'!$I$1:$I$777,"",0),IF(_xlpm.x="",0,IF(ISNUMBER(_xlpm.x),_xlpm.x,_xlfn.NUMBERVALUE(_xlpm.x,",",".")))) -> 42600 | L10: =H10+I10+J10 -> 22300 | M10: 0 | N10: 0 | O10: 0 | P10: 0 | Q10: 0 | R10: =SUM(M10:Q10) -> 0 | S10: 0 | T10: =_xlfn.LET(_xlpm.x,_xlfn.XLOOKUP(A10&"/2/2",'[1]S_ALR Export'!$O$1:$O$777,'[1]S_ALR Export'!$I$1:$I$777,"",0),IF(_xlpm.x="",0,IF(ISNUMBER(_xlpm.x),_xlpm.x,_xlfn.NUMBERVALUE(_xlpm.x,",",".")))) -> 0 | U10: 0 | V10: 0 | W10: 0 | X10: 0 | Y10: 0 | Z10: 0 | AA10: 0 | AB10: =SUM(V10:AA10) -> 0 | AC10: =SUM(L10,U10) -> 22300 | AD10: =AC10+AB10 -> 22300 | AE10: =_xlfn.XLOOKUP(A10,'[1]S_ALR Export'!$O$1:$O$777,'[1]S_ALR Export'!$I$1:$I$777,"",0) -> 42.600,00 | AP10: C7941/2567 | AQ10: Alok (SOW 202) | AR10: 0 | AS10: 0 | AT10: 0 | AU10: 63512 | AV10: 0 | AW10: =SUM(AR10:AV10) -> 63512 | AX10: 0 | AY10: 63512 | AZ10: Not Done
A11: C7941/2411 | B11: 0 | C11: 0 | D11: 0 | E11: 0 | F11: 0 | G11: Done | H11: =SUM(B11:F11) -> 0 | I11: 0 | J11: 1400 | K11: =_xlfn.LET(_xlpm.x,_xlfn.XLOOKUP(A11&"/2/1",'[1]S_ALR Export'!$O$1:$O$777,'[1]S_ALR Export'!$I$1:$I$777,"",0),IF(_xlpm.x="",0,IF(ISNUMBER(_xlpm.x),_xlpm.x,_xlfn.NUMBERVALUE(_xlpm.x,",",".")))) -> 2500 | L11: =H11+I11+J11 -> 1400 | M11: 0 | N11: 0 | O11: 0 | P11: 0 | Q11: 0 | R11: =SUM(M11:Q11) -> 0 | S11: 0 | T11: =_xlfn.LET(_xlpm.x,_xlfn.XLOOKUP(A11&"/2/2",'[1]S_ALR Export'!$O$1:$O$777,'[1]S_ALR Export'!$I$1:$I$777,"",0),IF(_xlpm.x="",0,IF(ISNUMBER(_xlpm.x),_xlpm.x,_xlfn.NUMBERVALUE(_xlpm.x,",",".")))) -> 0 | U11: 0 | V11: 0 | W11: 0 | X11: 0 | Y11: 0 | Z11: 0 | AA11: 0 | AB11: =SUM(V11:AA11) -> 0 | AC11: =SUM(L11,U11) -> 1400 | AD11: =AC11+AB11 -> 1400 | AE11: =_xlfn.XLOOKUP(A11,'[1]S_ALR Export'!$O$1:$O$777,'[1]S_ALR Export'!$I$1:$I$777,"",0) -> 2.500,00 | AP11: C7941/2577 | AQ11: Flexso | AR11: 0 | AS11: 0 | AT11: 0 | AU11: 2700 | AV11: 0 | AW11: =SUM(AR11:AV11) -> 2700 | AX11: 0 | AY11: 2700 | AZ11: Done
A12: C7941/2439 | B12: 0 | C12: 0 | D12: 0 | E12: 0 | F12: 0 | G12: Done | H12: =SUM(B12:F12) -> 0 | I12: 0 | J12: 10800 | K12: =_xlfn.LET(_xlpm.x,_xlfn.XLOOKUP(A12&"/2/1",'[1]S_ALR Export'!$O$1:$O$777,'[1]S_ALR Export'!$I$1:$I$777,"",0),IF(_xlpm.x="",0,IF(ISNUMBER(_xlpm.x),_xlpm.x,_xlfn.NUMBERVALUE(_xlpm.x,",",".")))) -> 15532 | L12: =H12+I12+J12 -> 10800 | M12: 0 | N12: 0 | O12: 0 | P12: 0 | Q12: 0 | R12: =SUM(M12:Q12) -> 0 | S12: 23800 | T12: =_xlfn.LET(_xlpm.x,_xlfn.XLOOKUP(A12&"/2/2",'[1]S_ALR Export'!$O$1:$O$777,'[1]S_ALR Export'!$I$1:$I$777,"",0),IF(_xlpm.x="",0,IF(ISNUMBER(_xlpm.x),_xlpm.x,_xlfn.NUMBERVALUE(_xlpm.x,",",".")))) -> 33920 | U12: 23800 | V12: 0 | W12: 0 | X12: 0 | Y12: 0 | Z12: 0 | AA12: -34251 | AB12: =SUM(V12:AA12) -> -34251 | AC12: =SUM(L12,U12) -> 34600 | AD12: =AC12+AB12 -> 349 | AE12: =_xlfn.XLOOKUP(A12,'[1]S_ALR Export'!$O$1:$O$777,'[1]S_ALR Export'!$I$1:$I$777,"",0) -> 49.452,00 | AP12: C7941/2577 | AQ12: TheValueChain | AR12: 0 | AS12: 0 | AT12: 0 | AU12: 19318.75 | AV12: 13921.88 | AW12: =SUM(AR12:AV12) -> 33240.63 | AX12: 0 | AY12: 33240.63 | AZ12: Done
A13: C7941/2567 | B13: 0 | C13: 0 | D13: 0 | E13: 27050 | F13: 135168.75 | G13: Check | H13: =SUM(B13:F13) -> 162218.75 | I13: 27676 | J13: 21236 | K13: =_xlfn.LET(_xlpm.x,_xlfn.XLOOKUP(A13&"/2/1",'[1]S_ALR Export'!$O$1:$O$777,'[1]S_ALR Export'!$I$1:$I$777,"",0),IF(_xlpm.x="",0,IF(ISNUMBER(_xlpm.x),_xlpm.x,_xlfn.NUMBERVALUE(_xlpm.x,",",".")))) -> 283200 | L13: =H13+I13+J13 -> 211130.75 | M13: 0 | N13: 0 | O13: 0 | P13: 63512 | Q13: 0 | R13: =SUM(M13:Q13) -> 63512 | S13: 0 | T13: =_xlfn.LET(_xlpm.x,_xlfn.XLOOKUP(A13&"/2/2",'[1]S_ALR Export'!$O$1:$O$777,'[1]S_ALR Export'!$I$1:$I$777,"",0),IF(_xlpm.x="",0,IF(ISNUMBER(_xlpm.x),_xlpm.x,_xlfn.NUMBERVALUE(_xlpm.x,",",".")))) -> 131700 | U13: 63512 | V13: 0 | W13: 0 | X13: 0 | Y13: 0 | Z13: 0 | AA13: 0 | AB13: =SUM(V13:AA13) -> 0 | AC13: =SUM(L13,U13) -> 274642.75 | AD13: =AC13+AB13 -> 274642.75 | AE13: =_xlfn.XLOOKUP(A13,'[1]S_ALR Export'!$O$1:$O$777,'[1]S_ALR Export'!$I$1:$I$777,"",0) -> 414.900,00 | AP13: C7941/2595 | AQ13: Cognizant | AR13: 0 | AS13: 0 | AT13: 0 | AU13: 0 | AV13: 12567.41 | AW13: =SUM(AR13:AV13) -> 12567.41 | AX13: -202.7 | AY13: 12364.71 | AZ13: Done
... A34: C7941/2669 | B34: 0 | C34: 0 | D34: 0 | E34: 0 | F34: 0 | G34: Done | H34: =SUM(B34:F34) -> 0 | I34: 0 | J34: 0 | K34: =_xlfn.LET(_xlpm.x,_xlfn.XLOOKUP(A34&"/2/1",'[1]S_ALR Export'!$O$1:$O$777,'[1]S_ALR Export'!$I$1:$I$777,"",0),IF(_xlpm.x="",0,IF(ISNUMBER(_xlpm.x),_xlpm.x,_xlfn.NUMBERVALUE(_xlpm.x,",",".")))) -> 40000 | L34: =H34+I34+J34 -> 0 | M34: 0 | N34: 0 | O34: 0 | P34: 0 | Q34: 0 | R34: =SUM(M34:Q34) -> 0 | S34: 0 | T34: =_xlfn.LET(_xlpm.x,_xlfn.XLOOKUP(A34&"/2/2",'[1]S_ALR Export'!$O$1:$O$777,'[1]S_ALR Export'!$I$1:$I$777,"",0),IF(_xlpm.x="",0,IF(ISNUMBER(_xlpm.x),_xlpm.x,_xlfn.NUMBERVALUE(_xlpm.x,",",".")))) -> 40000 | U34: 0 | V34: 0 | W34: 0 | X34: 0 | Y34: 0 | Z34: 0 | AA34: 0 | AB34: =SUM(V34:AA34) -> 0 | AC34: =SUM(L34,U34) -> 0 | AD34: =AC34+AB34 -> 0 | AE34: =_xlfn.XLOOKUP(A34,'[1]S_ALR Export'!$O$1:$O$777,'[1]S_ALR Export'!$I$1:$I$777,"",0) -> 80.000,00 | AP34: C7941/2679 | AQ34: DSR Global | AR34: 0 | AS34: 0 | AT34: 0 | AU34: 0 | AV34: 8338 | AW34: =SUM(AR34:AV34) -> 8338 | AX34: 3450 | AY34: 11788 | AZ34: Done
